Workbook

Sheet consolidated sheet
A1: Sl No | B1: Particulars | C1: Project | N1: HMA HR Revenue | O1: LSGB | P1: Total
C2: HLL Malappuram | D2: Power Grid Corporation of India Limited - Yelahanka, Bangalore | E2: Cochin Shipyard Limited - Andaman | F2: IOCL - Panipat | G2: HLL Cotton Hill, Trivandrum | H2: Swasthya-An innovative behaviour change programme for Aneamia in women of reproductive age | I2: Counselling support for transgender individuals-pre and post surgery and non surgical pathways in gender transition | J2: Inclusive community mental health initiative in Wayanad district | K2: My City | L2: Exploring the correlation and Diagnostic potential of Menstrual Blood | M2: HLL Maharashtra
A3: 1 | B3: HMA Core TeamSalary @5% | C3: ='CORE MANPOWER'!AF4 -> 5007 | D3: ='CORE MANPOWER'!AG4 -> 8409 | E3: ='CORE MANPOWER'!AH4 -> 6250 | F3: ='CORE MANPOWER'!AI4 -> 0 | G3: ='CORE MANPOWER'!AJ4 -> 0 | H3: ='CORE MANPOWER'!AK4 -> 5556 | I3: ='CORE MANPOWER'!AL4 -> 5877 | J3: ='CORE MANPOWER'!AM4 -> 10714 | ... M3: ='CORE MANPOWER'!AP4 -> 0 | N3: 0 | O3: ='CORE MANPOWER'!AQ4 -> 648949.77 | P3: =SUM(C3:O3) -> 690762.77
A4: 2 | B4: HR Expenses @5% | C4: ='JULY 2025 ADMIN EXPENSES'!I9 -> 11200.25 | D4: ='JULY 2025 ADMIN EXPENSES'!J9 -> 11200.25 | E4: ='JULY 2025 ADMIN EXPENSES'!K9 -> 11200.25 | F4: ='JULY 2025 ADMIN EXPENSES'!L9 -> 0 | G4: ='JULY 2025 ADMIN EXPENSES'!M9 -> 0 | H4: ='JULY 2025 ADMIN EXPENSES'!N9 -> 11200.25 | I4: ='JULY 2025 ADMIN EXPENSES'!O9 -> 0 | J4: ='JULY 2025 ADMIN EXPENSES'!P9 -> 0 | ... M4: ='JULY 2025 ADMIN EXPENSES'!S9 -> 0 | N4: 0 | O4: ='JULY 2025 ADMIN EXPENSES'!T9+'JULY 2025 ADMIN EXPENSES'!U9 -> 80759 | P4: =SUM(C4:O4) -> 125560
A5: 3 | B5: HMA Admin Expenses @5% | C5: ='JULY 2025 ADMIN EXPENSES'!W3 -> 0 | D5: ='JULY 2025 ADMIN EXPENSES'!X3 -> 0 | E5: ='JULY 2025 ADMIN EXPENSES'!Y3 -> 0 | F5: ='JULY 2025 ADMIN EXPENSES'!Z3 -> 0 | G5: ='JULY 2025 ADMIN EXPENSES'!AA3 -> 0 | H5: ='JULY 2025 ADMIN EXPENSES'!AB3 -> 0 | I5: ='JULY 2025 ADMIN EXPENSES'!AC3 -> 0 | J5: ='JULY 2025 ADMIN EXPENSES'!AD3 -> 0 | ... N5: ='JULY 2025 ADMIN EXPENSES'!AH3 -> 60000 | O5: ='JULY 2025 ADMIN EXPENSES'!AI11+'JULY 2025 ADMIN EXPENSES'!AI12+'JULY 2025 ADMIN EXPENSES'!AI13+'JULY 2025 ADMIN EXPENSES'!AI14+'JULY 2025 ADMIN EXPENSES'!AI15+'JULY 2025 ADMIN EXPENSES'!AI16+'JULY 2025 ADMIN EXPENSES'!AI17+'JULY 2025 ADMIN EXPENSES'!AI18+'JULY 2025 ADMIN EXPENSES'!AI19+'JULY 2025 ADMIN EXPENSES'!AI20+'JULY 2025 ADMIN EXPENSES'!AI21+'JULY 2025 ADMIN EXPENSES'!AI22+'JULY 2025 ADMIN EXPENSES'!AI23+'JULY 2025 ADMIN EXPENSES'!AI24+'JULY 2025 ADMIN EXPENSES'!AI25+'JULY 2025 ADMIN EXPENSES'!AI26+'JULY 2025 ADMIN EXPENSES'!AI27+'JULY 2025 ADMIN EXPENSES'!AI28 -> 261607 | P5: =SUM(C5:O5) -> 329940.33
A6: TOTAL | C6: =SUM(C3:C5) -> 16207.25 | D6: =SUM(D3:D5) -> 19609.25 | E6: =SUM(E3:E5) -> 17450.25 | F6: =SUM(F3:F5) -> 0 | G6: =SUM(G3:G5) -> 0 | H6: =SUM(H3:H5) -> 16756.25 | I6: =SUM(I3:I5) -> 5877 | J6: =SUM(J3:J5) -> 10714 | ... P6: =SUM(P3:P5) -> 1146263.1
A9: Sl No | B9: Particulars | C9: Project | N9: HMA HR Revenue | O9: LSGB | P9: Total
C10: HLL Malappuram | D10: Power Grid Corporation of India Limited - Yelahanka, Bangalore | E10: Cochin Shipyard Limited - Andaman | F10: IOCL - Panipat | G10: HLL Cotton Hill, Trivandrum | H10: Swasthya-An innovative behaviour change programme for Aneamia in women of reproductive age | I10: Counselling support for transgender individuals-pre and post surgery and non surgical pathways in gender transition | J10: Inclusive community mental health initiative in Wayanad district | K10: My City | L10: Exploring the correlation and Diagnostic potential of Menstrual Blood | M10: HLL Maharashtra
A11: 1 | B11: HMA Core TeamSalary @5% | C11: =C3/P3*100 -> 0.72485087 | D11: =D3/P3*100 -> 1.2173499 | E11: =E3/P3*100 -> 0.90479688 | F11: =F3/P3*100 -> 0 | G11: =G3/P3*100 -> 0 | H11: =H3/P3*100 -> 0.80432823 | I11: =I3/P3*100 -> 0.8507986 | J11: =J3/P3*100 -> 1.551039 | K11: =K3/P3*100 -> 0 | L11: =L3/P3*100 -> 0 | M11: =M3/P3*100 -> 0 | N11: =N3/P3*100 -> 0 | O11: =O3/P3*100 -> 93.946837 | P11: =P3/P3*100 -> 100
A12: 2 | B12: HR Expenses @5% | C12: =C4/P4*100 -> 8.9202373 | D12: =D4/P4*100 -> 8.9202373 | E12: =E4/P4*100 -> 8.9202373 | F12: =F4/P4*100 -> 0 | G12: =G4/P4*100 -> 0 | H12: =H4/P4*100 -> 8.9202373 | I12: =I4/P4*100 -> 0 | J12: =J4/P4*100 -> 0 | K12: =K4/P4*100 -> 0 | L12: =L4/P4*100 -> 0 | M12: =M4/P4*100 -> 0 | N12: =N4/P4*100 -> 0 | O12: =O4/P4*100 -> 64.319051 | P12: =P4/P4*100 -> 100
A13: 3 | B13: HMA Admin Expenses @5% | C13: =C5/P5*100 -> 0 | D13: =D5/P5*100 -> 0 | E13: =E5/P5*100 -> 0 | F13: =F5/P5*100 -> 0 | G13: =G5/P5*100 -> 0 | H13: =H5/P5*100 -> 0 | I13: =I5/P5*100 -> 0 | J13: =J5/P5*100 -> 0 | K13: =K5/P5*100 -> 2.5257092 | L13: =L5/P5*100 -> 0 | M13: =M5/P5*100 -> 0 | N13: =N5/P5*100 -> 18.185106 | O13: =O5/P5*100 -> 79.289185 | P13: =P5/P5*100 -> 100
A14: TOTAL | C14: =C6/P6*100 -> 1.4139206 | D14: =D6/P6*100 -> 1.7107111 | E14: =E6/P6*100 -> 1.5223599 | F14: =F6/P6*100 -> 0 | G14: =G6/P6*100 -> 0 | H14: =H6/P6*100 -> 1.4618153 | I14: =I6/P6*100 -> 0.51270951 | J14: =J6/P6*100 -> 0.93468942 | K14: =K6/P6*100 -> 0.72700005 | L14: =L6/P6*100 -> 0 | M14: =M6/P6*100 -> 0 | N14: =N6/P6*100 -> 5.2344003 | O14: =O6/P6*100 -> 86.482394 | P14: =P6/P6*100 -> 100

Sheet HMA HR REVNUE SHEET
A1: Sl No | B1: HMA HR REVENUE | C1: 45407 | D1: 45772 | E1: 45437 | F1: 45802 | G1: 45468 | H1: 45833 | I1: 45474 | J1: 45839 | K1: 45505 | L1: 45870 | M1: 45536 | N1: 45901 | O1: 45566 | P1: 45931 | Q1: 45597 | R1: 45962 | S1: 45627 | T1: 45992 | U1: 45658 | V1: 46023 | W1: 45689 | X1: 46054 | Y1: 45717 | Z1: 46082
A2: 1 | B2: INTERNSHIP/ST INT | C2: =37760 -> 37760 | D2: =116230+15000 -> 131230 | E2: =132160+9440 -> 141600 | F2: 234230 | G2: 24190 | H2: 187620 | I2: 129210 | J2: 60000 | K2: 51520 | L2: 30680 | N2: 0 | Q2: =97070+32640 -> 129710 | S2: 10 | W2: 100300 | Y2: =111790+143823 -> 255613
A3: 2 | B3: TRAINING | C3: 23319 | D3: 258703 | E3: 38513 | G3: 133955 | H3: 60386 | I3: 23107 | J3: 0 | K3: 96659 | M3: 52380 | N3: 0 | O3: 23850 | S3: 534598 | U3: 18711 | W3: 170190 | Y3: 296964
A4: 3 | B4: RECRUITMENT | C4: 1928773 | D4: 263698 | F4: 19435 | H4: 161264 | L4: 393088 | N4: 0 | O4: 2014000 | S4: 3370919 | Y4: =93709+61803+3754+19329+2528189 -> 2706784
A5: 4 | B5: HALL RENT | N5: 0
A6: Total | C6: =SUM(C2:C5) -> 1989852 | D6: =SUM(D2:D5) -> 653631 | E6: =SUM(E2:E5) -> 180113 | F6: =SUM(F2:F5) -> 253665 | G6: =SUM(G2:G5) -> 158145 | H6: =SUM(H2:H5) -> 409270 | I6: =SUM(I2:I5) -> 152317 | J6: =SUM(J2:J5) -> 60000 | ... Z6: =SUM(Z2:Z5) -> 0
S8: KSBCDC-3370919 | Y8: KSBCDC-2528189

Sheet admin Sheet2
A1: LSGB | G1: JUNE
A2: 1 | B2: Manjith Travels | C2: Contract Vehicle | D2: Monthly | E2: 524160 | F2: =E2/12 -> 43680
A3: 5 | B3: Dr Anandam | C3: House Rent | D3: Monthly | E3: 1800000 | F3: =E3/12 -> 150000
A4: 8 | B4: BSNL | C4: Land Line | D4: Monthly | E4: 24000 | F4: =E4/12 -> 2000 | G4: admin
A5: 11 | B5: KSEB | C5: Electricity Bill | D5: Monthly | E5: 264000 | F5: =E5/12 -> 22000
A6: 12 | B6: KWA | C6: Water Bill | D6: Monthly | E6: 96000 | F6: =E6/12 -> 8000
A7: 14 | B7: Subramania Industries | C7: DG AMC | D7: Half Yearly | E7: 10000 | F7: =E7/12 -> 833.33333
A8: 13 | B8: Imprest | C8: Monthly Imprest | D8: Monthly | E8: 120000 | F8: =E8/12 -> 10000
A9: 15 | B9: Alchemy IBS | C9: Website | D9: Monthly | E9: 200000 | F9: =E9/12 -> 16666.667
A10: 16 | B10: Geejey Solutions | C10: Epabx AMC | D10: Half Yearly | E10: 8000 | F10: =E10/12 -> 666.66667
A11: 17 | B11: VRS infosystems | C11: Tally Software Renewal | D11: Annualy | E11: 16000 | F11: =E11/12 -> 1333.3333
A12: 18 | B12: M/sArmtech Computer Services | C12: CAMC computer hardware | D12: Quarterly | E12: 15000 | F12: =E12/12 -> 1250
A13: 19 | B13: Nu aire | C13: AC AMC | D13: Quarterly | E13: 36000 | F13: =E13/12 -> 3000
A14: 20 | B14: Miscellaneous | C14: Repair & Maintenance | D14: Monthly | E14: 50000 | F14: =E14/12 -> 4166.6667
A15: 21 | B15: Microsoft 365 | C15: Software | D15: Annualy | E15: 7000 | F15: =E15/12 -> 583.33333
A16: 2 | B16: Asterisk | C16: Photocopier (Admin & DVP) | D16: Monthly | E16: 48000 | F16: =E16/12 -> 4000
A17: 9 | B17: Pradeep Kumar Cost Accountant | C17: Financial Consultant | D17: Monthly | E17: 1296000 | F17: =E17/12 -> 108000
A18: 10 | B18: Pradeep Kumar Cost Accountant | C18: Accounts Assistance | D18: Monthly | E18: 750000 | F18: =E18/12 -> 62500 | I18: PROJECT 1
A19: 7 | B19: Indian Postal Department | C19: Speed post | D19: Monthly | E19: 120000 | F19: =E19/12 -> 10000 | H19: HR 5% OF CSR | I19: 29545
G20: 520400 | H20: ADMIN CHARGES CSR | I20: 29545
A21: =SUM(F1:F27) -> 580746 | H21: HMA HR REVENUE
A22: HR 5% OF CSR | G22: project-1 | H22: project-2 | I22: project-3
A23: 1 | B23: Manjith Travels | C23: Contract Vehicle | D23: Monthly | E23: 524160 | F23: =E23/12 -> 43680 | G23: =G29*F23/F29 -> 8676.8134
A24: 3 | B24: Oval Blue Technologies | C24: Photocopier SDP | D24: Monthly | E24: 84000 | F24: =E24/12 -> 7000 | G24: =G29*F24/F29 -> 1390.515
A25: 4 | B25: Volks Electronics | C25: Desktop rental | D25: Monthly | E25: 720000 | F25: =E25/12 -> 60000 | G25: =G29*F25/F29 -> 11918.7
A26: 6 | B26: Asianet | C26: Internet Services | D26: Quarterly | E26: 56640 | F26: =E26/12 -> 4720 | G26: =F26*G29/F29 -> 937.60438
B27: Stationary | C27: project documentation | E27: 200000 | F27: 16666 | G27: =F27*G29/F29 -> 3310.6175
A28: 15 | B28: Alchemy IBS | C28: Website | D28: Monthly | E28: 200000 | F28: =E28/12 -> 16666.667 | G28: =F28*G29/F29 -> 3310.7499
F29: =SUM(F23:F28) -> 148732.67 | G29: 29545
A30: Admin Expenses OF CSR @ 5%
A31: 1 | B31: Manjith Travels | C31: Contract Vehicle | D31: Monthly | E31: 524160 | F31: =E31/12 -> 43680
A32: 5 | B32: Dr Anandam | C32: House Rent | D32: Monthly | E32: 1800000 | F32: =E32/12 -> 150000
A33: 8 | B33: BSNL | C33: Land Line | D33: Monthly | E33: 24000 | F33: =E33/12 -> 2000
A34: 11 | B34: KSEB | C34: Electricity Bill | D34: Monthly | E34: 264000 | F34: =E34/12 -> 22000
A35: 12 | B35: KWA | C35: Water Bill | D35: Monthly | E35: 96000 | F35: =E35/12 -> 8000
A36: 14 | B36: Subramania Industries | C36: DG AMC | D36: Half Yearly | E36: 10000 | F36: =E36/12 -> 833.33333
A37: 13 | B37: Imprest | C37: Monthly Imprest | D37: Monthly | E37: 120000 | F37: =E37/12 -> 10000
A38: 15 | B38: Alchemy IBS | C38: Website | D38: Monthly | E38: 200000 | F38: =E38/12 -> 16666.667
A39: 16 | B39: Geejey Solutions | C39: Epabx AMC | D39: Half Yearly | E39: 8000 | F39: =E39/12 -> 666.66667
A40: 17 | B40: VRS infosystems | C40: Tally Software Renewal | D40: Annualy | E40: 16000 | F40: =E40/12 -> 1333.3333
A41: 18 | B41: M/sArmtech Computer Services | C41: CAMC computer hardware | D41: Quarterly | E41: 15000 | F41: =E41/12 -> 1250
A42: 19 | B42: Nu aire | C42: AC AMC | D42: Quarterly | E42: 36000 | F42: =E42/12 -> 3000
... A48: 7 | B48: Indian Postal Department | C48: Speed post | D48: Monthly | E48: 120000 | F48: =E48/12 -> 10000
B50: HMA HR REVENUE | C50: JUNE | D50: JULY | E50: AUGUST | F50: SEPTEMBER | G50: OCTOBER
B51: OPENING BALANCE AS ON 01ST OF EVERY MONTH | C51: 5600000
B52: COMMITED
A53: 1 | B53: INTERNSHIP/ST INT | C53: 150000
A54: 3 | B54: TRAINING | C54: 150000
A55: 4 | B55: RECRUITMENT | C55: 250000
A56: 5 | B56: HALL RENT
C57: =SUM(C51:C56) -> 6150000
C58: =C57*5% -> 307500
A59: 13 | B59: Imprest | C59: Monthly Imprest | D59: Monthly | E59: 120000 | F59: =E59/12 -> 10000
A60: 2 | B60: Asterisk | C60: Photocopier (Admin & DVP) | D60: Monthly | E60: 48000 | F60: =E60/12 -> 4000
A61: 1 | B61: Manjith Travels | C61: Contract Vehicle | D61: Monthly | E61: 524160 | F61: =E61/12 -> 43680
A64: DO PERCENTAGE FOR BOOKING PURPOSE
A65: Admin expense booking
A66: 1 | B66: Manjith Travels | C66: Contract Vehicle | D66: Monthly | E66: 524160 | F66: =E66/12 -> 43680
A67: 5 | B67: Dr Anandam | C67: House Rent | D67: Monthly | E67: 1800000 | F67: =E67/12 -> 150000
A68: 8 | B68: BSNL | C68: Land Line | D68: Monthly | E68: 24000 | F68: =E68/12 -> 2000
A69: 11 | B69: KSEB | C69: Electricity Bill | D69: Monthly | E69: 264000 | F69: =E69/12 -> 22000
A70: 12 | B70: KWA | C70: Water Bill | D70: Monthly | E70: 96000 | F70: =E70/12 -> 8000
A71: 14 | B71: Subramania Industries | C71: DG AMC | D71: Half Yearly | E71: 10000 | F71: =E71/12 -> 833.33333
A72: 13 | B72: Imprest | C72: Monthly Imprest | D72: Monthly | E72: 120000 | F72: =E72/12 -> 10000
A73: 15 | B73: Alchemy IBS | C73: Website | D73: Monthly | E73: 200000 | F73: =E73/12 -> 16666.667
A74: 16 | B74: Geejey Solutions | C74: Epabx AMC | D74: Half Yearly | E74: 8000 | F74: =E74/12 -> 666.66667
A75: 17 | B75: VRS infosystems | C75: Tally Software Renewal | D75: Annualy | E75: 16000 | F75: =E75/12 -> 1333.3333
A76: 18 | B76: M/sArmtech Computer Services | C76: CAMC computer hardware | D76: Quarterly | E76: 15000 | F76: =E76/12 -> 1250
A77: 19 | B77: Nu aire | C77: AC AMC | D77: Quarterly | E77: 36000 | F77: =E77/12 -> 3000
... A83: 7 | B83: Indian Postal Department | C83: Speed post | D83: Monthly | E83: 120000 | F83: =E83/12 -> 10000

Sheet admin Sheet3
A1: 682066 | B1: Project 1 | C1: Project 2 | D1: Project 3 | E1: Project 4 | F1: Project 5 | G1: Project 6 | H1: Total | K1: HMA HR REVENUE
A2: 5% of project | B2: 30000 | C2: 30000 | D2: 30000 | H2: =SUM(B2:G2) -> 90000 | J2: OB | K2: 2500000
A3: Total admin charges monthly actual reciept basis | B3: 20000 | C3: 10000 | D3: 3000 | H3: =SUM(B3:G3) -> 33000 | J3: internship | K3: 100000
A4: Total monthly HR revenue | H4: =K7 -> 165000 | J4: training | K4: 0
A5: balance lsgb | J5: recruitment | K5: 50000
J6: hall rent | K6: 15000
J7: TOTAL | K7: =SUM(K3:K6) -> 165000
K9: PROJECT ADMIN CHARGES
A10: Every month the expenses will be booked for the reciept amount and any balance amount if any shall be booked from lsgb | J10: OB | K10: 1500000
I11: JULY | J11: RECEIVED | K11: 33000
J13: TOTAL | K13: =SUM(K10:K12) -> 1533000
J14: 5% OF TOTAL | K14: =K13*5% -> 76650

Sheet responsiblity
A1: Master sheets | B1: Status | C1: Responsiblity
A2: Core team member Sheet | B2: completed | C2: Nikhil
A3: Sheet Updation | C3: Anakha Joy/Vishnu
A4: Cross Verify | C4: Nikhil
A5: Consolidated Sheet | C5: Nikhil
A6: Over view | C6: Nikhil /Savitha
A7: Project Wise Financial | C7: Arjuna/Rasna
A8: Project Wise Financial cross verify | C8: Arathy
A10: PROJECT SPECIFIC STAFF
A11: Project specific sheet | B11: completed | C11: Nikhil
A12: Sheet Updation | C12: Anakha Joy/Vishnu
A13: Cross Verify | C13: Nikhil
A14: Consolidated Sheet | C14: Nikhil
A17: CSR @ 5%

Sheet MANPOWER
F1: 45748 | H1: 45778 | K1: 45809 | M1: 45839 | O1: 45870 | Q1: 45901 | S1: 45931 | U1: 45962 | W1: 45992 | Y1: 46023 | AA1: 46054 | AC1: 46082
A2: SL No | B2: Name | C2: Designation | D2: Project | E2: Monthly CTC | F2: Attendance | G2: Amount | H2: Attendance2 | I2: Amount3 | J2: Amount4 | K2: Attendance3 | L2: Amount2 | M2: Attendance6 | N2: Amount7 | O2: Attendance8 | P2: Amount9 | Q2: Attendance10 | R2: Amount11 | S2: Attendance12 | T2: Amount13 | U2: Attendance14 | V2: Amount15 | W2: Attendance16 | X2: Amount17 | Y2: Attendance18 | Z2: Amount19 | AA2: Attendance20 | AB2: Amount21 | AC2: Attendance22 | AD2: Amount23
A3: 6 | B3: Gayatri Vijay L | C3: Field Assistant | D3: CORE TEAM | E3: 21367 | F3: 28 | G3: =MANPOWER!$E3/30*MANPOWER!$F3 -> 19942.533 | H3: 29 | I3: =MANPOWER!$E3/31*MANPOWER!$H3 -> 19988.484 | J3: =MANPOWER!$E3-MANPOWER!$I3 -> 1378.5161 | L3: =MANPOWER!$E$3:$E$56 -> 21367 | N3: =MANPOWER!$E$3:$E$56 -> 21367 | P3: =MANPOWER!$E$3:$E$56 -> 21367 | R3: =MANPOWER!$E$3:$E$56 -> 21367 | T3: =MANPOWER!$E$3:$E$56 -> 21367 | V3: =MANPOWER!$E$3:$E$56 -> 21367 | X3: =MANPOWER!$E$3:$E$56 -> 21367 | Z3: =MANPOWER!$E$3:$E$56 -> 21367 | AB3: =MANPOWER!$E$3:$E$56 -> 21367 | AD3: =MANPOWER!$E$3:$E$56 -> 21367
A4: 43 | B4: Vishnu | C4: Field Assistant | D4: LSGB | E4: 21367 | F4: 0 | G4: =MANPOWER!$E4/30*MANPOWER!$F4 -> 0 | H4: 19 | I4: =MANPOWER!$E4/31*MANPOWER!$H4 -> 13095.903 | J4: =MANPOWER!$E4-MANPOWER!$I4 -> 8271.0968 | L4: =MANPOWER!$E$3:$E$56 -> 21367 | N4: =MANPOWER!$E$3:$E$56 -> 21367 | P4: =MANPOWER!$E$3:$E$56 -> 21367 | R4: =MANPOWER!$E$3:$E$56 -> 21367 | T4: =MANPOWER!$E$3:$E$56 -> 21367 | V4: =MANPOWER!$E$3:$E$56 -> 21367 | X4: =MANPOWER!$E$3:$E$56 -> 21367 | Z4: =MANPOWER!$E$3:$E$56 -> 21367 | AB4: =MANPOWER!$E$3:$E$56 -> 21367 | AD4: =MANPOWER!$E$3:$E$56 -> 21367
A5: 49 | B5: Anakha Joy | C5: Field Assistant | E5: 21367 | F5: 0 | G5: =MANPOWER!$E5/30*MANPOWER!$F5 -> 0 | H5: 0 | I5: =MANPOWER!$E5/31*MANPOWER!$H5 -> 0 | J5: =MANPOWER!$E5-MANPOWER!$I5 -> 21367 | L5: =MANPOWER!$E$3:$E$56 -> 21367 | N5: =MANPOWER!$E$3:$E$56 -> 21367 | P5: =MANPOWER!$E$3:$E$56 -> 21367 | R5: =MANPOWER!$E$3:$E$56 -> 21367 | T5: =MANPOWER!$E$3:$E$56 -> 21367 | V5: =MANPOWER!$E$3:$E$56 -> 21367 | X5: =MANPOWER!$E$3:$E$56 -> 21367 | Z5: =MANPOWER!$E$3:$E$56 -> 21367 | AB5: =MANPOWER!$E$3:$E$56 -> 21367 | AD5: =MANPOWER!$E$3:$E$56 -> 21367
A6: 37 | B6: Jeena Raju | C6: Cleaning staff | D6: HLL My city | E6: 22348 | F6: 27 | G6: 22348 | H6: 25 | I6: 21488 | J6: =MANPOWER!$E6-MANPOWER!$I6 -> 860 | L6: =MANPOWER!$E$3:$E$56 -> 22348 | N6: =MANPOWER!$E$3:$E$56 -> 22348 | P6: =MANPOWER!$E$3:$E$56 -> 22348 | R6: =MANPOWER!$E$3:$E$56 -> 22348 | T6: =MANPOWER!$E$3:$E$56 -> 22348 | V6: =MANPOWER!$E$3:$E$56 -> 22348 | X6: =MANPOWER!$E$3:$E$56 -> 22348 | Z6: =MANPOWER!$E$3:$E$56 -> 22348 | AB6: =MANPOWER!$E$3:$E$56 -> 22348 | AD6: =MANPOWER!$E$3:$E$56 -> 22348
A7: 38 | B7: Sujitha S | C7: Cleaning staff | D7: HLL My city | E7: 22348 | F7: 20 | G7: 17191 | H7: 24 | I7: 20629 | J7: =MANPOWER!$E7-MANPOWER!$I7 -> 1719 | L7: =MANPOWER!$E$3:$E$56 -> 22348 | N7: =MANPOWER!$E$3:$E$56 -> 22348 | P7: =MANPOWER!$E$3:$E$56 -> 22348 | R7: =MANPOWER!$E$3:$E$56 -> 22348 | T7: =MANPOWER!$E$3:$E$56 -> 22348 | V7: =MANPOWER!$E$3:$E$56 -> 22348 | X7: =MANPOWER!$E$3:$E$56 -> 22348 | Z7: =MANPOWER!$E$3:$E$56 -> 22348 | AB7: =MANPOWER!$E$3:$E$56 -> 22348 | AD7: =MANPOWER!$E$3:$E$56 -> 22348
A8: 39 | B8: Sudheesh | C8: Cleaning staff | D8: HLL My city | E8: 22348 | F8: 19 | G8: 16331 | H8: 0 | I8: =MANPOWER!$E8/31*MANPOWER!$H8 -> 0 | J8: =MANPOWER!$E8-MANPOWER!$I8 -> 22348
B9: Sukumaran | C9: Cleaning staff | D9: HLL My city | E9: 22348 | F9: 0 | G9: =MANPOWER!$E9/30*MANPOWER!$F9 -> 0 | H9: 18 | I9: 15472 | J9: =MANPOWER!$E9-MANPOWER!$I9 -> 6876 | L9: =MANPOWER!$E$3:$E$56 -> 22348 | N9: =MANPOWER!$E$3:$E$56 -> 22348 | P9: =MANPOWER!$E$3:$E$56 -> 22348 | R9: =MANPOWER!$E$3:$E$56 -> 22348 | T9: =MANPOWER!$E$3:$E$56 -> 22348 | V9: =MANPOWER!$E$3:$E$56 -> 22348 | X9: =MANPOWER!$E$3:$E$56 -> 22348 | Z9: =MANPOWER!$E$3:$E$56 -> 22348 | AB9: =MANPOWER!$E$3:$E$56 -> 22348 | AD9: =MANPOWER!$E$3:$E$56 -> 22348
A10: 5 | B10: Soumya S K | C10: Field Assistant | D10: CORE TEAM | E10: 22689 | F10: 28.5 | G10: =MANPOWER!$E10/30*MANPOWER!$F10 -> 21554.55 | H10: 30 | I10: =MANPOWER!$E10/31*MANPOWER!$H10 -> 21957.097 | J10: =MANPOWER!$E10-MANPOWER!$I10 -> 731.90323 | L10: =MANPOWER!$E$3:$E$56 -> 22689 | N10: =MANPOWER!$E$3:$E$56 -> 22689 | P10: =MANPOWER!$E$3:$E$56 -> 22689 | R10: =MANPOWER!$E$3:$E$56 -> 22689 | T10: =MANPOWER!$E$3:$E$56 -> 22689 | V10: =MANPOWER!$E$3:$E$56 -> 22689 | X10: =MANPOWER!$E$3:$E$56 -> 22689 | Z10: =MANPOWER!$E$3:$E$56 -> 22689 | AB10: =MANPOWER!$E$3:$E$56 -> 22689 | AD10: =MANPOWER!$E$3:$E$56 -> 22689
A11: 7 | B11: Vignesh Kumar P B | C11: Office Assistant | D11: CORE TEAM | E11: 22689 | F11: 30 | G11: =MANPOWER!$E11/30*MANPOWER!$F11 -> 22689 | H11: 31 | I11: =MANPOWER!$E11/31*MANPOWER!$H11 -> 22689 | J11: =MANPOWER!$E11-MANPOWER!$I11 -> 0 | L11: =MANPOWER!$E$3:$E$56 -> 22689 | N11: =MANPOWER!$E$3:$E$56 -> 22689 | P11: =MANPOWER!$E$3:$E$56 -> 22689 | R11: =MANPOWER!$E$3:$E$56 -> 22689 | T11: =MANPOWER!$E$3:$E$56 -> 22689 | V11: =MANPOWER!$E$3:$E$56 -> 22689 | X11: =MANPOWER!$E$3:$E$56 -> 22689 | Z11: =MANPOWER!$E$3:$E$56 -> 22689 | AB11: =MANPOWER!$E$3:$E$56 -> 22689 | AD11: =MANPOWER!$E$3:$E$56 -> 22689
A12: 3 | B12: Ashitha Vins V M | C12: Backend Support | D12: CORE TEAM | E12: 23309 | F12: 30 | G12: =MANPOWER!$E12/30*MANPOWER!$F12 -> 23309 | H12: 31 | I12: =MANPOWER!$E12/31*MANPOWER!$H12 -> 23309 | J12: =MANPOWER!$E12-MANPOWER!$I12 -> 0 | L12: =MANPOWER!$E$3:$E$56 -> 23309 | N12: =MANPOWER!$E$3:$E$56 -> 23309 | P12: =MANPOWER!$E$3:$E$56 -> 23309 | R12: =MANPOWER!$E$3:$E$56 -> 23309 | T12: =MANPOWER!$E$3:$E$56 -> 23309 | V12: =MANPOWER!$E$3:$E$56 -> 23309 | X12: =MANPOWER!$E$3:$E$56 -> 23309 | Z12: =MANPOWER!$E$3:$E$56 -> 23309 | AB12: =MANPOWER!$E$3:$E$56 -> 23309 | AD12: =MANPOWER!$E$3:$E$56 -> 23309
A13: 4 | B13: Savitha Y | C13: Backend Support | D13: CORE TEAM | E13: 23309 | F13: 30 | G13: =MANPOWER!$E13/30*MANPOWER!$F13 -> 23309 | H13: 31 | I13: =MANPOWER!$E13/31*MANPOWER!$H13 -> 23309 | J13: =MANPOWER!$E13-MANPOWER!$I13 -> 0 | L13: =MANPOWER!$E$3:$E$56 -> 23309 | N13: =MANPOWER!$E$3:$E$56 -> 23309 | P13: =MANPOWER!$E$3:$E$56 -> 23309 | R13: =MANPOWER!$E$3:$E$56 -> 23309 | T13: =MANPOWER!$E$3:$E$56 -> 23309 | V13: =MANPOWER!$E$3:$E$56 -> 23309 | X13: =MANPOWER!$E$3:$E$56 -> 23309 | Z13: =MANPOWER!$E$3:$E$56 -> 23309 | AB13: =MANPOWER!$E$3:$E$56 -> 23309 | AD13: =MANPOWER!$E$3:$E$56 -> 23309
A14: 41 | B14: Silpa | C14: Accounts Assistant | D14: Finance | E14: 24508 | F14: 10 | G14: =MANPOWER!$E14/30*MANPOWER!$F14 -> 8169.3333 | H14: 30 | I14: =MANPOWER!$E14/31*MANPOWER!$H14 -> 23717.419 | J14: =MANPOWER!$E14-MANPOWER!$I14 -> 790.58065 | L14: =MANPOWER!$E$3:$E$56 -> 24508 | N14: =MANPOWER!$E$3:$E$56 -> 24508 | P14: =MANPOWER!$E$3:$E$56 -> 24508 | R14: =MANPOWER!$E$3:$E$56 -> 24508 | T14: =MANPOWER!$E$3:$E$56 -> 24508 | V14: =MANPOWER!$E$3:$E$56 -> 24508 | X14: =MANPOWER!$E$3:$E$56 -> 24508 | Z14: =MANPOWER!$E$3:$E$56 -> 24508 | AB14: =MANPOWER!$E$3:$E$56 -> 24508 | AD14: =MANPOWER!$E$3:$E$56 -> 24508
A15: 44 | B15: Preethima | C15: Project Assistant | D15: CSL, Andaman | E15: 24508 | F15: 0 | G15: =MANPOWER!$E15/30*MANPOWER!$F15 -> 0 | H15: 0 | I15: =MANPOWER!$E15/31*MANPOWER!$H15 -> 0 | J15: =MANPOWER!$E15-MANPOWER!$I15 -> 24508 | L15: =MANPOWER!$E$3:$E$56 -> 24508 | N15: =MANPOWER!$E$3:$E$56 -> 24508 | P15: =MANPOWER!$E$3:$E$56 -> 24508 | R15: =MANPOWER!$E$3:$E$56 -> 24508 | T15: =MANPOWER!$E$3:$E$56 -> 24508 | V15: =MANPOWER!$E$3:$E$56 -> 24508 | X15: =MANPOWER!$E$3:$E$56 -> 24508 | Z15: =MANPOWER!$E$3:$E$56 -> 24508 | AB15: =MANPOWER!$E$3:$E$56 -> 24508 | AD15: =MANPOWER!$E$3:$E$56 -> 24508
A16: 48 | B16: Sakshi Baliram Savare | C16: Project Assistant | D16: HLL CSR MAHARASHTRA | E16: 24508 | F16: 0 | G16: =MANPOWER!$E16/30*MANPOWER!$F16 -> 0 | H16: 6 | I16: =MANPOWER!$E16/31*MANPOWER!$H16 -> 4743.4839 | J16: =MANPOWER!$E16-MANPOWER!$I16 -> 19764.516 | L16: =MANPOWER!$E$3:$E$56 -> 24508 | N16: =MANPOWER!$E$3:$E$56 -> 24508 | P16: =MANPOWER!$E$3:$E$56 -> 24508 | R16: =MANPOWER!$E$3:$E$56 -> 24508 | T16: =MANPOWER!$E$3:$E$56 -> 24508 | V16: =MANPOWER!$E$3:$E$56 -> 24508 | X16: =MANPOWER!$E$3:$E$56 -> 24508 | Z16: =MANPOWER!$E$3:$E$56 -> 24508 | AB16: =MANPOWER!$E$3:$E$56 -> 24508 | AD16: =MANPOWER!$E$3:$E$56 -> 24508
A17: 50 | B17: Rakhee | C17: Project Assistant | D17: CSL, Andaman | E17: 24508 | F17: 0 | G17: =MANPOWER!$E17/30*MANPOWER!$F17 -> 0 | H17: 0 | I17: =MANPOWER!$E17/31*MANPOWER!$H17 -> 0 | J17: =MANPOWER!$E17-MANPOWER!$I17 -> 24508 | L17: =MANPOWER!$E$3:$E$56 -> 24508 | N17: =MANPOWER!$E$3:$E$56 -> 24508 | P17: =MANPOWER!$E$3:$E$56 -> 24508 | R17: =MANPOWER!$E$3:$E$56 -> 24508 | T17: =MANPOWER!$E$3:$E$56 -> 24508 | V17: =MANPOWER!$E$3:$E$56 -> 24508 | X17: =MANPOWER!$E$3:$E$56 -> 24508 | Z17: =MANPOWER!$E$3:$E$56 -> 24508 | AB17: =MANPOWER!$E$3:$E$56 -> 24508 | AD17: =MANPOWER!$E$3:$E$56 -> 24508
A18: 11 | B18: Jayalekshmi J | C18: Project Assistant | D18: LSGB | E18: 24509 | F18: 30 | G18: =MANPOWER!$E18/30*MANPOWER!$F18 -> 24509 | H18: 31 | I18: =MANPOWER!$E18/31*MANPOWER!$H18 -> 24509 | J18: =MANPOWER!$E18-MANPOWER!$I18 -> 0 | L18: =MANPOWER!$E$3:$E$56 -> 24509 | N18: =MANPOWER!$E$3:$E$56 -> 24509 | P18: =MANPOWER!$E$3:$E$56 -> 24509 | R18: =MANPOWER!$E$3:$E$56 -> 24509 | T18: =MANPOWER!$E$3:$E$56 -> 24509 | V18: =MANPOWER!$E$3:$E$56 -> 24509 | X18: =MANPOWER!$E$3:$E$56 -> 24509 | Z18: =MANPOWER!$E$3:$E$56 -> 24509 | AB18: =MANPOWER!$E$3:$E$56 -> 24509 | AD18: =MANPOWER!$E$3:$E$56 -> 24509
A19: 10 | B19: Sushila | C19: Project Assistant | D19: IOCL Panipat , Haryana | E19: 24523 | F19: 30 | G19: =MANPOWER!$E19/30*MANPOWER!$F19 -> 24523 | H19: 31 | I19: =MANPOWER!$E19/31*MANPOWER!$H19 -> 24523 | J19: =MANPOWER!$E19-MANPOWER!$I19 -> 0 | L19: =MANPOWER!$E$3:$E$56 -> 24523 | N19: =MANPOWER!$E$3:$E$56 -> 24523 | P19: =MANPOWER!$E$3:$E$56 -> 24523 | R19: =MANPOWER!$E$3:$E$56 -> 24523 | T19: =MANPOWER!$E$3:$E$56 -> 24523 | V19: =MANPOWER!$E$3:$E$56 -> 24523 | X19: =MANPOWER!$E$3:$E$56 -> 24523 | Z19: =MANPOWER!$E$3:$E$56 -> 24523 | AB19: =MANPOWER!$E$3:$E$56 -> 24523 | AD19: =MANPOWER!$E$3:$E$56 -> 24523
A20: 40 | B20: Syamili | C20: Admistrative Assistant (Projects) | D20: Consultancy Projects | E20: 25317 | F20: 24 | G20: =MANPOWER!$E20/30*MANPOWER!$F20 -> 20253.6 | H20: 31 | I20: =MANPOWER!$E20/31*MANPOWER!$H20 -> 25317 | J20: =MANPOWER!$E20-MANPOWER!$I20 -> 0 | L20: =MANPOWER!$E$3:$E$56 -> 25317 | N20: =MANPOWER!$E$3:$E$56 -> 25317 | P20: =MANPOWER!$E$3:$E$56 -> 25317 | R20: =MANPOWER!$E$3:$E$56 -> 25317 | T20: =MANPOWER!$E$3:$E$56 -> 25317 | V20: =MANPOWER!$E$3:$E$56 -> 25317 | X20: =MANPOWER!$E$3:$E$56 -> 25317 | Z20: =MANPOWER!$E$3:$E$56 -> 25317 | AB20: =MANPOWER!$E$3:$E$56 -> 25317 | AD20: =MANPOWER!$E$3:$E$56 -> 25317
A21: 8 | B21: Saidali Safar | C21: Procurement Assistant | D21: CORE TEAM | E21: 25318 | F21: 30 | G21: =MANPOWER!$E21/30*MANPOWER!$F21 -> 25318 | H21: 31 | I21: =MANPOWER!$E21/31*MANPOWER!$H21 -> 25318 | J21: =MANPOWER!$E21-MANPOWER!$I21 -> 0 | L21: =MANPOWER!$E$3:$E$56 -> 25318 | N21: =MANPOWER!$E$3:$E$56 -> 25318 | P21: =MANPOWER!$E$3:$E$56 -> 25318 | R21: =MANPOWER!$E$3:$E$56 -> 25318 | T21: =MANPOWER!$E$3:$E$56 -> 25318 | V21: =MANPOWER!$E$3:$E$56 -> 25318 | X21: =MANPOWER!$E$3:$E$56 -> 25318 | Z21: =MANPOWER!$E$3:$E$56 -> 25318 | AB21: =MANPOWER!$E$3:$E$56 -> 25318 | AD21: =MANPOWER!$E$3:$E$56 -> 25318
... A23: 9 | B23: Dhanya B L | C23: Project Assistant | D23: LSGB | E23: 26026 | F23: 28 | G23: =MANPOWER!$E23/30*MANPOWER!$F23 -> 24290.933 | H23: 30.5 | I23: =MANPOWER!$E23/31*MANPOWER!$H23 -> 25606.226 | J23: =MANPOWER!$E23-MANPOWER!$I23 -> 419.77419 | L23: =MANPOWER!$E$3:$E$56 -> 26026 | N23: =MANPOWER!$E$3:$E$56 -> 26026 | P23: =MANPOWER!$E$3:$E$56 -> 26026 | R23: =MANPOWER!$E$3:$E$56 -> 26026 | T23: =MANPOWER!$E$3:$E$56 -> 26026 | V23: =MANPOWER!$E$3:$E$56 -> 26026 | X23: =MANPOWER!$E$3:$E$56 -> 26026 | Z23: =MANPOWER!$E$3:$E$56 -> 26026 | AB23: =MANPOWER!$E$3:$E$56 -> 26026 | AD23: =MANPOWER!$E$3:$E$56 -> 26026
A24: 1 | B24: Heksy Sebastian | C24: Admistrative Assistant (Projects) | D24: CORE TEAM | E24: 26885 | F24: 27.5 | G24: =MANPOWER!$E24/30*MANPOWER!$F24 -> 24644.583 | H24: 24.5 | I24: =MANPOWER!$E24/31*MANPOWER!$H24 -> 21247.823 | J24: =MANPOWER!$E24-MANPOWER!$I24 -> 5637.1774 | L24: 26885 | N24: =MANPOWER!$E$3:$E$56 -> 26885 | P24: =MANPOWER!$E$3:$E$56 -> 26885 | R24: =MANPOWER!$E$3:$E$56 -> 26885 | T24: =MANPOWER!$E$3:$E$56 -> 26885 | V24: =MANPOWER!$E$3:$E$56 -> 26885 | X24: =MANPOWER!$E$3:$E$56 -> 26885 | Z24: =MANPOWER!$E$3:$E$56 -> 26885 | AB24: =MANPOWER!$E$3:$E$56 -> 26885 | AD24: =MANPOWER!$E$3:$E$56 -> 26885
A25: 2 | B25: Manjusha V | C25: Admistrative Assistant (Projects) | D25: CORE TEAM | E25: 26885 | F25: 30 | G25: =MANPOWER!$E25/30*MANPOWER!$F25 -> 26885 | H25: 30 | I25: =MANPOWER!$E25/31*MANPOWER!$H25 -> 26017.742 | J25: =MANPOWER!$E25-MANPOWER!$I25 -> 867.25806 | L25: =MANPOWER!$E$3:$E$56 -> 26885 | N25: =MANPOWER!$E$3:$E$56 -> 26885 | P25: =MANPOWER!$E$3:$E$56 -> 26885 | R25: =MANPOWER!$E$3:$E$56 -> 26885 | T25: =MANPOWER!$E$3:$E$56 -> 26885 | V25: =MANPOWER!$E$3:$E$56 -> 26885 | X25: =MANPOWER!$E$3:$E$56 -> 26885 | Z25: =MANPOWER!$E$3:$E$56 -> 26885 | AB25: =MANPOWER!$E$3:$E$56 -> 26885 | AD25: =MANPOWER!$E$3:$E$56 -> 26885
A26: 13 | B26: Mariyathul Hibthiya | C26: Project Associate | D26: IOCL LAKSWADEEP | E26: 30096 | F26: 30 | G26: =MANPOWER!$E26/30*MANPOWER!$F26 -> 30096 | H26: 31 | I26: =MANPOWER!$E26/31*MANPOWER!$H26 -> 30096 | J26: =MANPOWER!$E26-MANPOWER!$I26 -> 0 | L26: =MANPOWER!$E$3:$E$56 -> 30096 | N26: =MANPOWER!$E$3:$E$56 -> 30096 | P26: =MANPOWER!$E$3:$E$56 -> 30096 | R26: =MANPOWER!$E$3:$E$56 -> 30096 | T26: =MANPOWER!$E$3:$E$56 -> 30096 | V26: =MANPOWER!$E$3:$E$56 -> 30096 | X26: =MANPOWER!$E$3:$E$56 -> 30096 | Z26: =MANPOWER!$E$3:$E$56 -> 30096 | AB26: =MANPOWER!$E$3:$E$56 -> 30096 | AD26: =MANPOWER!$E$3:$E$56 -> 30096
A27: 14 | B27: Ruksana Beegum Pakkichippura | C27: Project Associate | D27: IOCL LAKSWADEEP | E27: 30096 | F27: 30 | G27: =MANPOWER!$E27/30*MANPOWER!$F27 -> 30096 | H27: 31 | I27: =MANPOWER!$E27/31*MANPOWER!$H27 -> 30096 | J27: =MANPOWER!$E27-MANPOWER!$I27 -> 0 | L27: =MANPOWER!$E$3:$E$56 -> 30096 | N27: =MANPOWER!$E$3:$E$56 -> 30096 | P27: =MANPOWER!$E$3:$E$56 -> 30096 | R27: =MANPOWER!$E$3:$E$56 -> 30096 | T27: =MANPOWER!$E$3:$E$56 -> 30096 | V27: =MANPOWER!$E$3:$E$56 -> 30096 | X27: =MANPOWER!$E$3:$E$56 -> 30096 | Z27: =MANPOWER!$E$3:$E$56 -> 30096 | AB27: =MANPOWER!$E$3:$E$56 -> 30096 | AD27: =MANPOWER!$E$3:$E$56 -> 30096
A28: 24 | B28: Greeshma Kuriakose | C28: Project Associate (Public Health) | D28: CPCL North Chennai | E28: 30096 | F28: 30 | G28: =MANPOWER!$E28/30*MANPOWER!$F28 -> 30096 | H28: 31 | I28: =MANPOWER!$E28/31*MANPOWER!$H28 -> 30096 | J28: =MANPOWER!$E28-MANPOWER!$I28 -> 0 | L28: =MANPOWER!$E$3:$E$56 -> 30096 | N28: =MANPOWER!$E$3:$E$56 -> 30096 | P28: =MANPOWER!$E$3:$E$56 -> 30096 | R28: =MANPOWER!$E$3:$E$56 -> 30096 | T28: =MANPOWER!$E$3:$E$56 -> 30096 | V28: =MANPOWER!$E$3:$E$56 -> 30096 | X28: =MANPOWER!$E$3:$E$56 -> 30096 | Z28: =MANPOWER!$E$3:$E$56 -> 30096 | AB28: =MANPOWER!$E$3:$E$56 -> 30096 | AD28: =MANPOWER!$E$3:$E$56 -> 30096
A29: 35 | B29: Ashwini Bhausaheb Ranjane | C29: Project Associate (Public Health) | D29: HLL CSR Maharashtra | E29: 30096 | F29: 30 | G29: =MANPOWER!$E29/30*MANPOWER!$F29 -> 30096 | H29: 31 | I29: =MANPOWER!$E29/31*MANPOWER!$H29 -> 30096 | J29: =MANPOWER!$E29-MANPOWER!$I29 -> 0 | L29: =MANPOWER!$E$3:$E$56 -> 30096 | N29: =MANPOWER!$E$3:$E$56 -> 30096 | P29: =MANPOWER!$E$3:$E$56 -> 30096 | R29: =MANPOWER!$E$3:$E$56 -> 30096 | T29: =MANPOWER!$E$3:$E$56 -> 30096 | V29: =MANPOWER!$E$3:$E$56 -> 30096 | X29: =MANPOWER!$E$3:$E$56 -> 30096 | Z29: =MANPOWER!$E$3:$E$56 -> 30096 | AB29: =MANPOWER!$E$3:$E$56 -> 30096 | AD29: =MANPOWER!$E$3:$E$56 -> 30096
A30: 22 | B30: Swathy Krishna S | C30: Project Associate (Community Development) | D30: HMA Communications | E30: 30156 | F30: 29.5 | G30: =MANPOWER!$E30/30*MANPOWER!$F30 -> 29653.4 | H30: 26 | I30: =MANPOWER!$E30/31*MANPOWER!$H30 -> 25292.129 | J30: =MANPOWER!$E30-MANPOWER!$I30 -> 4863.871 | L30: =MANPOWER!$E$3:$E$56 -> 30156 | N30: =MANPOWER!$E$3:$E$56 -> 30156 | P30: =MANPOWER!$E$3:$E$56 -> 30156 | R30: =MANPOWER!$E$3:$E$56 -> 30156 | T30: =MANPOWER!$E$3:$E$56 -> 30156 | V30: =MANPOWER!$E$3:$E$56 -> 30156 | X30: =MANPOWER!$E$3:$E$56 -> 30156 | Z30: =MANPOWER!$E$3:$E$56 -> 30156 | AB30: =MANPOWER!$E$3:$E$56 -> 30156 | AD30: =MANPOWER!$E$3:$E$56 -> 30156
A31: 34 | B31: Anjali Prakash K | C31: Project Associate (Public Health) | D31: LSGB | E31: 30156 | F31: 30 | G31: =MANPOWER!$E31/30*MANPOWER!$F31 -> 30156 | H31: 31 | I31: =MANPOWER!$E31/31*MANPOWER!$H31 -> 30156 | J31: =MANPOWER!$E31-MANPOWER!$I31 -> 0 | L31: =MANPOWER!$E$3:$E$56 -> 30156 | N31: =MANPOWER!$E$3:$E$56 -> 30156 | P31: =MANPOWER!$E$3:$E$56 -> 30156 | R31: =MANPOWER!$E$3:$E$56 -> 30156 | T31: =MANPOWER!$E$3:$E$56 -> 30156 | V31: =MANPOWER!$E$3:$E$56 -> 30156 | X31: =MANPOWER!$E$3:$E$56 -> 30156 | Z31: =MANPOWER!$E$3:$E$56 -> 30156 | AB31: =MANPOWER!$E$3:$E$56 -> 30156 | AD31: =MANPOWER!$E$3:$E$56 -> 30156
A32: 42 | B32: Ajila Mohan N J | C32: Project Associate | D32: HLL CSR Division | E32: 30156 | F32: 0 | G32: =MANPOWER!$E32/30*MANPOWER!$F32 -> 0 | H32: 20 | I32: =MANPOWER!$E32/31*MANPOWER!$H32 -> 19455.484 | J32: =MANPOWER!$E32-MANPOWER!$I32 -> 10700.516 | L32: =MANPOWER!$E$3:$E$56 -> 30156 | N32: =MANPOWER!$E$3:$E$56 -> 30156 | P32: =MANPOWER!$E$3:$E$56 -> 30156 | R32: =MANPOWER!$E$3:$E$56 -> 30156 | T32: =MANPOWER!$E$3:$E$56 -> 30156 | V32: =MANPOWER!$E$3:$E$56 -> 30156 | X32: =MANPOWER!$E$3:$E$56 -> 30156 | Z32: =MANPOWER!$E$3:$E$56 -> 30156 | AB32: =MANPOWER!$E$3:$E$56 -> 30156 | AD32: =MANPOWER!$E$3:$E$56 -> 30156
A33: 45 | B33: Elizabeth Packim | C33: Project Associate | D33: CSL, Andaman | E33: 30156 | F33: 0 | G33: =MANPOWER!$E33/30*MANPOWER!$F33 -> 0 | H33: 9 | I33: =MANPOWER!$E33/31*MANPOWER!$H33 -> 8754.9677 | J33: =MANPOWER!$E33-MANPOWER!$I33 -> 21401.032 | L33: =MANPOWER!$E$3:$E$56 -> 30156 | N33: =MANPOWER!$E$3:$E$56 -> 30156 | P33: =MANPOWER!$E$3:$E$56 -> 30156 | R33: =MANPOWER!$E$3:$E$56 -> 30156 | T33: =MANPOWER!$E$3:$E$56 -> 30156 | V33: =MANPOWER!$E$3:$E$56 -> 30156 | X33: =MANPOWER!$E$3:$E$56 -> 30156 | Z33: =MANPOWER!$E$3:$E$56 -> 30156 | AB33: =MANPOWER!$E$3:$E$56 -> 30156 | AD33: =MANPOWER!$E$3:$E$56 -> 30156
A34: 46 | B34: Arathy A S Kumar | C34: Project Associate | E34: 30156 | F34: 0 | G34: =MANPOWER!$E34/30*MANPOWER!$F34 -> 0 | H34: 11 | I34: =MANPOWER!$E34/31*MANPOWER!$H34 -> 10700.516 | J34: =MANPOWER!$E34-MANPOWER!$I34 -> 19455.484 | L34: =MANPOWER!$E$3:$E$56 -> 30156 | N34: =MANPOWER!$E$3:$E$56 -> 30156 | P34: =MANPOWER!$E$3:$E$56 -> 30156 | R34: =MANPOWER!$E$3:$E$56 -> 30156 | T34: =MANPOWER!$E$3:$E$56 -> 30156 | V34: =MANPOWER!$E$3:$E$56 -> 30156 | X34: =MANPOWER!$E$3:$E$56 -> 30156 | Z34: =MANPOWER!$E$3:$E$56 -> 30156 | AB34: =MANPOWER!$E$3:$E$56 -> 30156 | AD34: =MANPOWER!$E$3:$E$56 -> 30156
A35: 47 | B35: Juhaina C K | C35: Project Associate | D35: HLL CSR MALAPPURAM | E35: 30156 | F35: 0 | G35: =MANPOWER!$E35/30*MANPOWER!$F35 -> 0 | H35: 6 | I35: =MANPOWER!$E35/31*MANPOWER!$H35 -> 5836.6452 | J35: =MANPOWER!$E35-MANPOWER!$I35 -> 24319.355 | L35: =MANPOWER!$E$3:$E$56 -> 30156 | N35: =MANPOWER!$E$3:$E$56 -> 30156 | P35: =MANPOWER!$E$3:$E$56 -> 30156 | R35: =MANPOWER!$E$3:$E$56 -> 30156 | T35: =MANPOWER!$E$3:$E$56 -> 30156 | V35: =MANPOWER!$E$3:$E$56 -> 30156 | X35: =MANPOWER!$E$3:$E$56 -> 30156 | Z35: =MANPOWER!$E$3:$E$56 -> 30156 | AB35: =MANPOWER!$E$3:$E$56 -> 30156 | AD35: =MANPOWER!$E$3:$E$56 -> 30156
A36: 51 | B36: Navya M | C36: Project Associate | D36: Powergrid CSR Thinkal | E36: 30156 | F36: 0 | G36: =MANPOWER!$E36/30*MANPOWER!$F36 -> 0 | H36: 0 | I36: =MANPOWER!$E36/31*MANPOWER!$H36 -> 0 | J36: =MANPOWER!$E36-MANPOWER!$I36 -> 30156 | L36: =MANPOWER!$E$3:$E$56 -> 30156 | N36: =MANPOWER!$E$3:$E$56 -> 30156 | P36: =MANPOWER!$E$3:$E$56 -> 30156 | R36: =MANPOWER!$E$3:$E$56 -> 30156 | T36: =MANPOWER!$E$3:$E$56 -> 30156 | V36: =MANPOWER!$E$3:$E$56 -> 30156 | X36: =MANPOWER!$E$3:$E$56 -> 30156 | Z36: =MANPOWER!$E$3:$E$56 -> 30156 | AB36: =MANPOWER!$E$3:$E$56 -> 30156 | AD36: =MANPOWER!$E$3:$E$56 -> 30156
A37: 23 | B37: Alka Wadhwa | C37: Project Associate (Public Health) | D37: IOCL CSR Haryana | E37: 30156 | F37: 30 | G37: =MANPOWER!$E37/30*MANPOWER!$F37 -> 30156 | H37: 31 | I37: =MANPOWER!$E37/31*MANPOWER!$H37 -> 30156 | J37: =MANPOWER!$E37-MANPOWER!$I37 -> 0 | L37: =MANPOWER!$E$3:$E$56 -> 30156 | N37: =MANPOWER!$E$3:$E$56 -> 30156 | P37: =MANPOWER!$E$3:$E$56 -> 30156 | R37: =MANPOWER!$E$3:$E$56 -> 30156 | T37: =MANPOWER!$E$3:$E$56 -> 30156 | V37: =MANPOWER!$E$3:$E$56 -> 30156 | X37: =MANPOWER!$E$3:$E$56 -> 30156 | Z37: =MANPOWER!$E$3:$E$56 -> 30156 | AB37: =MANPOWER!$E$3:$E$56 -> 30156 | AD37: =MANPOWER!$E$3:$E$56 -> 30156
A38: 36 | B38: Anjaly V | C38: Project Facilitator | D38: CORE TEAM | E38: 30635 | F38: 30 | G38: =MANPOWER!$E38/30*MANPOWER!$F38 -> 30635 | H38: 31 | I38: =MANPOWER!$E38/31*MANPOWER!$H38 -> 30635 | J38: =MANPOWER!$E38-MANPOWER!$I38 -> 0 | L38: =MANPOWER!$E$3:$E$56 -> 30635 | N38: =MANPOWER!$E$3:$E$56 -> 30635 | P38: =MANPOWER!$E$3:$E$56 -> 30635 | R38: =MANPOWER!$E$3:$E$56 -> 30635 | T38: =MANPOWER!$E$3:$E$56 -> 30635 | V38: =MANPOWER!$E$3:$E$56 -> 30635 | X38: =MANPOWER!$E$3:$E$56 -> 30635 | Z38: =MANPOWER!$E$3:$E$56 -> 30635 | AB38: =MANPOWER!$E$3:$E$56 -> 30635 | AD38: =MANPOWER!$E$3:$E$56 -> 30635
A39: 20 | B39: Anjali A S | C39: Project Associate (Community Development) | D39: LSGB | E39: 31064 | F39: 30 | G39: =MANPOWER!$E39/30*MANPOWER!$F39 -> 31064 | H39: 31 | I39: =MANPOWER!$E39/31*MANPOWER!$H39 -> 31064 | J39: =MANPOWER!$E39-MANPOWER!$I39 -> 0 | L39: =MANPOWER!$E$3:$E$56 -> 31064 | N39: =MANPOWER!$E$3:$E$56 -> 31064 | P39: =MANPOWER!$E$3:$E$56 -> 31064 | R39: =MANPOWER!$E$3:$E$56 -> 31064 | T39: =MANPOWER!$E$3:$E$56 -> 31064 | V39: =MANPOWER!$E$3:$E$56 -> 31064 | X39: =MANPOWER!$E$3:$E$56 -> 31064 | Z39: =MANPOWER!$E$3:$E$56 -> 31064 | AB39: =MANPOWER!$E$3:$E$56 -> 31064 | AD39: =MANPOWER!$E$3:$E$56 -> 31064
A40: 21 | B40: Rakhi Mohan | C40: Project Associate (Community Development) | D40: LSGB | E40: 31064 | F40: 28 | G40: =MANPOWER!$E40/30*MANPOWER!$F40 -> 28993.067 | H40: 31 | I40: =MANPOWER!$E40/31*MANPOWER!$H40 -> 31064 | J40: =MANPOWER!$E40-MANPOWER!$I40 -> 0 | L40: =MANPOWER!$E$3:$E$56 -> 31064 | N40: =MANPOWER!$E$3:$E$56 -> 31064 | P40: =MANPOWER!$E$3:$E$56 -> 31064 | R40: =MANPOWER!$E$3:$E$56 -> 31064 | T40: =MANPOWER!$E$3:$E$56 -> 31064 | V40: =MANPOWER!$E$3:$E$56 -> 31064 | X40: =MANPOWER!$E$3:$E$56 -> 31064 | Z40: =MANPOWER!$E$3:$E$56 -> 31064 | AB40: =MANPOWER!$E$3:$E$56 -> 31064 | AD40: =MANPOWER!$E$3:$E$56 -> 31064
A41: 15 | B41: Abhirami N A | C41: Project Associate (Community Development) | D41: LSGB | E41: 31762 | F41: 25 | G41: =MANPOWER!$E41/30*MANPOWER!$F41 -> 26468.333 | H41: 24 | I41: =MANPOWER!$E41/31*MANPOWER!$H41 -> 24589.935 | J41: =MANPOWER!$E41-MANPOWER!$I41 -> 7172.0645 | L41: =MANPOWER!$E$3:$E$56 -> 31762 | N41: =MANPOWER!$E$3:$E$56 -> 31762 | P41: =MANPOWER!$E$3:$E$56 -> 31762 | R41: =MANPOWER!$E$3:$E$56 -> 31762 | T41: =MANPOWER!$E$3:$E$56 -> 31762 | V41: =MANPOWER!$E$3:$E$56 -> 31762 | X41: =MANPOWER!$E$3:$E$56 -> 31762 | Z41: =MANPOWER!$E$3:$E$56 -> 31762 | AB41: =MANPOWER!$E$3:$E$56 -> 31762 | AD41: =MANPOWER!$E$3:$E$56 -> 31762
A42: 27 | B42: Sarika P S Krishna | C42: Project Associate (Public Health) | D42: LSGB | E42: 31762 | F42: 30 | G42: =MANPOWER!$E42/30*MANPOWER!$F42 -> 31762 | H42: 31 | I42: =MANPOWER!$E42/31*MANPOWER!$H42 -> 31762 | J42: =MANPOWER!$E42-MANPOWER!$I42 -> 0 | L42: =MANPOWER!$E$3:$E$56 -> 31762 | N42: =MANPOWER!$E$3:$E$56 -> 31762 | P42: =MANPOWER!$E$3:$E$56 -> 31762 | R42: =MANPOWER!$E$3:$E$56 -> 31762 | T42: =MANPOWER!$E$3:$E$56 -> 31762 | V42: =MANPOWER!$E$3:$E$56 -> 31762 | X42: =MANPOWER!$E$3:$E$56 -> 31762 | Z42: =MANPOWER!$E$3:$E$56 -> 31762 | AB42: =MANPOWER!$E$3:$E$56 -> 31762 | AD42: =MANPOWER!$E$3:$E$56 -> 31762
A43: 28 | B43: Bhavya R J | C43: Project Associate (Public Health) | D43: LSGB | E43: 31762 | F43: 27 | G43: =MANPOWER!$E43/30*MANPOWER!$F43 -> 28585.8 | H43: 30 | I43: =MANPOWER!$E43/31*MANPOWER!$H43 -> 30737.419 | J43: =MANPOWER!$E43-MANPOWER!$I43 -> 1024.5806 | L43: =MANPOWER!$E$3:$E$56 -> 31762 | N43: =MANPOWER!$E$3:$E$56 -> 31762 | P43: =MANPOWER!$E$3:$E$56 -> 31762 | R43: =MANPOWER!$E$3:$E$56 -> 31762 | T43: =MANPOWER!$E$3:$E$56 -> 31762 | V43: =MANPOWER!$E$3:$E$56 -> 31762 | X43: =MANPOWER!$E$3:$E$56 -> 31762 | Z43: =MANPOWER!$E$3:$E$56 -> 31762 | AB43: =MANPOWER!$E$3:$E$56 -> 31762 | AD43: =MANPOWER!$E$3:$E$56 -> 31762
A44: 30 | B44: Jesna C | C44: Project Associate (Public Health) | D44: LSGB | E44: 31762 | F44: 29 | G44: =MANPOWER!$E44/30*MANPOWER!$F44 -> 30703.267 | H44: 31 | I44: =MANPOWER!$E44/31*MANPOWER!$H44 -> 31762 | J44: =MANPOWER!$E44-MANPOWER!$I44 -> 0 | L44: =MANPOWER!$E$3:$E$56 -> 31762 | N44: =MANPOWER!$E$3:$E$56 -> 31762 | P44: =MANPOWER!$E$3:$E$56 -> 31762 | R44: =MANPOWER!$E$3:$E$56 -> 31762 | T44: =MANPOWER!$E$3:$E$56 -> 31762 | V44: =MANPOWER!$E$3:$E$56 -> 31762 | X44: =MANPOWER!$E$3:$E$56 -> 31762 | Z44: =MANPOWER!$E$3:$E$56 -> 31762 | AB44: =MANPOWER!$E$3:$E$56 -> 31762 | AD44: =MANPOWER!$E$3:$E$56 -> 31762
A45: 31 | B45: Rasna K S | C45: Project Associate (Public Health) | D45: LSGB | E45: 31762 | F45: 30 | G45: =MANPOWER!$E45/30*MANPOWER!$F45 -> 31762 | H45: 29.5 | I45: =MANPOWER!$E45/31*MANPOWER!$H45 -> 30225.129 | J45: =MANPOWER!$E45-MANPOWER!$I45 -> 1536.871 | L45: =MANPOWER!$E$3:$E$56 -> 31762 | N45: =MANPOWER!$E$3:$E$56 -> 31762 | P45: =MANPOWER!$E$3:$E$56 -> 31762 | R45: =MANPOWER!$E$3:$E$56 -> 31762 | T45: =MANPOWER!$E$3:$E$56 -> 31762 | V45: =MANPOWER!$E$3:$E$56 -> 31762 | X45: =MANPOWER!$E$3:$E$56 -> 31762 | Z45: =MANPOWER!$E$3:$E$56 -> 31762 | AB45: =MANPOWER!$E$3:$E$56 -> 31762 | AD45: =MANPOWER!$E$3:$E$56 -> 31762
A46: 29 | B46: Lenita G Lawrence | C46: Project Associate (Public Health) | D46: CORE TEAM | E46: 31974 | F46: 30 | G46: =MANPOWER!$E46/30*MANPOWER!$F46 -> 31974 | H46: 31 | I46: =MANPOWER!$E46/31*MANPOWER!$H46 -> 31974 | J46: =MANPOWER!$E46-MANPOWER!$I46 -> 0 | L46: =MANPOWER!$E$3:$E$56 -> 31974 | N46: =MANPOWER!$E$3:$E$56 -> 31974 | P46: =MANPOWER!$E$3:$E$56 -> 31974 | R46: =MANPOWER!$E$3:$E$56 -> 31974 | T46: =MANPOWER!$E$3:$E$56 -> 31974 | V46: =MANPOWER!$E$3:$E$56 -> 31974 | X46: =MANPOWER!$E$3:$E$56 -> 31974 | Z46: =MANPOWER!$E$3:$E$56 -> 31974 | AB46: =MANPOWER!$E$3:$E$56 -> 31974 | AD46: =MANPOWER!$E$3:$E$56 -> 31974
... A54: 33 | B54: Rejitha Ravi | C54: Project Associate (Public Health) | D54: LSGB | E54: 32035 | F54: 29.5 | G54: =MANPOWER!$E54/30*MANPOWER!$F54 -> 31501.083 | H54: 31 | I54: =MANPOWER!$E54/31*MANPOWER!$H54 -> 32035 | J54: =MANPOWER!$E54-MANPOWER!$I54 -> 0 | L54: =MANPOWER!$E$3:$E$56 -> 32035 | N54: =MANPOWER!$E$3:$E$56 -> 32035 | P54: =MANPOWER!$E$3:$E$56 -> 32035 | R54: =MANPOWER!$E$3:$E$56 -> 32035 | T54: =MANPOWER!$E$3:$E$56 -> 32035 | V54: =MANPOWER!$E$3:$E$56 -> 32035 | X54: =MANPOWER!$E$3:$E$56 -> 32035 | Z54: =MANPOWER!$E$3:$E$56 -> 32035 | AB54: =MANPOWER!$E$3:$E$56 -> 32035 | AD54: =MANPOWER!$E$3:$E$56 -> 32035
A55: 52 | B55: Devika HS | C55: Project Associate | D55: LSGB | E55: 32035 | F55: 29.5 | G55: =MANPOWER!$E55/30*MANPOWER!$F55 -> 31501.083 | H55: 2 | I55: =MANPOWER!$E55/31*MANPOWER!$H55 -> 2066.7742 | J55: =MANPOWER!$E55-MANPOWER!$I55 -> 29968.226
A56: 53 | B56: Jijo Pramod | C56: Project Associate | E56: 32035 | F56: 29.5 | G56: =MANPOWER!$E56/30*MANPOWER!$F56 -> 31501.083 | H56: 30 | I56: =MANPOWER!$E56/31*MANPOWER!$H56 -> 31001.613 | J56: =MANPOWER!$E56-MANPOWER!$I56 -> 1033.3871
G57: =SUM(G3:G56) -> 1166241.6 | I57: =SUM(I3:I56) -> 1220354.9

Sheet PROJECT SHEET
A1: Consolidated Expense | L1: Project Manpower
A2: Month | B2: Project 1 | C2: Project 2 | D2: Project 3 | E2: Project 4 | F2: Project 5 | G2: Project 6 | H2: Project 7 | I2: LSGB | J2: Total | L2: Month | M2: Project 1 | N2: Project 2 | O2: Project 3 | P2: Project 4 | Q2: Project 5 | R2: Project 6 | S2: Project 7 | T2: LSGB | U2: Total
A3: 45839 | B3: =M3+B15+M15 -> 10701 | C3: =N3+C15+N15 -> 8838 | D3: =O3+D15+O15 -> 13560 | E3: =P3+E15+P15 -> 17030 | F3: =Q3+F15+Q15 -> 20038 | G3: =R3+G15+R15 -> 24030 | H3: =S3+H15+S15 -> 12772 | I3: =T3+I15+T15 -> 60226 | J3: =U3+J15+U15 -> 167195 | L3: 45839 | M3: 2550 | N3: 3600 | O3: 5000 | P3: 6800 | Q3: 9000 | R3: 12000 | S3: 3500 | T3: 45050 | U3: =SUM(M3:T3) -> 87500
A4: 45870 | L4: 45870
A5: 45901 | L5: 45901
A6: 45931 | L6: 45931
A7: 45962 | L7: 45962
A8: 45992 | L8: 45992
A9: 46023 | L9: 46023
A10: 46054 | L10: 46054
A11: 46082 | L11: 46082
A12: Total
A13: Admin Expenses | L13: Core Manpower
A14: Month | B14: Project 1 | C14: Project 2 | D14: Project 3 | E14: Project 4 | F14: Project 5 | G14: Project 6 | H14: Project 7 | I14: LSGB | J14: Total | L14: Month | M14: Project 1 | N14: Project 2 | O14: Project 3 | P14: Project 4 | Q14: Project 5 | R14: Project 6 | S14: Project 7 | T14: LSGB | U14: Total
A15: 45839 | B15: 5126 | C15: 1234 | D15: 3560 | E15: 7030 | F15: 6012 | G15: 1230 | H15: 6421 | I15: 1111 | J15: =SUM(B15:I15) -> 31724 | L15: 45839 | M15: 3025 | N15: 4004 | O15: 5000 | P15: 3200 | Q15: 5026 | R15: 10800 | S15: 2851 | T15: 14065 | U15: =SUM(M15:T15) -> 47971
A16: 45870 | L16: 45870
A17: 45901 | L17: 45901
A18: 45931 | L18: 45931
A19: 45962 | L19: 45962
A20: 45992 | L20: 45992
A21: 46023 | L21: 46023
A22: 46054 | L22: 46054
A23: 46082 | L23: 46082

Sheet Sheet2
C1: CSR | L1: Consultancy -VBD/HCS
A2: Month | C2: Project 1 | D2: Project 2 | E2: Project 3 | F2: Project 4 | G2: Project 5 | H2: Project 6 | I2: Project 7 | K2: ARREARS 2024-25 | L2: Project 1 | M2: Project 2 | N2: Project 3 | O2: Project 4 | P2: Project 5 | Q2: CSR +VBD TOTAL | R2: LSGB
A3: 45839 | B3: 587176 | C3: 29545 | D3: 29545 | E3: 29545 | K3: 0 | L3: 50000 | Q3: =SUM(C3:P3) -> 138635 | R3: =B3-C3-D3-E3-F3-G3-H3-K3-I3-L3-M3-N3-O3-P3 -> 448541
A4: 45870
A5: 45901
A6: 45931
A7: 45962
A8: 45992
A9: 46023
A10: 46054
A11: 46082
Q13: =Q3/B3*100 -> 23.610468 | R13: =R3/B3*100 -> 76.389532
F14: =B3/C3 -> 19.873955
B16: =B3/12 -> 48931.333 | I16: =20*65000000 -> 1300000000

Sheet Sheet3
A1: EMPLOYEE BENEFIT COST | D1: CSR | E1: HMA REVENUE | F1: LSGB | G1: VBD | H1: CORE
A2: TPC SALARY | B2: 14400000 | D2: 3051708 | F2: 5184240 | H2: =B2-D2-F2 -> 6164052
A3: FTC SALARY | B3: 2700000
A4: PERMANENT | B4: 4800000
B5: =SUM(B2:B4) -> 21900000

Sheet MASTER FILE
F1: 45748 | H1: 45778 | J1: 45809 | L1: 45839 | N1: 45870 | P1: 45901 | R1: 45931 | T1: 45962 | V1: 45992 | X1: 46023 | Z1: 46054 | AB1: 46082
A2: SL No | B2: Name | C2: Designation | D2: Project | E2: Monthly CTC | F2: Attendance | G2: Amount | H2: Attendance | I2: Amount | J2: Attendance | K2: Amount | L2: Attendance | M2: Amount | N2: Attendance | O2: Amount | P2: Attendance | Q2: Amount | R2: Attendance | S2: Amount | T2: Attendance | U2: Amount | V2: Attendance | W2: Amount | X2: Attendance | Y2: Amount | Z2: Attendance | AA2: Amount | AB2: Attendance | AC2: Amount | AD2: Month | AE2: Project 1 | AF2: Project 2 | AG2: Project 3 | AH2: Project 4 | AI2: Project 5 | AJ2: Project 6 | AK2: Project 7 | AL2: LSGB
A3: 1 | B3: Heksy Sebastian | C3: Admistrative Assistant (Projects) | D3: CORE TEAM | E3: 26885 | F3: 27.5 | G3: 24644.583 | H3: 24.5 | I3: 21247.823 | K3: 26885 | L3: =HEKSY!L37 -> 28.5 | M3: =HEKSY!M37 -> 25861.452 | N3: =HEKSY!N37 -> 29.5 | O3: =HEKSY!O37 -> 26768.871 | P3: =HEKSY!P37 -> 26 | Q3: =HEKSY!Q37 -> 24379.333 | R3: =HEKSY!R37 -> 28 | S3: =HEKSY!S37 -> 25407.742 | ... AC3: =HEKSY!AC37 -> 28130 | AD3: 45839
A4: 2 | B4: Manjusha V | C4: Admistrative Assistant (Projects) | D4: CORE TEAM | E4: 26885 | F4: 30 | G4: 26885 | H4: 30 | I4: 26017.742 | K4: 26885 | L4: =MANJUSHA!L37 -> 31 | M4: =MANJUSHA!M37 -> 27598 | N4: =MANJUSHA!N37 -> 31 | O4: =MANJUSHA!O37 -> 27598 | P4: =MANJUSHA!P37 -> 26 | Q4: =MANJUSHA!Q37 -> 23918.267 | R4: =MANJUSHA!R37 -> 26 | S4: =MANJUSHA!S37 -> 23146.71 | ... AC4: =MANJUSHA!AC37 -> 27598 | AD4: 45870
A5: 3 | B5: Ashitha Vins V M | C5: Backend Support | D5: CORE TEAM | E5: 23309 | F5: 30 | G5: 23309 | H5: 31 | I5: 23309 | K5: 23309 | M5: 23309 | O5: 23309 | Q5: 23309 | S5: 23309 | U5: 23309 | W5: 23309 | Y5: 23309 | AA5: 23309 | AC5: 23309 | AD5: 45901
A6: 4 | B6: Savitha Y | C6: Backend Support | D6: CORE TEAM | E6: 23309 | F6: 30 | G6: 23309 | H6: 31 | I6: 23309 | K6: 23309 | M6: 23309 | O6: 23309 | Q6: 23309 | S6: 23309 | U6: 23309 | W6: 23309 | Y6: 23309 | AA6: 23309 | AC6: 23309 | AD6: 45931
A7: 5 | B7: Soumya S K | C7: Field Assistant | D7: CORE TEAM | E7: 22689 | F7: 28.5 | G7: 21554.55 | H7: 30 | I7: 21957.097 | K7: 22689 | M7: 22689 | O7: 22689 | Q7: 22689 | S7: 22689 | U7: 22689 | W7: 22689 | Y7: 22689 | AA7: 22689 | AC7: 22689 | AD7: 45962
A8: 6 | B8: Gayatri Vijay L | C8: Field Assistant | D8: CORE TEAM | E8: 21367 | F8: 28 | G8: 19942.533 | H8: 29 | I8: 19988.484 | K8: 21367 | M8: 21367 | O8: 21367 | Q8: 21367 | S8: 21367 | U8: 21367 | W8: 21367 | Y8: 21367 | AA8: 21367 | AC8: 21367 | AD8: 45992
A9: 7 | B9: Vignesh Kumar P B | C9: Office Assistant | D9: CORE TEAM | E9: 22689 | F9: 30 | G9: 22689 | H9: 31 | I9: 22689 | K9: 22689 | M9: 22689 | O9: 22689 | Q9: 22689 | S9: 22689 | U9: 22689 | W9: 22689 | Y9: 22689 | AA9: 22689 | AC9: 22689 | AD9: 46023
A10: 8 | B10: Saidali Safar | C10: Procurement Assistant | D10: CORE TEAM | E10: 25318 | F10: 30 | G10: 25318 | H10: 31 | I10: 25318 | K10: 25318 | M10: 25318 | O10: 25318 | Q10: 25318 | S10: 25318 | U10: 25318 | W10: 25318 | Y10: 25318 | AA10: 25318 | AC10: 25318 | AD10: 46054
A11: 9 | B11: Dhanya B L | C11: Project Assistant | D11: CORE TEAM | E11: 26026 | F11: 28 | G11: 24290.933 | H11: 30.5 | I11: 25606.226 | K11: 26026 | M11: 26026 | O11: 26026 | Q11: 26026 | S11: 26026 | U11: 26026 | W11: 26026 | Y11: 26026 | AA11: 26026 | AC11: 26026 | AD11: 46082
A12: 10 | B12: Sushila | C12: Project Assistant | D12: IOCL CSR HARYANA | E12: 24523 | F12: 30 | G12: 24523 | H12: 31 | I12: 24523 | K12: 24523 | M12: 24523 | O12: 24523 | Q12: 24523 | S12: 24523 | U12: 24523 | W12: 24523 | Y12: 24523 | AA12: 24523 | AC12: 24523
A13: 11 | B13: Jayalekshmi J | C13: Project Assistant | D13: LSGB | E13: 24509 | F13: 30 | G13: 24509 | H13: 31 | I13: 24509 | K13: 24509 | M13: 24509 | O13: 24509 | Q13: 24509 | S13: 24509 | U13: 24509 | W13: 24509 | Y13: 24509 | AA13: 24509 | AC13: 24509
A14: 12 | B14: Titu S Jayan | C14: Project Assistant (Accounts) | D14: CORE TEAM | E14: 25802 | F14: 30 | G14: 25802 | H14: 29.5 | I14: 24553.516 | K14: 25802 | M14: 25802 | O14: 25802 | Q14: 25802 | S14: 25802 | U14: 25802 | W14: 25802 | Y14: 25802 | AA14: 25802 | AC14: 25802
A15: 13 | B15: Mariyathul Hibthiya | C15: Project Associate | D15: IOCL LAKSWADEEP | E15: 30096 | F15: 30 | G15: 30096 | H15: 31 | I15: 30096 | K15: 30096 | M15: 30096 | O15: 30096 | Q15: 30096 | S15: 30096 | U15: 30096 | W15: 30096 | Y15: 30096 | AA15: 30096 | AC15: 30096
A16: 14 | B16: Ruksana Beegum Pakkichippura | C16: Project Associate | D16: IOCL LAKSWADEEP | E16: 30096 | F16: 30 | G16: 30096 | H16: 31 | I16: 30096 | K16: 30096 | M16: 30096 | O16: 30096 | Q16: 30096 | S16: 30096 | U16: 30096 | W16: 30096 | Y16: 30096 | AA16: 30096 | AC16: 30096
A17: 15 | B17: Abhirami N A | C17: Project Associate (Community Development) | D17: LSGB | E17: 31762 | F17: 25 | G17: 26468.333 | H17: 24 | I17: 24589.935 | K17: 31762 | M17: 31762 | O17: 31762 | Q17: 31762 | S17: 31762 | U17: 31762 | W17: 31762 | Y17: 31762 | AA17: 31762 | AC17: 31762
A18: 16 | B18: Devika Prasad | C18: Project Associate (Community Development) | D18: CORE TEAM | E18: 32035 | F18: 28 | G18: 29899.333 | H18: 30.5 | I18: 31518.306 | K18: 32035 | M18: 32035 | O18: 32035 | Q18: 32035 | S18: 32035 | U18: 32035 | W18: 32035 | Y18: 32035 | AA18: 32035 | AC18: 32035
A19: 17 | B19: Jayalekshmi M J | C19: Project Associate (Community Development) | D19: LSGB | E19: 32035 | F19: 30 | G19: 32035 | H19: 30.5 | I19: 31518.306 | K19: 32035 | M19: 32035 | O19: 32035 | Q19: 32035 | S19: 32035 | U19: 32035 | W19: 32035 | Y19: 32035 | AA19: 32035 | AC19: 32035
A20: 18 | B20: K Anakha Soman | C20: Project Associate (Community Development) | D20: CORE TEAM | E20: 32035 | F20: 30 | G20: 32035 | H20: 31 | I20: 32035 | K20: 32035 | M20: 32035 | O20: 32035 | Q20: 32035 | S20: 32035 | U20: 32035 | W20: 32035 | Y20: 32035 | AA20: 32035 | AC20: 32035
A21: 19 | B21: Jithin Dominic | C21: Project Associate (Community Development) | D21: CORE TEAM | E21: 32035 | F21: 27.5 | G21: 29365.417 | H21: 31 | I21: 32035 | K21: 32035 | M21: 32035 | O21: 32035 | Q21: 32035 | S21: 32035 | U21: 32035 | W21: 32035 | Y21: 32035 | AA21: 32035 | AC21: 32035
A22: 20 | B22: Anjali A S | C22: Project Associate (Community Development) | D22: LSGB | E22: 31064 | F22: 30 | G22: 31064 | H22: 31 | I22: 31064 | K22: 31064 | M22: 31064 | O22: 31064 | Q22: 31064 | S22: 31064 | U22: 31064 | W22: 31064 | Y22: 31064 | AA22: 31064 | AC22: 31064
A23: 21 | B23: Rakhi Mohan | C23: Project Associate (Community Development) | D23: LSGB | E23: 31064 | F23: 28 | G23: 28993.067 | H23: 31 | I23: 31064 | K23: 31064 | M23: 31064 | O23: 31064 | Q23: 31064 | S23: 31064 | U23: 31064 | W23: 31064 | Y23: 31064 | AA23: 31064 | AC23: 31064
... A48: 46 | B48: Navya M | C48: Project Associate | D48: Powergrid CSR Thinkal | E48: 30156 | F48: 0 | G48: 0 | H48: 0 | I48: 0 | K48: 30156 | M48: 30156 | O48: 30156 | Q48: 30156 | S48: 30156 | U48: 30156 | W48: 30156 | Y48: 30156 | AA48: 30156 | AC48: 30156

Sheet AUGUST 2025 ADMIN EXPENSES
I1: HR @ 5% CSR | V1: HR Revenue | X1: ADMIN CHARGES TOTAL | AI1: TOTAL | AJ1: BALANCE
A2: Sl No | B2: Vendor | C2: Service | D2: Payment frequency | E2: Annual commitment | F2: Monthly Average | G2: Actual expense | I2: ='CORE MANPOWER'!AF2 -> HLL Malappuram | J2: ='CORE MANPOWER'!AG2 -> Power Grid Corporation of India Limited - Yelahanka, Bangalore | K2: ='CORE MANPOWER'!AH2 -> Cochin Shipyard Limited - Andaman | L2: ='CORE MANPOWER'!AI2 -> IOCL - Panipat | M2: ='CORE MANPOWER'!AJ2 -> HLL Cotton Hill, Trivandrum | N2: ='CORE MANPOWER'!AK2 -> Swasthya-An innovative behaviour change programme for Aneamia in women of reproductive age | O2: ='CORE MANPOWER'!AL2 -> Counselling support for transgender individuals-pre and post surgery and non surgical pathways in gender transition | P2: ='CORE MANPOWER'!AM2 -> Inclusive community mental health initiative in Wayanad district | ... S2: ='CORE MANPOWER'!AP2 -> HLL Maharashtra | T2: LSGB | U2: Additional LSGB | W2: Month | X2: ='CORE MANPOWER'!AF2 -> HLL Malappuram | Y2: ='CORE MANPOWER'!AG2 -> Power Grid Corporation of India Limited - Yelahanka, Bangalore | Z2: ='CORE MANPOWER'!AH2 -> Cochin Shipyard Limited - Andaman | AA2: ='CORE MANPOWER'!AI2 -> IOCL - Panipat | AB2: ='CORE MANPOWER'!AJ2 -> HLL Cotton Hill, Trivandrum | AC2: ='CORE MANPOWER'!AK2 -> Swasthya-An innovative behaviour change programme for Aneamia in women of reproductive age | AD2: ='CORE MANPOWER'!AL2 -> Counselling support for transgender individuals-pre and post surgery and non surgical pathways in gender transition | AE2: ='CORE MANPOWER'!AM2 -> Inclusive community mental health initiative in Wayanad district | ... AH2: ='CORE MANPOWER'!AP2 -> HLL Maharashtra | AI2: HMA HR REVENUE | AJ2: LSGB
A3: 1 | B3: Manjith Travels | C3: Contract Vehicle | D3: Monthly | E3: =F3*12 -> 523932 | F3: 43661 | G3: 43661 | H3: =G3+G4+G5+G6+G7+G8 -> 120513 | I3: ='PROJECT MASTER FILE - COPY'!P17/H3*G3 -> 14714.488 | J3: ='PROJECT MASTER FILE - COPY'!P30/H3*G3 -> 11875.236 | K3: ='PROJECT MASTER FILE - COPY'!P43/H3*G3 -> 6799.5125 | L3: ='PROJECT MASTER FILE - COPY'!$P56/H3*G3 -> 19255.866 | M3: ='PROJECT MASTER FILE - COPY'!P69/H3*F3 -> 0 | N3: ='PROJECT MASTER FILE - COPY'!P82/H3*G3 -> 2550.5418 | O3: ='PROJECT MASTER FILE - COPY'!P95/H3*G3 -> 12982.04 | P3: ='PROJECT MASTER FILE - COPY'!P108/H3*G3 -> 14608.011 | Q3: 0 | R3: ='PROJECT MASTER FILE - COPY'!O134/H3*F3 -> 0 | S3: ='PROJECT MASTER FILE - COPY'!O4/H3*F3 -> 0 | T3: =F3- (I3+J3+K3+L3+M3+N3+O3+P3+Q3+R3+S3) -> -39124.695 | U3: =G3-F3 -> 0 | V3: 60000 | W3: 45839 | X3: ='PROJECT MASTER FILE - COPY'!O18 -> 0 | Y3: ='PROJECT MASTER FILE - COPY'!O31 -> 0 | Z3: ='PROJECT MASTER FILE - COPY'!O44 -> 0 | AA3: ='PROJECT MASTER FILE - COPY'!O57 -> 0 | AB3: ='PROJECT MASTER FILE - COPY'!O70 -> 0 | AC3: ='PROJECT MASTER FILE - COPY'!O83 -> 0 | AD3: ='PROJECT MASTER FILE - COPY'!O96 -> 0 | AE3: ='PROJECT MASTER FILE - COPY'!O109 -> 0 | AF3: ='PROJECT MASTER FILE - COPY'!O122 -> 8333.3333 | AG3: 0 | AH3: ='PROJECT MASTER FILE - COPY'!O5 -> 0 | AI3: ='HMA HR REVNUE SHEET'!J6 -> 60000 | AJ3: =G10-(X3+Y3+Z3+AD3+AE3+AF3+AH3+AI3) -> 50766.667
A4: 2 | B4: Alchemy IBS | C4: Website | D4: Monthly | E4: 200000 | F4: 0 | I4: ='PROJECT MASTER FILE - COPY'!P17/H3*G4 -> 0 | J4: ='PROJECT MASTER FILE - COPY'!P30/H3*G4 -> 0 | K4: ='PROJECT MASTER FILE - COPY'!P43/H3*G4 -> 0 | L4: ='PROJECT MASTER FILE - COPY'!P56/H3*G4 -> 0 | M4: ='PROJECT MASTER FILE - COPY'!P69/H3*F4 -> 0 | N4: ='PROJECT MASTER FILE - COPY'!P82/H3*G4 -> 0 | O4: ='PROJECT MASTER FILE - COPY'!P95/H3*G4 -> 0 | P4: ='PROJECT MASTER FILE - COPY'!P108/H3*G4 -> 0 | Q4: ='PROJECT MASTER FILE - COPY'!O121/H3*F4 -> 0 | R4: ='PROJECT MASTER FILE - COPY'!O134/H3*F4 -> 0 | S4: ='PROJECT MASTER FILE - COPY'!O4/H3*F4 -> 0 | T4: =F4- (I4+J4+K4+L4+M4+N4+O4+P4+Q4+R4+S4) -> 0 | U4: =G4-F4 -> 0 | V4: ='HMA HR REVNUE SHEET'!L6 -> 423768 | W4: 45870 | X4: ='PROJECT MASTER FILE - COPY'!O19 -> 16207.25 | Y4: ='PROJECT MASTER FILE - COPY'!P31 -> 0 | Z4: ='PROJECT MASTER FILE - COPY'!P44 -> 0 | AA4: ='PROJECT MASTER FILE - COPY'!P57 -> 0 | AB4: ='PROJECT MASTER FILE - COPY'!P70 | AC4: ='PROJECT MASTER FILE - COPY'!P83 -> 0 | AD4: ='PROJECT MASTER FILE - COPY'!P96 -> 0 | AE4: ='PROJECT MASTER FILE - COPY'!P109 -> 0 | AF4: 0 | AG4: 0 | AH4: ='PROJECT MASTER FILE - COPY'!P5 -> 0 | AI4: 423768 | AJ4: =G11-(X4+Y4+Z4+AD4+AE4+AF4+AH4+AI4) -> -437998.25
A5: 3 | B5: Oval Blue Technologies | C5: Photocopier SDP | D5: Monthly | E5: 84000 | F5: =E5/12 -> 7000 | G5: 6344 | I5: ='PROJECT MASTER FILE - COPY'!P17/H3*G5 -> 2138.0343 | J5: ='PROJECT MASTER FILE - COPY'!P30/H3*G5 -> 1725.4871 | K5: ='PROJECT MASTER FILE - COPY'!P43/H3*G5 -> 987.97799 | L5: ='PROJECT MASTER FILE - COPY'!P56/H3*G5 -> 2797.9023 | M5: ='PROJECT MASTER FILE - COPY'!P69/H3*F5 -> 0 | N5: ='PROJECT MASTER FILE - COPY'!P82/H3*G5 -> 370.59703 | O5: 0 | P5: ='PROJECT MASTER FILE - COPY'!P108/H3*G5 -> 2122.5629 | Q5: 0 | R5: ='PROJECT MASTER FILE - COPY'!O134/H3*F5 -> 0 | S5: ='PROJECT MASTER FILE - COPY'!O4/H3*F5 -> 0 | T5: =G5- (I5+J5+K5+L5+M5+N5+O5+P5+Q5+R5+S5) -> -3798.5617 | U5: 0 | W5: 45901
A6: 4 | B6: Volks Electronics | C6: Desktop rental | D6: Monthly | E6: 720000 | F6: 57180 | G6: 57180 | I6: ='PROJECT MASTER FILE - COPY'!P17/H3*G6 -> 19270.618 | J6: ='PROJECT MASTER FILE - COPY'!P30/H3*G6 -> 15552.231 | K6: ='PROJECT MASTER FILE - COPY'!P43/H3*G6 -> 8904.8836 | L6: ='PROJECT MASTER FILE - COPY'!P56/H3*G6 -> 25218.167 | M6: ='PROJECT MASTER FILE - COPY'!P69/H3*F6 -> 0 | N6: ='PROJECT MASTER FILE - COPY'!P82/H3*G6 -> 3340.2803 | O6: 0 | P6: ='PROJECT MASTER FILE - COPY'!P108/H3*G6 -> 19131.171 | Q6: 0 | R6: ='PROJECT MASTER FILE - COPY'!O134/H3*F6 -> 0 | S6: ='PROJECT MASTER FILE - COPY'!O4/H3*F6 -> 0 | T6: =F6- (I6+J6+K6+L6+M6+N6+O6+P6+Q6+R6+S6) -> -34237.351 | U6: =G6-F6 -> 0 | W6: 45931
A7: 5 | B7: Asianet | C7: Internet Services | D7: Quarterly | E7: 56640 | F7: 0 | I7: ='PROJECT MASTER FILE - COPY'!P17/H3*G7 -> 0 | J7: ='PROJECT MASTER FILE - COPY'!P30/H3*G7 -> 0 | K7: ='PROJECT MASTER FILE - COPY'!P43/H3*G7 -> 0 | L7: ='PROJECT MASTER FILE - COPY'!P56/H3*G7 -> 0 | M7: ='PROJECT MASTER FILE - COPY'!P69/H3*F7 -> 0 | N7: ='PROJECT MASTER FILE - COPY'!P82/H3*G7 -> 0 | O7: ='PROJECT MASTER FILE - COPY'!P95/H3*G7 -> 0 | P7: ='PROJECT MASTER FILE - COPY'!P108/H3*G7 -> 0 | Q7: ='PROJECT MASTER FILE - COPY'!O121/H3*F7 -> 0 | R7: ='PROJECT MASTER FILE - COPY'!O134/H3*F7 -> 0 | S7: ='PROJECT MASTER FILE - COPY'!O4/H3*F7 -> 0 | T7: =F7- (I7+J7+K7+L7+M7+N7+O7+P7+Q7+R7+S7) -> 0 | U7: =G7-F7 -> 0 | W7: 45962
A8: 6 | B8: Stationary | C8: Stationary | E8: 200000 | F8: 0 | G8: 13328 | I8: ='PROJECT MASTER FILE - COPY'!P17/H3*G8 -> 4491.7593 | J8: ='PROJECT MASTER FILE - COPY'!P30/H3*G8 -> 3625.0461 | K8: ='PROJECT MASTER FILE - COPY'!P43/H3*G8 -> 2075.6259 | L8: ='PROJECT MASTER FILE - COPY'!P56/H3*G8 -> 5878.0646 | M8: ='PROJECT MASTER FILE - COPY'!P69/H3*F8 -> 0 | N8: ='PROJECT MASTER FILE - COPY'!P82/H3*G8 -> 778.5809 | O8: ='PROJECT MASTER FILE - COPY'!P95/H3*G8 -> 3962.9104 | P8: ='PROJECT MASTER FILE - COPY'!P108/H3*G8 -> 4459.2557 | Q8: ='PROJECT MASTER FILE - COPY'!O121/H3*F8 -> 0 | R8: ='PROJECT MASTER FILE - COPY'!O134/H3*F8 -> 0 | S8: ='PROJECT MASTER FILE - COPY'!O4/H3*F8 -> 0 | T8: =G8- (I8+J8+K8+L8+M8+N8+O8+P8+Q8+R8+S8) -> -11943.243 | U8: 0 | W8: 45992
I9: =SUM(I3:I8) -> 40614.9 | J9: =SUM(J3:J8) -> 32778 | K9: =SUM(K3:K8) -> 18768 | L9: =SUM(L3:L8) -> 53150 | M9: =SUM(M3:M8) -> 0 | N9: =SUM(N3:N8) -> 7040 | O9: =SUM(O3:O8) -> 16944.951 | P9: =SUM(P3:P8) -> 40321 | ... T9: =SUM(T3:T8) -> -89103.851 | U9: 0
A10: 7 | B10: Dr Anandam | C10: House Rent | D10: Monthly | E10: 1800000 | F10: =E10/12 -> 150000 | G10: 119100 | H10: =SUM(F10:F28) -> 601833.33 | X10: =X4 -> 16207.25 | Y10: =Y4 -> 0 | Z10: =Z4 -> 0 | AA10: =AA4 -> 0 | AB10: =AB4 | AC10: =AC4 -> 0 | AD10: =AD4 -> 0 | AE10: =AE4 -> 0 | ... AH10: =AH4 -> 0 | AI10: =G10-(X10+Y10+Z10+AA10+AB10+AC10+AD10+AE10+AF10+AG10+AH10) -> 102892.75
A11: 8 | B11: BSNL | C11: Land Line | D11: Monthly | E11: 24000 | F11: =E11/12 -> 2000 | G11: 1977 | X11: 0 | Y11: 0 | Z11: 0 | AA11: 0 | AB11: 0 | AC11: 0 | AD11: 0 | AE11: 0 | AF11: 0 | AG11: 0 | AH11: 0 | AI11: 1977 | AJ11: 1974
A12: 9 | B12: KSEB | C12: Electricity Bill | D12: Monthly | E12: 264000 | F12: =E12/12 -> 22000 | AJ12: 21303
A13: 10 | B13: KWA | C13: Water Bill | D13: Monthly | E13: 96000 | F13: =E13/12 -> 8000
A14: 11 | B14: Subramania Industries | C14: DG AMC | D14: Half Yearly | E14: 10000 | F14: =E14/12 -> 833.33333
A15: 12 | B15: Imprest | C15: Monthly Imprest | D15: Monthly | E15: 120000 | F15: =E15/12 -> 10000 | G15: 10000
A16: 13 | B16: Geejey Solutions | C16: Epabx AMC | D16: Half Yearly | E16: 8000 | F16: =E16/12 -> 666.66667 | AJ16: 4360
A17: 14 | B17: VRS infosystems | C17: Tally Software Renewal | D17: Annualy | E17: 16000 | F17: =E17/12 -> 1333.3333
A18: 15 | B18: M/sArmtech Computer Services | C18: CAMC computer hardware | D18: Quarterly | E18: 15000 | F18: =E18/12 -> 1250
A19: 16 | B19: Nu aire | C19: AC AMC | D19: Quarterly | E19: 36000 | F19: =E19/12 -> 3000
A20: 17 | B20: Miscellaneous | C20: Repair & Maintenance | D20: Monthly | E20: 50000 | F20: =E20/12 -> 4166.6667
A21: 18 | B21: Microsoft 365 | C21: Software | D21: Annualy | E21: 7000 | F21: =E21/12 -> 583.33333
A22: 19 | B22: Asterisk | C22: Photocopier (Admin & DVP) | D22: Monthly | E22: 60000 | F22: 5000 | G22: 4354 | X22: 0 | Y22: 0 | Z22: 0 | AA22: 0 | AB22: 0 | AC22: 0 | AD22: 0 | AE22: 0 | AF22: 0 | AG22: 0 | AH22: 0 | AI22: 2177 | AJ22: =G22/2 -> 2177
A23: 20 | B23: Indian Postal Department | C23: Speed post | D23: Monthly | E23: 120000 | F23: =E23/12 -> 10000 | G23: 2572 | X23: 0 | Y23: 0 | Z23: 0 | AA23: 0 | AB23: 0 | AC23: 0 | AD23: 0 | AE23: 0 | AF23: 0 | AG23: 0 | AH23: 0 | AI23: 0 | AJ23: 2572
A24: 21 | B24: Pradeep Kumar Cost Accountant | C24: Financial Consultant | D24: Monthly | E24: 1296000 | F24: =E24/12 -> 108000
A25: 22 | B25: Pradeep Kumar Cost Accountant | C25: Accounts Assistance | D25: Monthly | E25: 750000 | F25: =E25/12 -> 62500
A26: 23 | B26: Vismaya Services | C26: HK salary | D26: Monthly | E26: 600000 | F26: 50000 | G26: 46955 | X26: 0 | Y26: 0 | Z26: 0 | AA26: 0 | AB26: 0 | AC26: 0 | AD26: 0 | AE26: 0 | AF26: 0 | AG26: 0 | AH26: 0 | AI26: 46955 | AJ26: 46016
A27: 24 | B27: Vismaya Services | C27: My city salary | D27: Monthly | E27: 810000 | F27: 67500 | G27: 66207 | X27: 0 | Y27: 0 | Z27: 0 | AA27: 0 | AB27: 0 | AC27: 0 | AD27: 0 | AE27: 0 | AF27: 0 | AG27: 0 | AH27: 0 | AI27: 0 | AJ27: 66676
A28: 25 | B28: Naveen Security Services | C28: Security salary | D28: Monthly | E28: =F28*12 -> 1140000 | F28: 95000 | G28: 96550 | X28: 0 | Y28: 0 | Z28: 0 | AA28: 0 | AB28: 0 | AC28: 0 | AD28: 0 | AE28: 0 | AF28: 0 | AG28: 0 | AH28: 0 | AI28: 96550 | AJ28: 96550

Sheet SEPTEMBER 2025 ADMIN EXPENSES
I1: HR @ 5% CSR | V1: HR Revenue | X1: ADMIN CHARGES TOTAL | AI1: TOTAL | AJ1: BALANCE
A2: Sl No | B2: Vendor | C2: Service | D2: Payment frequency | E2: Annual commitment | F2: Monthly Average | G2: Actual expense | I2: ='CORE MANPOWER'!AF2 -> HLL Malappuram | J2: ='CORE MANPOWER'!AG2 -> Power Grid Corporation of India Limited - Yelahanka, Bangalore | K2: ='CORE MANPOWER'!AH2 -> Cochin Shipyard Limited - Andaman | L2: ='CORE MANPOWER'!AI2 -> IOCL - Panipat | M2: ='CORE MANPOWER'!AJ2 -> HLL Cotton Hill, Trivandrum | N2: ='CORE MANPOWER'!AK2 -> Swasthya-An innovative behaviour change programme for Aneamia in women of reproductive age | O2: ='CORE MANPOWER'!AL2 -> Counselling support for transgender individuals-pre and post surgery and non surgical pathways in gender transition | P2: ='CORE MANPOWER'!AM2 -> Inclusive community mental health initiative in Wayanad district | ... S2: ='CORE MANPOWER'!AP2 -> HLL Maharashtra | T2: LSGB | U2: Additional LSGB | W2: Month | X2: ='CORE MANPOWER'!AF2 -> HLL Malappuram | Y2: ='CORE MANPOWER'!AG2 -> Power Grid Corporation of India Limited - Yelahanka, Bangalore | Z2: ='CORE MANPOWER'!AH2 -> Cochin Shipyard Limited - Andaman | AA2: ='CORE MANPOWER'!AI2 -> IOCL - Panipat | AB2: ='CORE MANPOWER'!AJ2 -> HLL Cotton Hill, Trivandrum | AC2: ='CORE MANPOWER'!AK2 -> Swasthya-An innovative behaviour change programme for Aneamia in women of reproductive age | AD2: ='CORE MANPOWER'!AL2 -> Counselling support for transgender individuals-pre and post surgery and non surgical pathways in gender transition | AE2: ='CORE MANPOWER'!AM2 -> Inclusive community mental health initiative in Wayanad district | ... AH2: ='CORE MANPOWER'!AP2 -> HLL Maharashtra | AI2: HMA HR REVENUE | AJ2: LSGB
A3: 1 | B3: Manjith Travels | C3: Contract Vehicle | D3: Monthly | E3: =F3*12 -> 523932 | F3: 43661 | G3: 46000 | H3: =G3+G4+G5+G6+G7+G8 -> 123202.46 | I3: 5171 | J3: 5979 | K3: 3611 | L3: 2525 | M3: ='PROJECT MASTER FILE - COPY'!P69/H3*F3 -> 0 | N3: 603 | O3: 7757 | P3: 7557 | Q3: 0 | R3: ='PROJECT MASTER FILE - COPY'!O134/H3*F3 -> 0 | S3: ='PROJECT MASTER FILE - COPY'!O4/H3*F3 -> 0 | T3: 12797 | U3: 0 | V3: 60000 | W3: 45839 | X3: ='PROJECT MASTER FILE - COPY'!O18 -> 0 | Y3: ='PROJECT MASTER FILE - COPY'!O31 -> 0 | Z3: ='PROJECT MASTER FILE - COPY'!O44 -> 0 | AA3: ='PROJECT MASTER FILE - COPY'!O57 -> 0 | AB3: ='PROJECT MASTER FILE - COPY'!O70 -> 0 | AC3: ='PROJECT MASTER FILE - COPY'!O83 -> 0 | AD3: ='PROJECT MASTER FILE - COPY'!O96 -> 0 | AE3: ='PROJECT MASTER FILE - COPY'!O109 -> 0 | AF3: ='PROJECT MASTER FILE - COPY'!O122 -> 8333.3333 | AG3: 0 | AH3: ='PROJECT MASTER FILE - COPY'!O5 -> 0 | AI3: ='HMA HR REVNUE SHEET'!J6 -> 60000 | AJ3: =G10-(X3+Y3+Z3+AD3+AE3+AF3+AH3+AI3) -> 50766.667
A4: 2 | B4: Alchemy IBS | C4: Website | D4: Monthly | E4: 200000 | F4: 0 | I4: ='PROJECT MASTER FILE - COPY'!P17/H3*G4 -> 0 | J4: ='PROJECT MASTER FILE - COPY'!P30/H3*G4 -> 0 | K4: ='PROJECT MASTER FILE - COPY'!P43/H3*G4 -> 0 | L4: ='PROJECT MASTER FILE - COPY'!P56/H3*G4 -> 0 | M4: ='PROJECT MASTER FILE - COPY'!P69/H3*F4 -> 0 | N4: ='PROJECT MASTER FILE - COPY'!P82/H3*G4 -> 0 | O4: ='PROJECT MASTER FILE - COPY'!P95/H3*G4 -> 0 | P4: ='PROJECT MASTER FILE - COPY'!P108/H3*G4 -> 0 | Q4: ='PROJECT MASTER FILE - COPY'!O121/H3*F4 -> 0 | R4: ='PROJECT MASTER FILE - COPY'!O134/H3*F4 -> 0 | S4: ='PROJECT MASTER FILE - COPY'!O4/H3*F4 -> 0 | T4: =F4- (I4+J4+K4+L4+M4+N4+O4+P4+Q4+R4+S4) -> 0 | U4: =G4-F4 -> 0 | V4: ='HMA HR REVNUE SHEET'!L6 -> 423768 | W4: 45870 | X4: ='PROJECT MASTER FILE - COPY'!O19 -> 16207.25 | Y4: ='PROJECT MASTER FILE - COPY'!P31 -> 0 | Z4: ='PROJECT MASTER FILE - COPY'!P44 -> 0 | AA4: ='PROJECT MASTER FILE - COPY'!P57 -> 0 | AB4: ='PROJECT MASTER FILE - COPY'!P70 | AC4: ='PROJECT MASTER FILE - COPY'!P83 -> 0 | AD4: ='PROJECT MASTER FILE - COPY'!P96 -> 0 | AE4: ='PROJECT MASTER FILE - COPY'!P109 -> 0 | AF4: 0 | AG4: 0 | AH4: ='PROJECT MASTER FILE - COPY'!P5 -> 0 | AI4: 423768 | AJ4: =G11-(X4+Y4+Z4+AD4+AE4+AF4+AH4+AI4) -> -437998.25
A5: 3 | B5: Oval Blue Technologies | C5: Photocopier SDP | D5: Monthly | E5: 84000 | F5: =E5/12 -> 7000 | G5: 4720 | I5: 0 | J5: 0 | K5: 0 | L5: 0 | M5: ='PROJECT MASTER FILE - COPY'!P69/H3*F5 -> 0 | N5: 0 | O5: 0 | P5: 0 | Q5: 0 | R5: ='PROJECT MASTER FILE - COPY'!O134/H3*F5 -> 0 | S5: ='PROJECT MASTER FILE - COPY'!O4/H3*F5 -> 0 | T5: =G5- (I5+J5+K5+L5+M5+N5+O5+P5+Q5+R5+S5) -> 4720 | U5: 0 | W5: 45901 | X5: 0 | Y5: ='PROJECT MASTER FILE - COPY'!Q31 -> 0 | Z5: ='PROJECT MASTER FILE - COPY'!Q44 -> 0 | AA5: ='PROJECT MASTER FILE - COPY'!Q57 -> 0 | AB5: 0 | AC5: ='PROJECT MASTER FILE - COPY'!Q83 -> 0 | AD5: ='PROJECT MASTER FILE - COPY'!Q96 -> 0 | AE5: ='PROJECT MASTER FILE - COPY'!Q109 -> 0 | AF5: 0 | AG5: 0 | AH5: ='PROJECT MASTER FILE - COPY'!Q5 -> 0 | AI5: 0
A6: 4 | B6: Volks Electronics | C6: Desktop rental | D6: Monthly | E6: 720000 | F6: 57652 | G6: 57652 | I6: ='PROJECT MASTER FILE - COPY'!P17/H3*G6 -> 19005.548 | J6: ='PROJECT MASTER FILE - COPY'!P30/H3*G6 -> 15338.308 | K6: ='PROJECT MASTER FILE - COPY'!P43/H3*G6 -> 8782.3955 | L6: 0 | M6: ='PROJECT MASTER FILE - COPY'!P69/H3*F6 -> 0 | N6: ='PROJECT MASTER FILE - COPY'!P82/H3*G6 -> 3294.3342 | O6: 0 | P6: ='PROJECT MASTER FILE - COPY'!P108/H3*G6 -> 18868.018 | Q6: 0 | R6: ='PROJECT MASTER FILE - COPY'!O134/H3*F6 -> 0 | S6: ='PROJECT MASTER FILE - COPY'!O4/H3*F6 -> 0 | T6: 24170 | U6: =G6-F6 -> 0 | W6: 45931
A7: 5 | B7: Asianet | C7: Internet Services | D7: Quarterly | E7: 56640 | F7: 0 | G7: 5306.46 | I7: 0 | J7: 0 | K7: 0 | L7: 0 | M7: 0 | N7: 0 | O7: 0 | P7: 0 | Q7: 0 | R7: ='PROJECT MASTER FILE - COPY'!O134/H3*F7 -> 0 | S7: ='PROJECT MASTER FILE - COPY'!O4/H3*F7 -> 0 | T7: 5306.46 | U7: =G7-F7 -> 5306.46 | W7: 45962
A8: 6 | B8: Stationary | C8: Stationary | E8: 200000 | F8: 0 | G8: 9524 | I8: 0 | J8: 0 | K8: 0 | L8: 0 | M8: ='PROJECT MASTER FILE - COPY'!P69/H3*F8 -> 0 | N8: 0 | O8: 0 | P8: 0 | Q8: ='PROJECT MASTER FILE - COPY'!O121/H3*F8 -> 0 | R8: ='PROJECT MASTER FILE - COPY'!O134/H3*F8 -> 0 | S8: ='PROJECT MASTER FILE - COPY'!O4/H3*F8 -> 0 | T8: =G8- (I8+J8+K8+L8+M8+N8+O8+P8+Q8+R8+S8) -> 9524 | U8: 0 | W8: 45992
I9: =SUM(I3:I8) -> 24176.548 | J9: =SUM(J3:J8) -> 21317.308 | K9: =SUM(K3:K8) -> 12393.396 | L9: =SUM(L3:L8) -> 2525 | M9: =SUM(M3:M8) -> 0 | N9: =SUM(N3:N8) -> 3897.3342 | O9: =SUM(O3:O8) -> 7757 | P9: =SUM(P3:P8) -> 26425.018 | ... T9: =SUM(T3:T8) -> 56517.46 | U9: 0
A10: 7 | B10: Dr Anandam | C10: House Rent | D10: Monthly | E10: 1800000 | F10: =E10/12 -> 150000 | G10: 119100 | H10: =SUM(F10:F28) -> 601833.33 | X10: 0 | Y10: =Y5 -> 0 | Z10: =Z5 -> 0 | AA10: =AA5 -> 0 | AB10: 0 | AC10: =AC5 -> 0 | AD10: 0 | AE10: 6923 | AF10: 0 | AG10: 0 | AH10: 7500 | AI10: 0 | AJ10: =G10-(AI10+AH10+AG10+AF10+AE10+AD10+AC10+AB10+AA10+Z10+Y10+X10) -> 104677
A11: 8 | B11: BSNL | C11: Land Line | D11: Monthly | E11: 24000 | F11: =E11/12 -> 2000 | G11: 1977 | X11: 0 | Y11: 0 | Z11: 0 | AA11: 0 | AB11: 0 | AC11: 0 | AD11: 0 | AE11: 0 | AF11: 0 | AG11: 0 | AH11: 0 | AI11: 1977 | AJ11: 0
A12: 9 | B12: KSEB | C12: Electricity Bill | D12: Monthly | E12: 264000 | F12: =E12/12 -> 22000 | G12: 19999
A13: 10 | B13: KWA | C13: Water Bill | D13: Monthly | E13: 96000 | F13: =E13/12 -> 8000
A14: 11 | B14: Subramania Industries | C14: DG AMC | D14: Half Yearly | E14: 10000 | F14: =E14/12 -> 833.33333
A15: 12 | B15: Imprest | C15: Monthly Imprest | D15: Monthly | E15: 120000 | F15: =E15/12 -> 10000 | G15: 10000
A16: 13 | B16: Geejey Solutions | C16: Epabx AMC | D16: Half Yearly | E16: 8000 | F16: =E16/12 -> 666.66667
A17: 14 | B17: VRS infosystems | C17: Tally Software Renewal | D17: Annualy | E17: 16000 | F17: =E17/12 -> 1333.3333
A18: 15 | B18: M/sArmtech Computer Services | C18: CAMC computer hardware | D18: Quarterly | E18: 15000 | F18: =E18/12 -> 1250
A19: 16 | B19: Nu aire | C19: AC AMC | D19: Quarterly | E19: 36000 | F19: =E19/12 -> 3000
A20: 17 | B20: Miscellaneous | C20: Repair & Maintenance | D20: Monthly | E20: 50000 | F20: =E20/12 -> 4166.6667
A21: 18 | B21: Microsoft 365 | C21: Software | D21: Annualy | E21: 7000 | F21: =E21/12 -> 583.33333
A22: 19 | B22: Asterisk | C22: Photocopier (Admin & DVP) | D22: Monthly | E22: 60000 | F22: 5000 | X22: 0 | Y22: 0 | Z22: 0 | AA22: 0 | AB22: 0 | AC22: 0 | AD22: 0 | AE22: 0 | AF22: 0 | AG22: 0 | AH22: 0 | AI22: 2177 | AJ22: =G22/2 -> 0
A23: 20 | B23: Indian Postal Department | C23: Speed post | D23: Monthly | E23: 120000 | F23: =E23/12 -> 10000 | G23: 2572 | X23: 0 | Y23: 0 | Z23: 0 | AA23: 0 | AB23: 0 | AC23: 0 | AD23: 0 | AE23: 0 | AF23: 0 | AG23: 0 | AH23: 0 | AI23: 0 | AJ23: 2572
A24: 21 | B24: Pradeep Kumar Cost Accountant | C24: Financial Consultant | D24: Monthly | E24: 1296000 | F24: =E24/12 -> 108000
A25: 22 | B25: Pradeep Kumar Cost Accountant | C25: Accounts Assistance | D25: Monthly | E25: 750000 | F25: =E25/12 -> 62500
A26: 23 | B26: Vismaya Services | C26: HK salary | D26: Monthly | E26: 600000 | F26: 50000 | G26: 46955 | X26: 0 | Y26: 0 | Z26: 0 | AA26: 0 | AB26: 0 | AC26: 0 | AD26: 0 | AE26: 0 | AF26: 0 | AG26: 0 | AH26: 0 | AI26: 46955 | AJ26: 46016
A27: 24 | B27: Vismaya Services | C27: My city salary | D27: Monthly | E27: 810000 | F27: 67500 | G27: 66207 | X27: 0 | Y27: 0 | Z27: 0 | AA27: 0 | AB27: 0 | AC27: 0 | AD27: 0 | AE27: 0 | AF27: 0 | AG27: 0 | AH27: 0 | AI27: 0 | AJ27: 66676
A28: 25 | B28: Naveen Security Services | C28: Security salary | D28: Monthly | E28: =F28*12 -> 1140000 | F28: 95000 | G28: 96550 | X28: 0 | Y28: 0 | Z28: 0 | AA28: 0 | AB28: 0 | AC28: 0 | AD28: 0 | AE28: 0 | AF28: 0 | AG28: 0 | AH28: 0 | AI28: 96550 | AJ28: 96550

Sheet PROJECT MASTER FILE
A1: Sl No | B1: Project Name | C1: Project Type | D1: Project Value | E1: Project Split Up | F1: Value | G1: 45839 | H1: 45870 | I1: 45901 | J1: 45931 | K1: 45962 | L1: 45992 | M1: 46023 | N1: 46054 | O1: 46082 | P1: 46113 | Q1: 46143 | R1: Total
A2: 1 | B2: IOCL M -Cup Project Lakshadweep | C2: CSR | D2: 6500000 | E2: HMA Core TeamSalary @5% | F2: =D2*5% -> 325000 | G2: =$F2/11 -> 29545.455 | H2: =$F2/11 -> 29545.455 | I2: =$F2/11 -> 29545.455 | J2: =$F2/11 -> 29545.455 | K2: =$F2/11 -> 29545.455 | L2: =$F2/11 -> 29545.455 | M2: =$F2/11 -> 29545.455 | N2: =$F2/11 -> 29545.455 | ... Q2: =$F2/11 -> 29545.455 | R2: =SUM(G2:Q2) -> 325000
E3: HR Expenses @5% | F3: =D2*5% -> 325000 | G3: =$F3/11 -> 29545.455 | H3: =$F3/11 -> 29545.455 | I3: =$F3/11 -> 29545.455 | J3: =$F3/11 -> 29545.455 | K3: =$F3/11 -> 29545.455 | L3: =$F3/11 -> 29545.455 | M3: =$F3/11 -> 29545.455 | N3: =$F3/11 -> 29545.455 | ... Q3: =$F3/11 -> 29545.455 | R3: =SUM(G3:Q3) -> 325000
E4: HMA Admin Expenses @5% | F4: =D2*5% -> 325000 | G4: =$F4/11 -> 29545.455 | H4: =$F4/11 -> 29545.455 | I4: =$F4/11 -> 29545.455 | J4: =$F4/11 -> 29545.455 | K4: =$F4/11 -> 29545.455 | L4: =$F4/11 -> 29545.455 | M4: =$F4/11 -> 29545.455 | N4: =$F4/11 -> 29545.455 | ... Q4: =$F4/11 -> 29545.455 | R4: =SUM(G4:Q4) -> 325000
E5: 15% total of Project Value | F5: =SUM(F2:F4) -> 975000 | G5: =SUM(G2:G4) -> 88636.364 | H5: =SUM(H2:H4) -> 88636.364 | I5: =SUM(I2:I4) -> 88636.364 | J5: =SUM(J2:J4) -> 88636.364 | K5: =SUM(K2:K4) -> 88636.364 | L5: =SUM(L2:L4) -> 88636.364 | M5: =SUM(M2:M4) -> 88636.364 | ... Q5: =SUM(Q2:Q4) -> 88636.364 | R5: =SUM(G5:Q5) -> 975000
E6: Project specific salary | G6: 0 | H6: 0 | I6: 0 | J6: 60192 | K6: 60192 | L6: 60192 | M6: 60192 | N6: 60192 | O6: 60192 | P6: 60192 | Q6: 60192 | R6: =SUM(G6:Q6) -> 481536
E7: Design Phase | F7: =D2*50%-(F5/2)-(R6/2) -> 2521732 | R7: =SUM(G7:Q7) -> 0
E8: Implementation Phase | F8: =D2*40%-(F5/2)-(R6/2) -> 1871732 | R8: =SUM(G8:Q8) -> 0
E9: Monitoring and Evaluation | F9: =D2*10% -> 650000 | R9: =SUM(G9:Q9) -> 0
E10: Surplus | R10: =D2-R9-R8-R7-R6-R5-R4-R3-R2 -> 4068464

Sheet PROJECT MASTER FILE - COPY
A2: Sl No | B2: Project Name | C2: Project Type | D2: Project Value | E2: Project Split Up | F2: Value | H2: 45650 | I2: 45682 | J2: 45689 | K2: 45717 | L2: 45762 | M2: 45802 | N2: 45833 | O2: 45863 | P2: 45894 | Q2: 45925 | R2: 45955 | S2: 45986 | T2: 46016 | U2: 46047 | V2: 46078 | W2: 46106 | X2: 46113 | Y2: Total | Z2: Remarks
A3: 1 | B3: HLL Maharashtra | C3: CSR | D3: 1500000 | E3: HMA Core TeamSalary @5% | F3: 75000 | J3: 0 | K3: 0 | L3: 128157 | M3: 0 | N3: 0 | O3: 0 | P3: 0 | Q3: 0 | R3: 0 | S3: 0 | T3: 0 | U3: 0 | V3: 0 | Y3: 128157 | Z3: Taken - 8.54% Instead of 5%
E4: HR Expenses @5% | F4: 75000 | J4: 0 | K4: 0 | L4: 0 | M4: 0 | N4: 12000 | O4: 0 | P4: 15600 | Q4: 0 | R4: - | S4: - | T4: - | U4: - | V4: - | Y4: 27600 | Z4: Instead of 21843 taken 27600
E5: HMA Admin Expenses @5% | F5: 75000 | J5: 0 | K5: 0 | L5: 0 | M5: 0 | N5: 30000 | O5: 0 | P5: 0 | Q5: 0 | R5: 7848.6 | S5: 7848.6 | T5: 7848.6 | U5: 7848.6 | V5: 7848.6 | Y5: 69243
E6: 15% total of Project Value | F6: 225000 | J6: 0 | K6: 0 | L6: 128157 | M6: 0 | N6: 42000 | O6: 0 | P6: 15600 | Q6: 0 | R6: 7848.6 | S6: 7848.6 | T6: 7848.6 | U6: 7848.6 | V6: 7848.6 | Y6: 225000
E7: Project Direct Expenses (i.e 85% total of Project Value) | F7: 1275000
E8: Project specific salary | F8: 522072 | J8: 0 | K8: 0 | L8: 30096 | M8: 34890 | N8: 42473 | O8: 30156 | P8: 45930 | Q8: 56421 | R8: 56421 | S8: 56421 | T8: 56421 | U8: 56421 | V8: 56422 | Y8: 522072
E9: Design Phase | F9: =512000-25000-25000-261036 -> 200964 | J9: 0 | K9: 0 | L9: 2581 | M9: 1634 | N9: =6433+270 -> 6703 | O9: 52829.5 | P9: 120000 | Q9: 0 | R9: 17216.5 | Y9: 200964
E10: Implementation Phase | F10: =726500-25000-25000-261036 -> 415464 | O10: 1213 | P10: 25888.8 | Q10: 294 | R10: 194034.1 | S10: 194034.1 | Y10: 415464
E11: Monitoring and Evaluation | F11: =190000+71500-25000-25000-75000 -> 136500 | P11: 15050 | T11: 40483 | U11: 40483 | V11: 40484 | Y11: 136500
E12: Surplus
A15: Sl No | B15: Project Name | C15: Project Type | D15: Project Value | E15: Project Split Up | F15: Value | H15: 45650 | I15: 45682 | J15: 45689 | K15: 45717 | L15: 45762 | M15: 45802 | N15: 45833 | O15: 45863 | P15: 45894 | Q15: 45925 | R15: 45955 | S15: 45986 | T15: 46016 | U15: 46047 | V15: 46078 | W15: 46106 | X15: 46113 | Y15: Total
A16: 2 | B16: HLL Malappuram | C16: CSR | D16: 1200000 | E16: HMA Core TeamSalary @5% | F16: 60000 | J16: 0 | K16: 7627 | L16: 7311 | M16: 0 | N16: 5006 | O16: 5007 | P16: 5007 | Q16: 5007 | R16: 5007 | S16: 5007 | T16: 5007 | U16: 5007 | V16: 5007 | Y16: 60000
E17: HR Expenses @5% | F17: 60000 | J17: 0 | K17: 0 | L17: 0 | M17: 0 | N17: 0 | O17: 11200.25 | P17: 40614.9 | Q17: 1364.14 | R17: 1364.14 | S17: 1364.14 | T17: 1364.14 | U17: 1364.14 | V17: 1364.15 | Y17: 60000
E18: HMA CSR Admin Expenses @5% | F18: 60000 | J18: 0 | K18: 0 | L18: 0 | M18: 0 | N18: 24000 | O18: 0 | P18: 0 | Q18: 0 | R18: 7200 | S18: 7200 | T18: 7200 | U18: 7200 | V18: 7200 | Y18: 60000
E19: 15% total of Project Value | F19: 180000 | J19: 0 | K19: 7627 | L19: 7311 | M19: 0 | N19: 29006 | O19: 16207.25 | P19: 45621.9 | Q19: 6371.14 | R19: 13571.14 | S19: 13571.14 | T19: 13571.14 | U19: 13571.14 | V19: 13571.15 | Y19: 180000
E20: Project Direct Expenses (i.e 85% total of Project Value) | F20: 1020000
E21: Project specific salary | F21: 241248 | J21: 0 | K21: 0 | L21: 0 | M21: 5886 | N21: 30156 | O21: 30156 | P21: 30156 | Q21: 24149 | R21: 24149 | S21: 24149 | T21: 24149 | U21: 24149 | V21: 24149 | Y21: 241248
E22: Design Phase | F22: =782000-F21/2-F16/3-F17/3 -> 621376 | J22: 0 | K22: 0 | L22: 0 | M22: 0 | N22: 0 | O22: 100960.5 | P22: 160000 | Q22: 24800.3 (accounted) 50400 (commited) | R22: 285215.2 | Y22: 621376
E23: Implementation Phase | F23: =246000-F21/2-F16/3-F17/3 -> 85376 | P23: 20052.4 | Q23: 10009 | R23: 27657.3 | S23: 27657.3 | Y23: 85376
E24: Monitoring and Evaluation | F24: =172000-F16/3-F17/3-F18 -> 72000 | P24: 15050 | T24: 18983 | U24: 18983 | V24: 18984 | Y24: 72000
E25: Surplus
A28: Sl No | B28: Project Name | C28: Project Type | D28: Project Value | E28: Project Split Up | F28: Value | H28: 45650 | I28: 45682 | J28: 45689 | K28: 45717 | L28: 45762 | M28: 45802 | N28: 45833 | O28: 45863 | P28: 45894 | Q28: 45925 | R28: 45955 | S28: 45986 | T28: 46016 | U28: 46047 | V28: 46078 | W28: 46106 | X28: 46113 | Y28: Total
A29: 3 | B29: Power Grid Corporation of India Limited - Yelahanka, Bangalore | C29: CSR | D29: 1850100 | E29: HMA Core TeamSalary @5% | F29: 92505 | L29: 0 | M29: 0 | N29: 8409 | O29: 8409 | P29: 8409 | Q29: 8409 | R29: 8409 | S29: 8410 | T29: 8410 | U29: 8410 | V29: 8410 | W29: 8410 | X29: 8410 | Y29: 92505
E30: HR Expenses @5% | F30: 92505 | L30: 0 | M30: 0 | N30: 0 | O30: 11200.25 | P30: 32778 | Q30: 6065.84 | R30: 6065.84 | S30: 6065.84 | T30: 6065.84 | U30: 6065.84 | V30: 6065.85 | W30: 6065.85 | X30: 6065.85 | Y30: 92505
E31: HMA Admin Expenses @5% | F31: 92505 | L31: 0 | M31: 46253 | N31: 0 | O31: 0 | P31: 0 | Q31: 0 | R31: 6607 | S31: 6607 | T31: 6607 | U31: 6607 | V31: 6608 | W31: 6608 | X31: 6608 | Y31: 92505
E32: 15% total of Project Value | F32: 277515 | L32: 0 | M32: =SUM(M29:M31) -> 46253 | N32: =SUM(N29:N31) -> 8409 | O32: 19609.25 | P32: 41187 | Q32: 14474.84 | R32: 21081.84 | S32: 21082.84 | T32: 21082.84 | U32: 21082.84 | V32: 21083.85 | W32: 21083.85 | X32: 21083.85 | Y32: 277515
E33: Project Direct Expenses (i.e 85% total of Project Value) | F33: 1572585
E34: Project specific salary | F34: 546640 | N34: 15109 | O34: 44412 | P34: 54665 | Q34: 54056.75 | R34: 54056.75 | S34: 54056.75 | T34: 54056.75 | U34: 54056.75 | V34: 54056.75 | W34: 54056.75 | X34: 54056.75 | Y34: 546640
E35: Design Phase | F35: 633117 | L35: 22408 | M35: 0 | N35: 2700 | O35: 743 | P35: 4625 | Q35: 60481.9 | R35: 542159.1 | Y35: 633117
E36: Implementation Phase | F36: 351117 | Q36: 0 | R36: 117039 | S36: 117039 | T36: 117039 | Y36: 351117
E37: Monitoring and Evaluation | F37: 41711 | U37: 10427 | V37: 10428 | W37: 10428 | X37: 10428 | Y37: 41711
E38: Surplus
A41: Sl No | B41: Project Name | C41: Project Type | D41: Project Value | E41: Project Split Up | F41: Value | H41: 45650 | I41: 45682 | J41: 45689 | K41: 45717 | L41: 45762 | M41: 45802 | N41: 45833 | O41: 45863 | P41: 45894 | Q41: 45925 | R41: 45955 | S41: 45986 | T41: 46016 | U41: 46047 | V41: 46078 | W41: 46106 | X41: 46113 | Y41: Total
A42: 4 | B42: Cochin Shipyard Limited - Andaman | C42: CSR | D42: 1000000 | E42: HMA Core TeamSalary @5% | F42: 50000 | J42: 0 | K42: 0 | L42: 0 | M42: 0 | N42: 6250 | O42: 6250 | P42: 6250 | Q42: 6250 | R42: 6250 | S42: 6250 | T42: 6250 | U42: 6250 | Y42: 50000
E43: HR Expenses @5% | F43: 50000 | J43: 0 | K43: 0 | L43: 0 | M43: 5997 | N43: =4720+4296+1321 -> 10337 | O43: 11200.25 | P43: 18768 | Q43: 739.55 | R43: 739.55 | S43: 739.55 | T43: 739.55 | U43: 739.55 | Y43: 50000
E44: HMA Admin Expenses @5% | F44: 50000 | J44: 0 | K44: 0 | L44: 0 | M44: 25000 | N44: 0 | O44: 0 | P44: 0 | Q44: 0 | R44: 6250 | S44: 6250 | T44: 6250 | U44: 6250 | Y44: 50000
E45: 15% total of Project Value | F45: 150000 | M45: 30997 | N45: 16587 | O45: 17450.25 | P45: 25018 | Q45: 6989.55 | R45: 13239.55 | S45: 13239.55 | T45: 13239.55 | U45: 13239.55 | Y45: 1500000
E46: Project Direct Expenses (i.e 85% total of Project Value) | F46: 850000
E47: Project specific salary | F47: 171556 | J47: 0 | K47: 0 | L47: 0 | M47: 8796 | N47: 15545 | O47: 24509 | P47: 24509 | Q47: 19639 | R47: 19639 | S47: 19639 | T47: 19640 | U47: 19640 | Y47: 171556
E48: Design Phase | F48: =416500-F47/2-F42/3-F43/3 -> 297388.67 | J48: 520 | K48: 0 | L48: 0 | M48: =7021+27451+5542+2877 -> 42891 | N48: 147297 | O48: 87500 | P48: 0 | Q48: 0 | R48: 19180.667 | Y48: 297388.67
E49: Implementation Phase | F49: =458500-F47/2-F42/3-F43/3 -> 339388.67 | N49: 36293 | O49: 230 | P49: 11499 | Q49: 0 | R49: 291366.67 | Y49: 339388.67
E50: Monitoring and Evaluation | F50: =125000-F44-F42/3-F43/3 -> 41666.667 | S50: 13888.889 | T50: 13888.889 | U50: 13888.889 | Y50: 41666.667
E51: Surplus
A54: Sl No | B54: Project Name | C54: Project Type | D54: Project Value | E54: Project Split Up | F54: Value | G54: 45552 | H54: 45616 | I54: 45682 | J54: 45689 | K54: 45717 | L54: 45762 | M54: 45802 | N54: 45833 | O54: 45863 | P54: 45894 | Q54: 45925 | R54: 45955 | S54: 45986 | T54: 46016 | U54: 46047 | V54: 46078 | W54: 46106 | X54: 46113 | Y54: Total | Z54: Remarks
A55: 5 | B55: IOCL - Panipat | C55: CSR | D55: 5422200 | E55: HMA Core TeamSalary @5% | F55: 271110 | G55: 0 | H55: 0 | I55: 37781 | J55: 109715 | K55: 132144 | L55: 58373 | M55: 0 | N55: 0 | O55: 0 | P55: 0 | Q55: 0 | R55: 0 | S55: 0 | T55: 0 | Y55: 338013 | Z55: Taken - 6.23% Instead of 5%
E56: HR Expenses @5% | F56: 271110 | G56: 0 | H56: 0 | I56: 0 | J56: 28369.5 | K56: 102236 | L56: 0 | M56: =36000 -> 36000 | N56: 0 | O56: 0 | P56: 53150 | Q56: 0 | R56: 0 | S56: 0 | T56: 0 | Y56: 219755.5 | Z56: Taken 219755.5 Instead of 204207 | AA56: -15548.5
E57: HMA Admin Expenses @5% | F57: 271110 | G57: 0 | H57: 0 | I57: 0 | J57: 82000 | K57: 0 | L57: 0 | M57: 0 | N57: 0 | O57: 0 | P57: 0 | Q57: 0 | R57: 57853.83 | S57: 57853.83 | T57: 57853.84 | Y57: 255561.5
E58: 15% total of Project Value | F58: 813330 | I58: 37781 | J58: 220084.5 | K58: 234380 | L58: 58373 | M58: 36000 | N58: 0 | O58: 0 | P58: 53150 | Q58: 0 | R58: 57853.83 | S58: 57853.83 | T58: 57853.84 | Y58: 813330
E59: Project Direct Expenses (i.e 85% total of Project Value) | F59: 4608870
E60: Project specific salary | F60: 572746 | G60: 0 | H60: 0 | I60: 19321 | J60: 54693 | K60: 54693 | L60: 54693 | M60: 54707 | N60: 54707 | O60: 54686 | P60: 54707 | Q60: 42634.75 | R60: 42634.75 | S60: 42634.75 | T60: 42634.75 | Y60: 572746
E61: Design Phase | F61: =2004000-F55/3-F56/3-F60/2 -> 1536887 | G61: 2980 | H61: 37445.75 | I61: 500 | J61: 113221 | K61: 1041600 | R61: 341140.25 | Y61: 1536887
E62: Implementation Phase | F62: 2192887 | I62: 43692 | J62: 122188 | K62: 174225.6 | L62: 12980 | M62: 50369 | N62: 21610 | O62: 16094 | P62: 440835 | Q62: 12980 | R62: 1297913.4 | Y62: 1660221.9
E63: Monitoring and Evaluation | F63: 306350 | S63: 153175 | T63: 153175 | Y63: =758200-Y57-Y55/3-Y56/3 -> 316715.67
E64: Surplus
A67: Sl No | B67: Project Name | C67: Project Type | D67: Project Value | E67: Project Split Up | F67: Value | I67: 45682 | J67: 45689 | K67: 45717 | L67: 45772 | M67: 45778 | N67: 45809 | O67: 45839 | P67: 45870 | Q67: 45901 | R67: 45931 | S67: 45962 | T67: 45992 | U67: 46023 | V67: 46054 | W67: 46082 | X67: 46137 | Y67: Total
A68: 6 | B68: HLL Cotton Hill, Trivandrum | C68: CSR | D68: 150000 | E68: HMA Core TeamSalary @5% | F68: 0 | M68: 0 | N68: 0 | O68: 0 | Y68: 7500
E69: HR Expenses @5% | F69: 0 | M69: 0 | N69: 12000 | O69: 0 | Y69: 7500
E70: HMA Admin Expenses @5% | F70: 7500 | M70: 0 | N70: 0 | O70: 0 | Q70: 7500 | Y70: 7500
E71: 5% total of Project Value | F71: 7500 | M71: 0 | N71: 0 | O71: 0 | Q71: 7500 | Y71: 22500
E72: Project Direct Expenses (i.e 95% total of Project Value) | F72: 142500
E73: Project specific salary | F73: 60312 | M73: 0 | N73: 0 | O73: 30739 | P73: 10171 | Q73: 19402 | Y73: 60312
E74: Design Phase | F74: =82000-F73/2 -> 51844 | M74: 0 | N74: 0 | O74: 677 | P74: 44825 | Q74: 23600 | Y74: 51844
E75: Implementation Phase | F75: =53656-F73/2 -> 23500 | N75: 0 | O75: 0 | P75: 12988 | Q75: 0 | R75: 10512 | Y75: 23500
E76: Monitoring and Evaluation | F76: =14344-F70 -> 6844 | O76: 0 | R76: 6844 | Y76: 6844
E77: Surplus
A80: Sl No | B80: Project Name | C80: Project Type | D80: Project Value | E80: Project Split Up | F80: Value | I80: 45682 | J80: 45689 | K80: 45717 | L80: 45772 | M80: 45778 | N80: 45809 | O80: 45839 | P80: 45870 | Q80: 45901 | R80: 45931 | S80: 45962 | T80: 45992 | U80: 46023 | V80: 46054 | W80: 46082 | X80: 46137 | Y80: Total
A81: 7 | B81: Swasthya-An innovative behaviour change programme for Aneamia in women of reproductive age | C81: CSR | D81: 1000000 | E81: HMA Core TeamSalary @5% | F81: 50000 | J81: 0 | K81: 0 | L81: 0 | M81: 0 | N81: 5555 | O81: 5556 | P81: 5556 | Q81: 5555.5 | R81: 5555.5 | S81: 5555.5 | T81: 5555.5 | U81: 5555.5 | V81: 5555.5 | Y81: 500000
E82: HR Expenses @5% | F82: 50000 | J82: 0 | K82: 0 | L82: 0 | M82: 0 | N82: 3850 | O82: 11200.25 | P82: 7040 | Q82: 4651.625 | R82: 4651.625 | S82: 4651.625 | T82: 4651.625 | U82: 4651.625 | V82: 4651.625 | Y82: 50000
E83: HMA Admin Expenses @5% | F83: 50000 | J83: 0 | K83: 0 | L83: 0 | M83: 0 | N83: 50000 | O83: 0 | P83: 0 | Q83: 0 | R83: 0 | S83: 0 | T83: 0 | U83: 0 | V83: 0 | Y83: 50000
E84: 15% total of Project Value | F84: 150000 | J84: 0 | K84: 0 | L84: 0 | M84: 0 | N84: 59405 | O84: 16756.25 | P84: 6956 | Q84: 11195.5 | R84: 11137.45 | S84: 11137.45 | T84: 11137.45 | U84: 11137.45 | V84: 11137.45 | Y84: 150000
E85: Project Direct Expenses (i.e 85% total of Project Value) | F85: 850000
E86: Project specific salary | F86: 241248 | M86: 30156 | N86: 0 | O86: 26273 | P86: 30156 | Q86: 25777 | R86: 25777 | S86: 25777 | T86: 25777 | U86: 25777 | V86: 25778 | Y86: 241248
E87: Design Phase | F87: =200000-F86/2-F81/3-F82/3 -> 46042.667 | J87: 0 | K87: 0 | L87: 0 | M87: 0 | N87: 3850 | O87: 0 | P87: 0 | Q87: 0 | R87: 42192.667 | Y87: 46042.667
E88: Implementation Phase | F88: =710000-F86/2-F81/3-F82/3 -> 556042.67 | P88: 23489.8 | Q88: 0 | R88: 266276.43 | S88: 266276.44 | Y88: 556042.67
E89: Monitoring and Evaluation | F89: =90000-F83-F81/3-F82/3 -> 6666.6667 | S89: 1666.665 | T89: 1666.665 | U89: 1666.665 | V89: 1666.665 | Y89: 6666.667
E90: Surplus
A93: Sl No | B93: Project Name | C93: Project Type | D93: Project Value | E93: Project Split Up | F93: Value | I93: 45682 | J93: 45689 | K93: 45717 | L93: 45772 | M93: 45778 | N93: 45809 | O93: 45839 | P93: 45870 | Q93: 45901 | R93: 45931 | S93: 45962 | T93: 45992 | U93: 46023 | V93: 46054 | W93: 46082 | X93: 46137 | Y93: Total
A94: 8 | B94: Counselling support for transgender individuals-pre and post surgery and non surgical pathways in gender transition | C94: CSR | D94: 1500000 | E94: HMA Core TeamSalary @5% | F94: 75000 | J94: 0 | K94: 0 | L94: 33862 | M94: 0 | N94: 5876 | O94: 5877 | P94: 0 | Q94: 7346.25 | R94: 7346.25 | S94: 7346.25 | T94: 7346.25 | Y94: 75000
E95: HR Expenses @5% | F95: 75000 | J95: 0 | K95: 0 | L95: 0 | M95: 0 | N95: 0 | O95: 0 | P95: 35833 | Q95: 9791.75 | R95: 9791.75 | S95: 9791.75 | T95: 9791.75 | Y95: 75000
E96: HMA Admin Expenses @5% | F96: 75000 | J96: 0 | K96: 0 | L96: 0 | M96: 0 | N96: 30000 | O96: 0 | P96: 0 | Q96: 0 | R96: 15000 | S96: 15000 | T96: 15000 | Y96: 75000
E97: 15% total of Project Value | F97: 225000 | J97: 0 | K97: 0 | L97: 33862 | M97: 0 | N97: 35876 | O97: 5877 | P97: 35833 | Q97: 17138 | R97: 32138 | S97: 32138 | T97: 32138 | Y97: 225000
E98: Project Direct Expenses (i.e 85% total of Project Value) | F98: 1275000
E99: Project specific salary | F99: 0 | J99: 0 | K99: 0 | L99: 0 | M99: 0 | N99: 0 | O99: 0 | P99: 33862 | Q99: 0 | R99: 0 | S99: 0 | T99: 0
E100: Design Phase | F100: 382500 | J100: 0 | K100: 0 | L100: 0 | M100: 0 | N100: 0 | O100: 0 | P100: 8439.8 | Q100: 0 | R100: 374060.2 | Y100: 382500
E101: Implementation Phase | F101: 765000 | Q101: 0 | R101: 382500 | S101: 382500 | Y101: 765000
E102: Monitoring and Evaluation | F102: 127500 | P102: 15050 | S102: 56225 | T102: 56225 | Y102: 127500
E103: Surplus
A106: Sl No | B106: Project Name | C106: Project Type | D106: Project Value | E106: Project Split Up | F106: Value | I106: 45682 | J106: 45689 | K106: 45717 | L106: 45772 | M106: 45778 | N106: 45809 | O106: 45839 | P106: 45870 | Q106: 45901 | R106: 45931 | S106: 45962 | T106: 45992 | U106: 46023 | V106: 46054 | W106: 46082 | X106: 46137 | Y106: 45803 | Z106: 45809 | AA106: 45839 | AB106: Total | AC106: Remarks
A107: 9 | B107: Inclusive community mental health initiative in Wayanad district | C107: CSR | D107: 3000000 | E107: HMA Core TeamSalary @5% | F107: 150000 | J107: 0 | K107: 0 | L107: 0 | M107: 0 | N107: 10714 | O107: 10714 | P107: 10714 | Q107: 10714 | R107: 10714 | S107: 10714 | T107: 10714 | U107: 10714 | V107: 10714 | W107: 10714 | X107: 10715 | Y107: 10715 | Z107: 10715 | AA107: 10715 | AB107: 150000
E108: HR Expenses @5% | F108: 150000 | J108: 0 | K108: 0 | L108: 0 | M108: 0 | N108: 12000 | O108: 0 | P108: 40321 | Q108: 8879 | R108: 8880 | S108: 8880 | T108: 8880 | U108: 8880 | V108: 8880 | W108: 8880 | X108: 8880 | Y108: 8880 | Z108: 8880 | AA108: 8880 | AB108: 150000
E109: HMA Admin Expenses @5% | F109: 150000 | J109: 0 | K109: 0 | L109: 0 | M109: 0 | N109: 60000 | O109: 0 | P109: 0 | Q109: 0 | R109: 9000 | S109: 9000 | T109: 9000 | U109: 9000 | V109: 9000 | W109: 9000 | X109: 9000 | Y109: 9000 | Z109: 9000 | AA109: 9000 | AB109: 150000
E110: 15% total of Project Value | F110: 450000 | J110: 0 | K110: 0 | L110: 0 | M110: 0 | N110: 82714 | O110: 10714 | P110: 51035 | Q110: 19593 | R110: 28594 | S110: 28594 | T110: 28594 | U110: 28594 | V110: 28594 | W110: 28594 | X110: 28595 | Y110: 28595 | Z110: 28595 | AA110: 28595 | AB110: 450000
E111: Project Direct Expenses (i.e 85% total of Project Value) | F111: 2550000
E112: Project specific salary | J112: 0 | K112: 0 | L112: 0 | M112: 0 | N112: 0 | O112: 0 | P112: 30490 | Q112: 0 | R112: 0 | S112: 0 | T112: 0 | U112: 0 | V112: 0
E113: Design Phase | F113: 765000
E114: Implementation Phase | F114: 1530000 | P114: 8439.8
E115: Monitoring and Evaluation | F115: 255000 | P115: 15050
E116: Surplus
A119: Sl No | B119: Project Name | C119: Project Type | D119: Project Value | E119: Project Split Up | F119: Value | I119: 45682 | J119: 45689 | K119: 45717 | L119: 45772 | M119: 45778 | N119: 45809 | O119: 45839 | P119: 45870 | Q119: 45901 | R119: 45931 | S119: 45962 | T119: 45992 | U119: 46023 | V119: 46054 | W119: 46082 | X119: 46137 | Y119: Total | Z119: Remarks
...

Sheet CORE MANPOWER
F1: 45748 | H1: 45778 | J1: 45809 | L1: 45839 | N1: 45870 | P1: 45901 | R1: 45931 | T1: 45962 | V1: 45992 | X1: 46023 | Z1: 46054 | AB1: 46082 | AD1: CORE TEAM SALARY BOOKING SHEET
A2: SL No | B2: Name | C2: Designation | D2: Project | E2: Monthly CTC | F2: Attendance | G2: Amount | H2: Attendance | I2: Amount | J2: Attendance | K2: Amount | L2: Attendance | M2: Amount | N2: Attendance | O2: Amount | P2: Attendance | Q2: Amount | R2: Attendance | S2: Amount | T2: Attendance | U2: Amount | V2: Attendance | W2: Amount | X2: Attendance | Y2: Amount | Z2: Attendance | AA2: Amount | AB2: Attendance | AC2: Amount | AD2: Month | AF2: ='PROJECT MASTER FILE - COPY'!B16 -> HLL Malappuram | AG2: ='PROJECT MASTER FILE - COPY'!B29 -> Power Grid Corporation of India Limited - Yelahanka, Bangalore | AH2: ='PROJECT MASTER FILE - COPY'!B42 -> Cochin Shipyard Limited - Andaman | AI2: ='PROJECT MASTER FILE - COPY'!B55 -> IOCL - Panipat | AJ2: ='PROJECT MASTER FILE - COPY'!B68 -> HLL Cotton Hill, Trivandrum | AK2: ='PROJECT MASTER FILE - COPY'!B81 -> Swasthya-An innovative behaviour change programme for Aneamia in women of reproductive age | AL2: ='PROJECT MASTER FILE - COPY'!B94 -> Counselling support for transgender individuals-pre and post surgery and non surgical pathways in gender transition | AM2: ='PROJECT MASTER FILE - COPY'!B107 -> Inclusive community mental health initiative in Wayanad district | AN2: ='PROJECT MASTER FILE - COPY'!B120 -> My City | AO2: ='PROJECT MASTER FILE - COPY'!B133 -> Exploring the correlation and Diagnostic potential of Menstrual Blood | AP2: ='PROJECT MASTER FILE - COPY'!B3 -> HLL Maharashtra | AQ2: LSGB
AD3: 45809 | AE3: =K31 -> 593057 | AF3: ='PROJECT MASTER FILE - COPY'!N16 -> 5006 | AG3: ='PROJECT MASTER FILE - COPY'!N29 -> 8409 | AH3: ='PROJECT MASTER FILE - COPY'!N42 -> 6250 | AI3: ='PROJECT MASTER FILE - COPY'!N55 -> 0 | AJ3: ='PROJECT MASTER FILE - COPY'!N68 -> 0 | AK3: ='PROJECT MASTER FILE - COPY'!N81 -> 5555 | AL3: ='PROJECT MASTER FILE - COPY'!N94 -> 5876 | AM3: ='PROJECT MASTER FILE - COPY'!N107 -> 10714 | AN3: 0 | AO3: ='PROJECT MASTER FILE - COPY'!N133 | AP3: ='PROJECT MASTER FILE - COPY'!N3 -> 0 | AQ3: =AE3-AF3-AG3-AH3-AI3-AJ3-AK3-AL3-AM3-AN3-AO3-AP3 -> 551247
A4: 1 | B4: Heksy Sebastian | C4: Admistrative Assistant (Projects) | D4: CORE TEAM | E4: 28130 | F4: 27.5 | G4: 24644.583 | H4: 24.5 | I4: 21247.823 | J4: 29 | K4: 27197 | L4: =HEKSY!L37 -> 28.5 | M4: 25867 | N4: =HEKSY!N37 -> 29.5 | O4: 26774 | P4: =HEKSY!P37 -> 26 | Q4: =HEKSY!Q37 -> 24379.333 | R4: =HEKSY!R37 -> 28 | S4: =HEKSY!S37 -> 25407.742 | T4: =HEKSY!T37 -> 30 | U4: =HEKSY!U37 -> 28130 | V4: =HEKSY!V37 -> 31 | W4: =HEKSY!W37 -> 28130 | ... AC4: =HEKSY!AC37 -> 28130 | AD4: 45839 | AE4: =M31 -> 690762.77 | AF4: ='PROJECT MASTER FILE - COPY'!O16 -> 5007 | AG4: ='PROJECT MASTER FILE - COPY'!O29 -> 8409 | AH4: ='PROJECT MASTER FILE - COPY'!O42 -> 6250 | AI4: ='PROJECT MASTER FILE - COPY'!O55 -> 0 | AJ4: ='PROJECT MASTER FILE - COPY'!O68 -> 0 | AK4: ='PROJECT MASTER FILE - COPY'!O81 -> 5556 | AL4: ='PROJECT MASTER FILE - COPY'!O94 -> 5877 | AM4: ='PROJECT MASTER FILE - COPY'!O107 -> 10714 | AN4: 0 | AO4: ='PROJECT MASTER FILE - COPY'!O133 | AP4: ='PROJECT MASTER FILE - COPY'!O3 -> 0 | AQ4: =AE4-AF4-AG4-AH4-AI4-AJ4-AK4-AL4-AM4-AN4-AO4-AP4 -> 648949.77
A5: 2 | B5: Manjusha V | C5: Admistrative Assistant (Projects) | D5: CORE TEAM | E5: 27598 | F5: 30 | G5: 26885 | H5: 30 | I5: 26017.742 | J5: 30 | K5: 27598 | L5: 31 | M5: =MANJUSHA!M37 -> 27598 | N5: =MANJUSHA!N37 -> 31 | O5: =MANJUSHA!O37 -> 27598 | P5: =MANJUSHA!P37 -> 26 | Q5: =MANJUSHA!Q37 -> 23918.267 | R5: =MANJUSHA!R37 -> 26 | S5: =MANJUSHA!S37 -> 23146.71 | T5: =MANJUSHA!T37 -> 30 | ... AC5: =MANJUSHA!AC37 -> 27598 | AD5: 45870 | AE5: =O31 -> 632239 | AF5: ='PROJECT MASTER FILE - COPY'!P16 -> 5007 | AG5: ='PROJECT MASTER FILE - COPY'!P29 -> 8409 | AH5: ='PROJECT MASTER FILE - COPY'!P42 -> 6250 | AI5: ='PROJECT MASTER FILE - COPY'!P55 -> 0 | AJ5: ='PROJECT MASTER FILE - COPY'!P68 | AK5: ='PROJECT MASTER FILE - COPY'!P81 -> 5556 | AL5: =P94 | AM5: ='PROJECT MASTER FILE - COPY'!P107 -> 10714 | AN5: 0 | AO5: ='PROJECT MASTER FILE - COPY'!P133 | AP5: ='PROJECT MASTER FILE - COPY'!P3 -> 0 | AQ5: =AE5-AF5-AG5-AH5-AI5-AJ5-AK5-AL5-AM5-AN5-AO5-AP5 -> 596303
A6: 3 | B6: Ashitha Vins V M | C6: Backend Support | D6: CORE TEAM | E6: 23309 | F6: 30 | G6: 23309 | H6: 31 | I6: 23309 | J6: 30 | K6: =(E6/30)*J6 -> 23309 | L6: 31 | M6: ='ASHITHA VINS'!M37 -> 23309 | N6: ='ASHITHA VINS'!N37 -> 28 | O6: 21059 | P6: ='ASHITHA VINS'!P37 -> 27 | Q6: ='ASHITHA VINS'!Q37 -> 20978.1 | R6: ='ASHITHA VINS'!R37 -> 31 | S6: ='ASHITHA VINS'!S37 -> 23309 | T6: ='ASHITHA VINS'!T37 -> 30 | U6: ='ASHITHA VINS'!U37 -> 23309 | V6: ='ASHITHA VINS'!V37 -> 31 | W6: ='ASHITHA VINS'!W37 -> 23309 | ... AC6: ='ASHITHA VINS'!AC37 -> 23309 | AD6: 45901 | AN6: ='PROJECT MASTER FILE - COPY'!B123 | AP6: ='PROJECT MASTER FILE - COPY'!B6
A7: 4 | B7: Savitha Y | C7: Backend Support | D7: CORE TEAM | E7: 23309 | F7: 30 | G7: 23309 | H7: 31 | I7: 23309 | J7: 30 | K7: =(E7/30)*J7 -> 23309 | L7: 30 | M7: 22560 | N7: ='SAVITHA Y'!N37 -> 31 | O7: ='SAVITHA Y'!O37 -> 23309 | P7: ='SAVITHA Y'!P37 -> 28 | Q7: ='SAVITHA Y'!Q37 -> 21755.067 | R7: ='SAVITHA Y'!R37 -> 29.5 | S7: ='SAVITHA Y'!S37 -> 22181.145 | T7: ='SAVITHA Y'!T37 -> 30 | U7: ='SAVITHA Y'!U37 -> 23309 | ... AC7: ='SAVITHA Y'!AC37 -> 23309 | AD7: 45931 | AN7: ='PROJECT MASTER FILE - COPY'!B124 | AP7: ='PROJECT MASTER FILE - COPY'!B7
A8: 5 | B8: Soumya S K | C8: Field Assistant | D8: CORE TEAM | E8: 23980 | F8: 28.5 | G8: 21554.55 | H8: 30 | I8: 21957.097 | J8: 28.5 | K8: 22783 | L8: 28.5 | M8: 22052 | N8: ='SOUMYA S K'!N37 -> 26.5 | O8: 20510 | P8: ='SOUMYA S K'!P37 -> 26.5 | Q8: ='SOUMYA S K'!Q37 -> 21182.333 | R8: ='SOUMYA S K'!R37 -> 30 | S8: ='SOUMYA S K'!S37 -> 23206.452 | T8: ='SOUMYA S K'!T37 -> 30 | U8: ='SOUMYA S K'!U37 -> 23980 | V8: ='SOUMYA S K'!V37 -> 31 | W8: ='SOUMYA S K'!W37 -> 23980 | ... AC8: ='SOUMYA S K'!AC37 -> 23980 | AD8: 45962 | AN8: ='PROJECT MASTER FILE - COPY'!B125 | AP8: ='PROJECT MASTER FILE - COPY'!B8
A9: 6 | B9: Gayatri Vijay L | C9: Project Assistant | D9: CORE TEAM | E9: 24448 | F9: 28 | G9: 19942.533 | H9: 29 | I9: 19988.484 | J9: 27 | K9: 22065 | L9: ='GAYATHRI VIJAY'!L37 -> 29 | M9: 22871 | N9: ='GAYATHRI VIJAY'!N37 -> 31 | O9: 24509 | P9: ='GAYATHRI VIJAY'!P37 -> 28 | Q9: ='GAYATHRI VIJAY'!Q37 -> 22818.133 | R9: ='GAYATHRI VIJAY'!R37 -> 30 | S9: ='GAYATHRI VIJAY'!S37 -> 23659.355 | T9: ='GAYATHRI VIJAY'!T37 -> 30 | U9: ='GAYATHRI VIJAY'!U37 -> 24448 | V9: ='GAYATHRI VIJAY'!V37 -> 31 | W9: ='GAYATHRI VIJAY'!W37 -> 24448 | ... AC9: ='GAYATHRI VIJAY'!AC37 -> 24448 | AD9: 45992 | AN9: ='PROJECT MASTER FILE - COPY'!B126 | AP9: ='PROJECT MASTER FILE - COPY'!B9
A10: 7 | B10: Vignesh Kumar P B | C10: Office Assistant | D10: CORE TEAM | E10: 22689 | F10: 30 | G10: 22689 | H10: 31 | I10: 22689 | J10: 30 | K10: =(E10/30)*J10 -> 22689 | L10: ='VIGNESH KUMAR'!L37 -> 31 | M10: ='VIGNESH KUMAR'!M37 -> 22689 | N10: ='VIGNESH KUMAR'!N37 -> 31 | O10: ='VIGNESH KUMAR'!O37 -> 22689 | P10: ='VIGNESH KUMAR'!P37 -> 30 | Q10: ='VIGNESH KUMAR'!Q37 -> 22689 | R10: ='VIGNESH KUMAR'!R37 -> 31 | S10: ='VIGNESH KUMAR'!S37 -> 22689 | ... AC10: ='VIGNESH KUMAR'!AC37 -> 22689 | AD10: 46023 | AN10: ='PROJECT MASTER FILE - COPY'!B127 | AP10: ='PROJECT MASTER FILE - COPY'!B10
A11: 8 | B11: Saidali Safar | C11: Procurement Assistant | D11: CORE TEAM | E11: 25318 | F11: 30 | G11: 25318 | H11: 31 | I11: 25318 | J11: 30 | K11: =(E11/30)*J11 -> 25318 | L11: ='SAIDALI SAFAR'!L37 -> 30 | M11: 24503 | N11: ='SAIDALI SAFAR'!N37 -> 30 | O11: 24503 | P11: ='SAIDALI SAFAR'!P37 -> 26.5 | Q11: ='SAIDALI SAFAR'!Q37 -> 22364.233 | R11: ='SAIDALI SAFAR'!R37 -> 30 | S11: ='SAIDALI SAFAR'!S37 -> 24501.29 | T11: ='SAIDALI SAFAR'!T37 -> 30 | U11: ='SAIDALI SAFAR'!U37 -> 25318 | V11: ='SAIDALI SAFAR'!V37 -> 31 | W11: ='SAIDALI SAFAR'!W37 -> 25318 | ... AC11: ='SAIDALI SAFAR'!AC37 -> 25318 | AD11: 46054 | AN11: ='PROJECT MASTER FILE - COPY'!B128 | AP11: ='PROJECT MASTER FILE - COPY'!B11
A12: 9 | B12: Dhanya B L | C12: Project Assistant | D12: CORE TEAM | E12: 27511 | F12: 28 | G12: 24290.933 | H12: 30.5 | I12: 25606.226 | J12: 30 | K12: =(E12/30)*J12 -> 27511 | L12: ='DHANYA B L'!L37 -> 30 | M12: 26622 | N12: ='DHANYA B L'!N37 -> 28.5 | O12: 25296 | P12: ='DHANYA B L'!P37 -> 26.5 | Q12: ='DHANYA B L'!Q37 -> 24301.383 | R12: ='DHANYA B L'!R37 -> 28 | S12: ='DHANYA B L'!S37 -> 24848.645 | T12: ='DHANYA B L'!T37 -> 30 | U12: ='DHANYA B L'!U37 -> 27511 | V12: ='DHANYA B L'!V37 -> 31 | W12: ='DHANYA B L'!W37 -> 27511 | ... AC12: ='DHANYA B L'!AC37 -> 27511 | AD12: 46082 | AN12: ='PROJECT MASTER FILE - COPY'!B129 | AP12: ='PROJECT MASTER FILE - COPY'!B12
A13: 10 | B13: Titu S Jayan | C13: Project Assistant (Accounts) | D13: CORE TEAM | E13: 26997 | F13: 30 | G13: 25802 | H13: 29.5 | I13: 24553.516 | J13: 25.5 | K13: 22958 | L13: ='TITU S JAYAN'!L37 -> 30 | M13: 26128 | N13: ='TITU S JAYAN'!N37 -> 28 | O13: 24388 | P13: ='TITU S JAYAN'!P37 -> 27.5 | Q13: ='TITU S JAYAN'!Q37 -> 24747.25 | R13: ='TITU S JAYAN'!R37 -> 27.5 | S13: ='TITU S JAYAN'!S37 -> 23948.952 | T13: ='TITU S JAYAN'!T37 -> 30 | U13: ='TITU S JAYAN'!U37 -> 26997 | V13: ='TITU S JAYAN'!V37 -> 31 | W13: ='TITU S JAYAN'!W37 -> 26997 | ... AC13: ='TITU S JAYAN'!AC37 -> 26997 | AN13: ='PROJECT MASTER FILE - COPY'!B130 | AP13: ='PROJECT MASTER FILE - COPY'!B13
A14: 11 | B14: Devika Prasad | C14: Project Associate (Community Development) | D14: CORE TEAM | E14: 33862 | F14: 28 | G14: 29899.333 | H14: 30.5 | I14: 31518.306 | J14: 30 | K14: =(E14/30)*J14 -> 33862 | L14: ='DEVIKA PRASAD'!L37 -> 31 | M14: ='DEVIKA PRASAD'!M37 -> 33862 | N14: ='DEVIKA PRASAD'!N37 -> 26.5 | O14: 28957 | P14: ='DEVIKA PRASAD'!P37 -> 28 | Q14: ='DEVIKA PRASAD'!Q37 -> 31604.533 | R14: ='DEVIKA PRASAD'!R37 -> 28.5 | S14: ='DEVIKA PRASAD'!S37 -> 31131.194 | T14: ='DEVIKA PRASAD'!T37 -> 30 | U14: ='DEVIKA PRASAD'!U37 -> 33862 | V14: ='DEVIKA PRASAD'!V37 -> 31 | W14: ='DEVIKA PRASAD'!W37 -> 33862 | ... AC14: ='DEVIKA PRASAD'!AC37 -> 33862 | AD14: Month | AF14: =AF2 -> HLL Malappuram | AG14: =AG2 -> Power Grid Corporation of India Limited - Yelahanka, Bangalore | AH14: =AH2 -> Cochin Shipyard Limited - Andaman | AI14: =AI2 -> IOCL - Panipat | AJ14: =AJ2 -> HLL Cotton Hill, Trivandrum | AK14: =AK2 -> Swasthya-An innovative behaviour change programme for Aneamia in women of reproductive age | AL14: =AL2 -> Counselling support for transgender individuals-pre and post surgery and non surgical pathways in gender transition | AM14: =AM2 -> Inclusive community mental health initiative in Wayanad district | ... AQ14: =AQ2 -> LSGB
A15: 12 | B15: K Anakha Soman | C15: Project Associate (Community Development) | D15: CORE TEAM | E15: 33862 | F15: 30 | G15: 32035 | H15: 31 | I15: 32035 | J15: 30 | K15: =(E15/30)*J15 -> 33862 | L15: ='K ANAKHA SOMAN'!L37 -> 31 | M15: ='K ANAKHA SOMAN'!M37 -> 33862 | N15: 0 | O15: 0 | P15: ='K ANAKHA SOMAN'!P37 -> 27 | Q15: ='K ANAKHA SOMAN'!Q37 -> 30475.8 | R15: ='K ANAKHA SOMAN'!R37 -> 31 | S15: ='K ANAKHA SOMAN'!S37 -> 33862 | T15: ='K ANAKHA SOMAN'!T37 -> 30 | U15: ='K ANAKHA SOMAN'!U37 -> 33862 | V15: ='K ANAKHA SOMAN'!V37 -> 31 | W15: ='K ANAKHA SOMAN'!W37 -> 33862 | ... AC15: ='K ANAKHA SOMAN'!AC37 -> 33862 | AD15: 45839 | AF15: =AF4/AE4*100 -> 0.72485087 | AG15: =$AG4/AE4/100 -> 0.00012173499 | AH15: =$AG4/AF4/100 -> 0.016794488 | AI15: =$AG4/AG4/100 -> 0.01 | AJ15: =$AG4/AH4/100 -> 0.0134544 | AK15: =$AG4/AI4/100 -> #DIV/0! | AL15: =$AG4/AJ4/100 -> #DIV/0! | AM15: =$AG4/AK4/100 -> 0.015134989 | AN15: =$AG4/AL4/100 -> 0.014308321 | ... AP15: =$AG4/AN4/100 -> #DIV/0! | AQ15: =AQ4/AE4*100 -> 93.946837
A16: 13 | B16: Jithin Dominic | C16: Project Associate (Community Development) | D16: CORE TEAM | E16: 32035 | F16: 27.5 | G16: 29365.417 | H16: 31 | I16: 32035 | J16: 30 | K16: =(E16/30)*J16 -> 32035 | L16: ='JITHIN DOMNIC'!L37 -> 30.5 | M16: 31521 | N16: ='JITHIN DOMNIC'!N37 -> 29 | O16: 31213 | P16: ='JITHIN DOMNIC'!P37 -> 29.5 | Q16: ='JITHIN DOMNIC'!Q37 -> 31501.083 | R16: ='JITHIN DOMNIC'!R37 -> 29.5 | S16: ='JITHIN DOMNIC'!S37 -> 30484.919 | T16: ='JITHIN DOMNIC'!T37 -> 30 | U16: ='JITHIN DOMNIC'!U37 -> 32035 | V16: ='JITHIN DOMNIC'!V37 -> 31 | W16: ='JITHIN DOMNIC'!W37 -> 32035 | ... AC16: ='JITHIN DOMNIC'!AC37 -> 32035 | AD16: 45870
A17: 14 | B17: Divya Vinod | C17: Project Associate (Public Health) | D17: CORE TEAM | E17: 33884 | F17: 30 | G17: 32035 | H17: 31 | I17: 32035 | J17: 30 | K17: 33862 | L17: ='DIVYA VINOD'!L37 -> 31 | M17: ='DIVYA VINOD'!M37 -> 33884 | N17: ='DIVYA VINOD'!N37 -> 31 | O17: 33862 | P17: ='DIVYA VINOD'!P37 -> 28 | Q17: ='DIVYA VINOD'!Q37 -> 31625.067 | R17: ='DIVYA VINOD'!R37 -> 16.5 | S17: ='DIVYA VINOD'!S37 -> 18035.032 | T17: ='DIVYA VINOD'!T37 -> 30 | U17: ='DIVYA VINOD'!U37 -> 33884 | V17: ='DIVYA VINOD'!V37 -> 31 | W17: ='DIVYA VINOD'!W37 -> 33884 | ... AC17: ='DIVYA VINOD'!AC37 -> 33884 | AD17: 45901 | AN17: ='PROJECT MASTER FILE - COPY'!B134 | AP17: ='PROJECT MASTER FILE - COPY'!B17
A18: 15 | B18: Sherin Jacob | C18: Project Associate (Public Health) | D18: CORE TEAM | E18: 33862 | F18: 29 | G18: 30967.167 | H18: 31 | I18: 32035 | J18: 30 | K18: =(E18/30)*J18 -> 33862 | L18: ='SHERIN JACOB'!L37 -> 29 | M18: 32770 | N18: ='SHERIN JACOB'!N37 -> 31 | O18: ='SHERIN JACOB'!O37 -> 33862 | P18: ='SHERIN JACOB'!P37 -> 27 | Q18: ='SHERIN JACOB'!Q37 -> 30475.8 | R18: ='SHERIN JACOB'!R37 -> 29.5 | S18: ='SHERIN JACOB'!S37 -> 32223.516 | T18: ='SHERIN JACOB'!T37 -> 30 | U18: ='SHERIN JACOB'!U37 -> 33862 | ... AC18: ='SHERIN JACOB'!AC37 -> 33862 | AD18: 45931 | AN18: ='PROJECT MASTER FILE - COPY'!B135 | AP18: ='PROJECT MASTER FILE - COPY'!B18
A19: 16 | B19: Lenita G Lawrence | C19: Project Associate (Public Health) | D19: CORE TEAM | E19: 32035 | F19: 30 | G19: 31974 | H19: 31 | I19: 31974 | J19: 30 | K19: =(E19/30)*J19 -> 32035 | L19: 0 | M19: 0 | N19: 0 | O19: 0 | P19: ='LENITA G LAWRENCE'!P37 -> 28 | Q19: ='LENITA G LAWRENCE'!Q37 -> 29899.333 | R19: ='LENITA G LAWRENCE'!R37 -> 29 | S19: ='LENITA G LAWRENCE'!S37 -> 29968.226 | T19: ='LENITA G LAWRENCE'!T37 -> 30 | U19: ='LENITA G LAWRENCE'!U37 -> 32035 | V19: ='LENITA G LAWRENCE'!V37 -> 31 | W19: ='LENITA G LAWRENCE'!W37 -> 32035 | ... AC19: ='LENITA G LAWRENCE'!AC37 -> 32035 | AD19: 45962 | AN19: ='PROJECT MASTER FILE - COPY'!B136 | AP19: ='PROJECT MASTER FILE - COPY'!B19
A20: 17 | B20: Anjaly V | C20: Project Facilitator | D20: CORE TEAM | E20: 32384 | F20: 30 | G20: 30635 | H20: 31 | I20: 30635 | J20: 30 | K20: =(E20/30)*J20 -> 32384 | L20: ='ANJALY V'!L37 -> 31 | M20: ='ANJALY V'!M37 -> 32384 | N20: ='ANJALY V'!N37 -> 31 | O20: ='ANJALY V'!O37 -> 32384 | P20: ='ANJALY V'!P37 -> 28 | Q20: ='ANJALY V'!Q37 -> 30225.067 | R20: ='ANJALY V'!R37 -> 28 | S20: ='ANJALY V'!S37 -> 29250.065 | ... AC20: ='ANJALY V'!AC37 -> 32384 | AD20: 45992 | AN20: ='PROJECT MASTER FILE - COPY'!B137 | AP20: ='PROJECT MASTER FILE - COPY'!B20
A21: 18 | B21: Syamili | C21: Admistrative Assistant (Projects) | D21: CORE TEAM | E21: 25318 | F21: 24 | G21: 20253.6 | H21: 31 | I21: 25317 | J21: 30 | K21: =(E21/30)*J21 -> 25318 | L21: =SYAMILI!L37 -> 31 | M21: =SYAMILI!M37 -> 25318 | N21: =SYAMILI!N37 -> 31 | O21: =SYAMILI!O37 -> 25318 | P21: =SYAMILI!P37 -> 28 | Q21: =SYAMILI!Q37 -> 23630.133 | R21: =SYAMILI!R37 -> 29.5 | S21: =SYAMILI!S37 -> 24092.935 | ... AC21: =SYAMILI!AC37 -> 25318 | AD21: 46023 | AN21: ='PROJECT MASTER FILE - COPY'!B138 | AP21: ='PROJECT MASTER FILE - COPY'!B21
A22: 19 | B22: Silpa | C22: Accounts Assistant | D22: CORE TEAM | E22: 24509 | F22: 10 | G22: 8169.3333 | H22: 30 | I22: 23717.419 | J22: 30 | K22: 24113 | L22: ='SILPA P L'!L37 -> 30.5 | M22: 24113 | N22: ='SILPA P L'!N37 -> 31 | O22: ='SILPA P L'!O37 -> 24509 | P22: ='SILPA P L'!P37 -> 26.5 | Q22: ='SILPA P L'!Q37 -> 21649.617 | R22: ='SILPA P L'!R37 -> 27.5 | S22: ='SILPA P L'!S37 -> 21741.855 | T22: ='SILPA P L'!T37 -> 30 | U22: ='SILPA P L'!U37 -> 24509 | ... AC22: ='SILPA P L'!AC37 -> 24509 | AD22: 46054 | AN22: ='PROJECT MASTER FILE - COPY'!B139 | AP22: ='PROJECT MASTER FILE - COPY'!B22
A23: 20 | B23: Neelima K N | C23: Administartive Assiatant (HR) | D23: CORE TEAM | E23: 25318 | F23: 10 | G23: 8169.3333 | H23: 30 | I23: 23717.419 | J23: 30 | K23: =(E23/30)*J23 -> 25318 | L23: ='NEELIMA K N'!L37 -> 31 | M23: ='NEELIMA K N'!M37 -> 25318 | N23: ='NEELIMA K N'!N37 -> 31 | O23: ='NEELIMA K N'!O37 -> 25318 | P23: ='NEELIMA K N'!P37 -> 28 | Q23: ='NEELIMA K N'!Q37 -> 23630.133 | R23: ='NEELIMA K N'!R37 -> 30.5 | S23: ='NEELIMA K N'!S37 -> 24909.645 | ... AC23: ='NEELIMA K N'!AC37 -> 25318 | AN23: ='PROJECT MASTER FILE - COPY'!B140 | AP23: ='PROJECT MASTER FILE - COPY'!B23
A24: 21 | B24: Vishnu | C24: Field Assistant | D24: CORE TEAM | E24: 21367 | F24: 0 | G24: 0 | H24: 19 | I24: 13095.903 | J24: 29.5 | K24: 21011 | L24: =VISHNU!L37 -> 22 | M24: 15182 | N24: =VISHNU!N37 -> 31 | O24: =VISHNU!O37 -> 21367 | P24: =VISHNU!P37 -> 27.5 | Q24: =VISHNU!Q37 -> 19586.417 | R24: =VISHNU!R37 -> 30.5 | S24: =VISHNU!S37 -> 21022.371 | T24: =VISHNU!T37 -> 30 | U24: =VISHNU!U37 -> 21367 | ... AC24: =VISHNU!AC37 -> 21367 | AD24: 46082 | AN24: ='PROJECT MASTER FILE - COPY'!B141 | AP24: ='PROJECT MASTER FILE - COPY'!B24
A25: 22 | B25: Jayalakshmi J | C25: Project Assistant | D25: CORE TEAM | E25: ='PROJECT MANPOWER'!E4 -> 24448 | J25: 0 | K25: 0 | L25: ='JAYALEKSHMI J'!L37 -> 18 | M25: ='JAYALEKSHMI J'!M37 -> 14195.613 | N25: ='JAYALEKSHMI J'!N37 -> 29 | O25: 22931
A26: 23 | B26: Arjuna V Nath | C26: Project Associate (Public Health) | D26: CORE TEAM | E26: ='PROJECT MANPOWER'!E17 -> 32035 | J26: 0 | K26: 0 | L26: ='ARJUNA V NATH'!L37 -> 31 | M26: ='ARJUNA V NATH'!M37 -> 32035 | N26: ='ARJUNA V NATH'!N37 -> 31 | O26: 32035
A27: 24 | B27: ='PROJECT MANPOWER'!B11 -> Swathy Krishna S | C27: ='PROJECT MANPOWER'!C11 -> Project Associate (Community Development) | D27: CORE TEAM | E27: ='PROJECT MANPOWER'!E11 -> 30186 | J27: 0 | K27: 0 | L27: ='SWATHY KRISHNA S'!L37 -> 30.5 | M27: ='SWATHY KRISHNA S'!M37 -> 29699.129 | N27: ='SWATHY KRISHNA S'!N37 -> 29.5 | O27: 28700
A28: 25 | B28: ='PROJECT MANPOWER'!B14 -> Bhavya R J | C28: ='PROJECT MANPOWER'!C14 -> Project Associate (Public Health) | D28: CORE TEAM | E28: ='PROJECT MANPOWER'!E14 -> 31762 | J28: 0 | K28: 0 | L28: ='BHAVYA R J'!L37 -> 30 | M28: ='BHAVYA R J'!M37 -> 30737.419 | N28: ='BHAVYA R J'!N37 -> 31 | O28: 32187
A29: 26 | B29: ='PROJECT MANPOWER'!B18 -> Rejitha Ravi | C29: ='PROJECT MANPOWER'!C18 -> Project Associate (Public Health) | D29: CORE TEAM | E29: ='PROJECT MANPOWER'!E18 -> 32035 | J29: 0 | K29: 0 | L29: ='REJITHA RAVI'!L37 -> 30 | M29: ='REJITHA RAVI'!M37 -> 31001.613
A30: 27 | B30: Anakha Joy | C30: Field Assistant | D30: CORE TEAM | E30: 21367 | F30: 0 | G30: 0 | H30: 0 | I30: 0 | J30: 29 | K30: 20658 | L30: ='ANAKHA JOY'!L37 -> 30 | M30: 20681 | N30: ='ANAKHA JOY'!N37 -> 27.5 | O30: 18961 | P30: ='ANAKHA JOY'!P37 -> 25 | Q30: ='ANAKHA JOY'!Q37 -> 17805.833 | R30: ='ANAKHA JOY'!R37 -> 29.5 | S30: ='ANAKHA JOY'!S37 -> 20333.113 | T30: ='ANAKHA JOY'!T37 -> 30 | U30: ='ANAKHA JOY'!U37 -> 21367 | V30: ='ANAKHA JOY'!V37 -> 31 | W30: ='ANAKHA JOY'!W37 -> 21367 | ... AC30: ='ANAKHA JOY'!AC37 -> 21367 | AN30: ='PROJECT MASTER FILE - COPY'!B142 | AP30: ='PROJECT MASTER FILE - COPY'!B25
E31: =SUM(E4:E30) -> 753558 | K31: =SUM(K4:K30) -> 593057 | M31: =SUM(M4:M30) -> 690762.77 | O31: =SUM(O4:O30) -> 632239 | AN31: ='PROJECT MASTER FILE - COPY'!B143 | AP31: ='PROJECT MASTER FILE - COPY'!B26

Sheet PROJECT MANPOWER
A1: SL No | B1: Name | C1: Designation | D1: Project | E1: Monthly CTC | F1: 45748 | H1: 45778 | J1: 45809 | L1: 45839 | N1: 45870 | P1: 45901 | R1: 45931 | T1: 45962 | V1: 45992 | X1: 46023 | Z1: 46054 | AB1: 46082
F2: Attendance | G2: Amount | H2: Attendance | I2: Amount | J2: Attendance | K2: Amount | L2: Attendance | M2: Amount | N2: Attendance | O2: Amount | P2: Attendance | Q2: Amount | R2: Attendance | S2: Amount | T2: Attendance | U2: Amount | V2: Attendance | W2: Amount | X2: Attendance | Y2: Amount | Z2: Attendance | AA2: Amount | AB2: Attendance | AC2: Amount | AD2: Month | AE2: Project 1 | AF2: Project 2 | AG2: Project 3 | AH2: Project 4 | AI2: Project 5 | AJ2: Project 6 | AK2: Project 7 | AL2: LSGB
A3: 1 | B3: Sushila | C3: Project Assistant | D3: IOCL CSR HARYANA | E3: 24530 | F3: 30 | G3: 24523 | H3: 31 | I3: 24523 | J3: 30 | K3: =(E3/30)*J3 -> 24530 | L3: =SUSHILA!L37 -> 31 | M3: =SUSHILA!M37 -> 24530 | N3: =SUSHILA!N37 -> 31 | O3: =SUSHILA!O37 -> 24530 | P3: =SUSHILA!P37 -> 30 | Q3: =SUSHILA!Q37 -> 24530 | R3: =SUSHILA!R37 -> 31 | S3: =SUSHILA!S37 -> 24530 | ... AC3: =SUSHILA!AC37 -> 24530 | AD3: 45839
A4: 2 | B4: Jayalekshmi J | C4: Project Assistant | D4: LSGB | E4: 24448 | F4: 30 | G4: 24509 | H4: 31 | I4: 24509 | J4: 30 | K4: 24509 | L4: 0 | M4: 0 | N4: 0 | O4: 0 | P4: ='JAYALEKSHMI J'!P37 -> 26.5 | Q4: ='JAYALEKSHMI J'!Q37 -> 21595.733 | R4: ='JAYALEKSHMI J'!R37 -> 29 | S4: ='JAYALEKSHMI J'!S37 -> 22870.71 | T4: ='JAYALEKSHMI J'!T37 -> 30 | U4: ='JAYALEKSHMI J'!U37 -> 24448 | V4: ='JAYALEKSHMI J'!V37 -> 31 | W4: ='JAYALEKSHMI J'!W37 -> 24448 | ... AC4: ='JAYALEKSHMI J'!AC37 -> 24448 | AD4: 45870
A5: 3 | B5: Mariyathul Hibthiya | C5: Project Associate | D5: LSGB | E5: 30156 | F5: 30 | G5: 30096 | H5: 31 | I5: 30096 | J5: 31 | K5: 30096 | L5: ='MARIYATHUL HIBITHYA'!L37 -> 31 | M5: ='MARIYATHUL HIBITHYA'!M37 -> 30156 | N5: ='MARIYATHUL HIBITHYA'!N37 -> 31 | O5: ='MARIYATHUL HIBITHYA'!O37 -> 30156 | P5: ='MARIYATHUL HIBITHYA'!P37 -> 25 | Q5: ='MARIYATHUL HIBITHYA'!Q37 -> 25130 | R5: ='MARIYATHUL HIBITHYA'!R37 -> 31 | S5: ='MARIYATHUL HIBITHYA'!S37 -> 30156 | ... AC5: ='MARIYATHUL HIBITHYA'!AC37 -> 30156 | AD5: 45901
A6: 4 | B6: Ruksana Beegum Pakkichippura | C6: Project Associate | D6: LSGB | E6: 30156 | F6: 30 | G6: 30096 | H6: 31 | I6: 30096 | J6: 31 | K6: 30096 | L6: ='RUKSANA BEEGUM'!L37 -> 16 | M6: 15593 | N6: ='RUKSANA BEEGUM'!N37 -> 0 | O6: ='RUKSANA BEEGUM'!O37 -> 0 | P6: ='RUKSANA BEEGUM'!P37 -> 0 | Q6: ='RUKSANA BEEGUM'!Q37 -> 0 | R6: ='RUKSANA BEEGUM'!R37 -> 31 | S6: ='RUKSANA BEEGUM'!S37 -> 30156 | T6: ='RUKSANA BEEGUM'!T37 -> 30 | U6: ='RUKSANA BEEGUM'!U37 -> 30156 | ... AC6: ='RUKSANA BEEGUM'!AC37 -> 30156 | AD6: 45931
A7: 5 | B7: Abhirami N A | C7: Project Associate (Community Development) | D7: LSGB | E7: 31762 | F7: 25 | G7: 26468.333 | H7: 24 | I7: 24589.935 | J7: 24.5 | K7: 31762 | L7: ='ABHIRAMI N A '!L37 -> 0 | M7: ='ABHIRAMI N A '!M37 -> 0 | N7: ='ABHIRAMI N A '!N37 -> 31 | O7: 60706 | P7: ='ABHIRAMI N A '!P37 -> 30 | Q7: ='ABHIRAMI N A '!Q37 -> 31762 | R7: ='ABHIRAMI N A '!R37 -> 31 | S7: ='ABHIRAMI N A '!S37 -> 31762 | T7: ='ABHIRAMI N A '!T37 -> 30 | U7: ='ABHIRAMI N A '!U37 -> 31762 | V7: ='ABHIRAMI N A '!V37 -> 31 | W7: ='ABHIRAMI N A '!W37 -> 31762 | ... AC7: ='ABHIRAMI N A '!AC37 -> 31762 | AD7: 45962
A8: 6 | B8: Jayalekshmi M J | C8: Project Associate (Community Development) | D8: LSGB | E8: 33862 | F8: 30 | G8: 32035 | H8: 30.5 | I8: 31518.306 | J8: 30 | K8: 32035 | L8: ='JAYALAKSHMI M J'!L37 -> 31 | M8: ='JAYALAKSHMI M J'!M37 -> 33862 | N8: ='JAYALAKSHMI M J'!N37 -> 31 | O8: ='JAYALAKSHMI M J'!O37 -> 33862 | P8: ='JAYALAKSHMI M J'!P37 -> 30 | Q8: ='JAYALAKSHMI M J'!Q37 -> 33862 | R8: ='JAYALAKSHMI M J'!R37 -> 30 | S8: ='JAYALAKSHMI M J'!S37 -> 32769.677 | ... AC8: ='JAYALAKSHMI M J'!AC37 -> 33862 | AD8: 45992
A9: 7 | B9: Anjali A S | C9: Project Associate (Community Development) | D9: LSGB | E9: 30156 | F9: 30 | G9: 31064 | H9: 31 | I9: 31064 | J9: 29.5 | K9: 31064 | L9: ='ANJALY A S'!L37 -> 30 | M9: 29186 | N9: ='ANJALY A S'!N37 -> 31 | O9: ='ANJALY A S'!O37 -> 30156 | P9: ='ANJALY A S'!P37 -> 28.5 | Q9: ='ANJALY A S'!Q37 -> 28648.2 | R9: ='ANJALY A S'!R37 -> 30 | S9: ='ANJALY A S'!S37 -> 29183.226 | T9: ='ANJALY A S'!T37 -> 30 | U9: ='ANJALY A S'!U37 -> 30156 | ... AC9: ='ANJALY A S'!AC37 -> 30156 | AD9: 46023
A10: 8 | B10: Rakhi Mohan | C10: Project Associate (Community Development) | D10: LSGB | E10: 30156 | F10: 28 | G10: 28993.067 | H10: 31 | I10: 31064 | J10: 30 | K10: 31064 | L10: ='RAKHI MOHAN'!L37 -> 31 | M10: ='RAKHI MOHAN'!M37 -> 30156 | N10: ='RAKHI MOHAN'!N37 -> 29.5 | O10: 28700 | P10: ='RAKHI MOHAN'!P37 -> 29.5 | Q10: ='RAKHI MOHAN'!Q37 -> 29653.4 | R10: ='RAKHI MOHAN'!R37 -> 28 | S10: ='RAKHI MOHAN'!S37 -> 27237.677 | T10: ='RAKHI MOHAN'!T37 -> 30 | U10: ='RAKHI MOHAN'!U37 -> 30156 | V10: ='RAKHI MOHAN'!V37 -> 31 | W10: ='RAKHI MOHAN'!W37 -> 30156 | ... AC10: ='RAKHI MOHAN'!AC37 -> 30156 | AD10: 46054
A11: 9 | B11: Swathy Krishna S | C11: Project Associate (Community Development) | D11: LSGB | E11: 30186 | F11: 29.5 | G11: 29653.4 | H11: 26 | I11: 25292.129 | J11: 28 | K11: 30156 | L11: 0 | M11: 0 | N11: 0 | O11: 0 | P11: ='SWATHY KRISHNA S'!P37 -> 28 | Q11: ='SWATHY KRISHNA S'!Q37 -> 28173.6 | R11: ='SWATHY KRISHNA S'!R37 -> 29.5 | S11: ='SWATHY KRISHNA S'!S37 -> 28725.387 | T11: ='SWATHY KRISHNA S'!T37 -> 30 | U11: ='SWATHY KRISHNA S'!U37 -> 30186 | V11: ='SWATHY KRISHNA S'!V37 -> 31 | W11: ='SWATHY KRISHNA S'!W37 -> 30186 | ... AC11: ='SWATHY KRISHNA S'!AC37 -> 30186 | AD11: 46082
A12: 10 | B12: Alka Wadhwa | C12: Project Associate (Public Health) | D12: IOCL CSR HARYANA | E12: 30156 | F12: 30 | G12: 30170 | H12: 31 | I12: 30170 | J12: 30 | K12: 30170 | L12: ='ALKA WADHWA'!L37 -> 31 | M12: ='ALKA WADHWA'!M37 -> 30156 | N12: ='ALKA WADHWA'!N37 -> 31 | O12: 30177 | P12: ='ALKA WADHWA'!P37 -> 30 | Q12: ='ALKA WADHWA'!Q37 -> 30156 | R12: ='ALKA WADHWA'!R37 -> 31 | S12: ='ALKA WADHWA'!S37 -> 30156 | T12: ='ALKA WADHWA'!T37 -> 30 | U12: ='ALKA WADHWA'!U37 -> 30156 | V12: ='ALKA WADHWA'!V37 -> 31 | W12: ='ALKA WADHWA'!W37 -> 30156 | ... AC12: ='ALKA WADHWA'!AC37 -> 30156
A13: 11 | B13: Sarika P S Krishna | C13: Project Associate (Public Health) | D13: LSGB | E13: 31762 | F13: 30 | G13: 31762 | H13: 31 | I13: 31762 | J13: 30 | K13: 31762 | L13: ='SARIKA P S KRISHNA'!L37 -> 31 | M13: ='SARIKA P S KRISHNA'!M37 -> 32303.935 | N13: ='SARIKA P S KRISHNA'!N37 -> 31 | O13: =22556+9631 -> 32187 | P13: ='SARIKA P S KRISHNA'!P37 -> 27.5 | Q13: ='SARIKA P S KRISHNA'!Q37 -> 29640.167 | R13: ='SARIKA P S KRISHNA'!R37 -> 30 | S13: ='SARIKA P S KRISHNA'!S37 -> 31347.097 | T13: ='SARIKA P S KRISHNA'!T37 -> 30 | U13: ='SARIKA P S KRISHNA'!U37 -> 32322 | V13: ='SARIKA P S KRISHNA'!V37 -> 31 | W13: ='SARIKA P S KRISHNA'!W37 -> 32371.677 | ... AC13: ='SARIKA P S KRISHNA'!AC37 -> 32371.677
A14: 12 | B14: Bhavya R J | C14: Project Associate (Public Health) | D14: LSGB | E14: 31762 | F14: 27 | G14: 28585.8 | H14: 30 | I14: 30737.419 | J14: 30 | K14: 31762 | L14: 0 | M14: 0 | N14: 0 | O14: 0 | P14: ='BHAVYA R J'!P37 -> 27.5 | Q14: ='BHAVYA R J'!Q37 -> 29115.167 | R14: ='BHAVYA R J'!R37 -> 28 | S14: ='BHAVYA R J'!S37 -> 28688.258 | T14: ='BHAVYA R J'!T37 -> 30 | U14: ='BHAVYA R J'!U37 -> 31762 | V14: ='BHAVYA R J'!V37 -> 31 | W14: ='BHAVYA R J'!W37 -> 31762 | ... AC14: ='BHAVYA R J'!AC37 -> 31762
A15: 13 | B15: Jesna C | C15: Project Associate (Public Health) | D15: LSGB | E15: 31762 | F15: 29 | G15: 30703.267 | H15: 31 | I15: 31762 | J15: 30 | K15: 31762 | L15: ='JESNA C'!L37 -> 31 | M15: ='JESNA C'!M37 -> 31762 | N15: ='JESNA C'!N37 -> 31 | O15: ='JESNA C'!O37 -> 31762 | P15: ='JESNA C'!P37 -> 30 | Q15: ='JESNA C'!Q37 -> 31762 | R15: ='JESNA C'!R37 -> 31 | S15: ='JESNA C'!S37 -> 31762 | ... AC15: ='JESNA C'!AC37 -> 31762
A16: 14 | B16: Rasna K S | C16: Project Associate (Public Health) | D16: HLL CSR COTTON HILL | E16: 31762 | F16: 30 | G16: 31762 | H16: 29.5 | I16: 30225.129 | J16: 30 | K16: 31762 | L16: ='RASNA K S'!L37 -> 30 | M16: 30739 | N16: ='RASNA K S'!N37 -> 29.5 | O16: 30226 | P16: ='RASNA K S'!P37 -> 29 | Q16: ='RASNA K S'!Q37 -> 30703.267 | R16: ='RASNA K S'!R37 -> 29 | S16: ='RASNA K S'!S37 -> 29712.839 | T16: ='RASNA K S'!T37 -> 30 | U16: ='RASNA K S'!U37 -> 31762 | V16: ='RASNA K S'!V37 -> 31 | W16: ='RASNA K S'!W37 -> 31762 | ... AC16: ='RASNA K S'!AC37 -> 31762
A17: 15 | B17: Arjuna V Nath | C17: Project Associate (Public Health) | D17: LSGB | E17: 32035 | F17: 30 | G17: 32035 | H17: 31 | I17: 32035 | J17: 30 | K17: 32035 | L17: 0 | M17: 0 | N17: 0 | O17: 0 | P17: ='ARJUNA V NATH'!P37 -> 27.5 | Q17: ='ARJUNA V NATH'!Q37 -> 29365.417 | R17: ='ARJUNA V NATH'!R37 -> 29 | S17: ='ARJUNA V NATH'!S37 -> 29968.226 | T17: ='ARJUNA V NATH'!T37 -> 30 | U17: ='ARJUNA V NATH'!U37 -> 32035 | V17: ='ARJUNA V NATH'!V37 -> 31 | W17: ='ARJUNA V NATH'!W37 -> 32035 | ... AC17: ='ARJUNA V NATH'!AC37 -> 32035
A18: 16 | B18: Rejitha Ravi | C18: Project Associate (Public Health) | D18: HLL CSR Navajeevana , Wayanad | E18: 32035 | F18: 29.5 | G18: 31501.083 | H18: 31 | I18: 32035 | J18: 30 | K18: 32035 | L18: 0 | M18: 0 | N18: ='REJITHA RAVI'!N37 -> 29.5 | O18: 30490 | P18: ='REJITHA RAVI'!P37 -> 30 | Q18: ='REJITHA RAVI'!Q37 -> 32035 | R18: ='REJITHA RAVI'!R37 -> 29.5 | S18: ='REJITHA RAVI'!S37 -> 30484.919 | T18: ='REJITHA RAVI'!T37 -> 30 | U18: ='REJITHA RAVI'!U37 -> 32035 | V18: ='REJITHA RAVI'!V37 -> 31 | W18: ='REJITHA RAVI'!W37 -> 32035 | ... AC18: ='REJITHA RAVI'!AC37 -> 32035
A19: 17 | B19: Anjali Prakash K | C19: Project Associate (Public Health) | D19: HLL CSR SWASTHYA | E19: 30156 | F19: 30 | G19: 30156 | H19: 31 | I19: 30156 | J19: 22 | K19: 30156 | L19: ='ANJALI PRAKASH K'!L37 -> 27 | M19: 26273 | N19: ='ANJALI PRAKASH K'!N37 -> 31 | O19: ='ANJALI PRAKASH K'!O37 -> 30156 | P19: ='ANJALI PRAKASH K'!P37 -> 30 | Q19: ='ANJALI PRAKASH K'!Q37 -> 30156 | R19: ='ANJALI PRAKASH K'!R37 -> 29 | S19: ='ANJALI PRAKASH K'!S37 -> 28210.452 | T19: ='ANJALI PRAKASH K'!T37 -> 30 | U19: ='ANJALI PRAKASH K'!U37 -> 30156 | ... AC19: ='ANJALI PRAKASH K'!AC37 -> 30156
A20: 18 | B20: Ashwini Bhausaheb Ranjane | C20: Project Associate (Public Health) | D20: HLL CSR Maharashtra | E20: 30156 | F20: 30 | G20: 30096 | H20: 31 | I20: 30096 | J20: 30 | K20: 30096 | L20: ='ASHWINI RANJANE'!L37 -> 31 | M20: ='ASHWINI RANJANE'!M37 -> 30156 | N20: ='ASHWINI RANJANE'!N37 -> 31 | O20: 30096 | P20: ='ASHWINI RANJANE'!P37 -> 29 | Q20: ='ASHWINI RANJANE'!Q37 -> 29150.8 | R20: ='ASHWINI RANJANE'!R37 -> 29 | S20: ='ASHWINI RANJANE'!S37 -> 28210.452 | T20: ='ASHWINI RANJANE'!T37 -> 30 | U20: ='ASHWINI RANJANE'!U37 -> 30156 | V20: ='ASHWINI RANJANE'!V37 -> 31 | W20: ='ASHWINI RANJANE'!W37 -> 30156 | ... AC20: ='ASHWINI RANJANE'!AC37 -> 30156
A21: 19 | B21: Arathy A S Kumar | C21: Project Associate | D21: LSGB | E21: 30156 | F21: 0 | G21: 0 | H21: 11 | I21: 10700.516 | J21: 30 | K21: 30156 | L21: ='ARATHY A S KUMAR'!L37 -> 30.5 | M21: 29670 | N21: ='ARATHY A S KUMAR'!N37 -> 8 | O21: 7827 | P21: ='ARATHY A S KUMAR'!P37 -> 30 | Q21: ='ARATHY A S KUMAR'!Q37 -> 30156 | R21: ='ARATHY A S KUMAR'!R37 -> 31 | S21: ='ARATHY A S KUMAR'!S37 -> 30156 | T21: ='ARATHY A S KUMAR'!T37 -> 30 | U21: ='ARATHY A S KUMAR'!U37 -> 30156 | V21: ='ARATHY A S KUMAR'!V37 -> 31 | W21: ='ARATHY A S KUMAR'!W37 -> 30156 | ... AC21: ='ARATHY A S KUMAR'!AC37 -> 30156
A22: 20 | B22: Juhaina C K | C22: Project Associate | D22: HLL CSR MALAPPURAM | E22: 30156 | F22: 0 | G22: 0 | H22: 6 | I22: 5836.6452 | J22: 30 | K22: 30156 | L22: ='JUHAINA C K'!L37 -> 31 | M22: ='JUHAINA C K'!M37 -> 30156 | N22: ='JUHAINA C K'!N37 -> 31 | O22: ='JUHAINA C K'!O37 -> 30156 | P22: ='JUHAINA C K'!P37 -> 30 | Q22: ='JUHAINA C K'!Q37 -> 30156 | R22: ='JUHAINA C K'!R37 -> 31 | S22: ='JUHAINA C K'!S37 -> 30156 | ... AC22: ='JUHAINA C K'!AC37 -> 30156
A23: 21 | B23: Sakshi Baliram Savare | C23: Project Assistant | D23: HLL CSR MAHARASHTRA | E23: 24509 | F23: 0 | G23: 0 | H23: 6 | I23: 4743.4839 | J23: 15 | K23: 24508 | L23: ='SAKSHI BALRAM SAVRE'!L34 -> 0 | M23: ='SAKSHI BALRAM SAVRE'!M34 -> 0 | N23: ='SAKSHI BALRAM SAVRE'!N34 -> 0 | O23: ='SAKSHI BALRAM SAVRE'!O34 -> 0 | P23: ='SAKSHI BALRAM SAVRE'!P34 -> 30 | Q23: ='SAKSHI BALRAM SAVRE'!Q34 -> 24508 | R23: ='SAKSHI BALRAM SAVRE'!R34 -> 31 | S23: ='SAKSHI BALRAM SAVRE'!S34 -> 24508 | ... AC23: ='SAKSHI BALRAM SAVRE'!AC34 -> 24508
A24: 22 | B24: Rakhee | C24: Project Assistant | D24: CSL, Andaman | E24: 24509 | F24: 0 | G24: 0 | H24: 0 | I24: 0 | J24: 19 | K24: 24508 | L24: =RAKHEE!L37 -> 31 | M24: =RAKHEE!M37 -> 24509 | N24: =RAKHEE!N37 -> 31 | O24: =RAKHEE!O37 -> 24509 | P24: =RAKHEE!P37 -> 30 | Q24: =RAKHEE!Q37 -> 24509 | R24: =RAKHEE!R37 -> 31 | S24: =RAKHEE!S37 -> 24509 | ... AC24: =RAKHEE!AC37 -> 24509
A25: 23 | B25: Navya M | C25: Project Associate | D25: Powergrid CSR Thinkal | E25: 30156 | F25: 0 | G25: 0 | H25: 0 | I25: 0 | J25: 15 | K25: 30156 | L25: ='NAVYA M'!L37 -> 31 | M25: ='NAVYA M'!M37 -> 30156 | N25: ='NAVYA M'!N37 -> 31 | O25: ='NAVYA M'!O37 -> 30156 | P25: ='NAVYA M'!P37 -> 30 | Q25: ='NAVYA M'!Q37 -> 30156 | R25: ='NAVYA M'!R37 -> 31 | S25: ='NAVYA M'!S37 -> 30156 | ... AC25: ='NAVYA M'!AC37 -> 30156
A26: 24 | B26: Ajila Mohan N J | C26: Project Associate | D26: LSGB | E26: 30156 | F26: 0 | G26: 0 | H26: 20 | I26: 19455.484 | J26: 30 | K26: 30156 | L26: ='AJILA MOHAN N J'!L37 -> 31 | M26: ='AJILA MOHAN N J'!M37 -> 30156 | N26: ='AJILA MOHAN N J'!N37 -> 31 | O26: ='AJILA MOHAN N J'!O37 -> 30156 | P26: ='AJILA MOHAN N J'!P37 -> 30 | Q26: ='AJILA MOHAN N J'!Q37 -> 30156 | R26: ='AJILA MOHAN N J'!R37 -> 30 | S26: ='AJILA MOHAN N J'!S37 -> 29183.226 | ... AC26: ='AJILA MOHAN N J'!AC37 -> 30156
A27: 25 | B27: Lenita Lawrance | C27: Project Associate | D27: LSGB | E27: ='LENITA G LAWRENCE'!D36 -> 32035 | J27: 0 | K27: 0 | L27: ='LENITA G LAWRENCE'!L37 -> 31 | M27: ='LENITA G LAWRENCE'!M37 -> 32035 | N27: ='LENITA G LAWRENCE'!N37 -> 31 | O27: 32035
A28: 26 | B28: Chaithra | C28: Project Assistant | D28: Powergrid CSR Thinkal | E28: 24509 | J28: 0 | L28: =CHAITRA!L37 -> 18 | M28: 14256 | N28: =CHAITRA!N37 -> 31 | O28: =CHAITRA!O37 -> 24509 | P28: =CHAITRA!P37 -> 30 | Q28: =CHAITRA!Q37 -> 24509 | R28: =CHAITRA!R37 -> 31 | S28: =CHAITRA!S37 -> 24509 | T28: =CHAITRA!T37 -> 30 | U28: =CHAITRA!U37 -> 24509 | ... AC28: =CHAITRA!AC37 -> 24509
A29: 27 | B29: Monali Dinesh | C29: Project Assistant | D29: HLL CSR Maharashtra | E29: 24509 | J29: 0 | K29: 0 | L29: 0 | M29: 0 | N29: =Monali!N37 -> 20 | O29: 15834 | P29: =Monali!P37 -> 30 | Q29: =Monali!Q37 -> 24509 | R29: =Monali!R37 -> 31 | S29: =Monali!S37 -> 24509 | T29: =Monali!T37 -> 30 | U29: =Monali!U37 -> 24509 | V29: =Monali!V37 -> 31 | W29: =Monali!W37 -> 24509 | ... AC29: =Monali!AC37 -> 24509
A30: 28 | B30: ='CORE MANPOWER'!B15 -> K Anakha Soman | C30: ='CORE MANPOWER'!C15 -> Project Associate (Community Development) | D30: HLL CSR Ekatwa | E30: ='CORE MANPOWER'!E15 -> 33862 | F30: ='CORE MANPOWER'!F15 -> 30 | G30: ='CORE MANPOWER'!G15 -> 32035 | H30: ='CORE MANPOWER'!H15 -> 31 | I30: ='CORE MANPOWER'!I15 -> 32035 | J30: 0 | K30: 0 | L30: 0 | M30: 0 | N30: ='K ANAKHA SOMAN'!N37 -> 31 | O30: ='K ANAKHA SOMAN'!O37 -> 33862 | P30: ='CORE MANPOWER'!P15 -> 27 | Q30: ='CORE MANPOWER'!Q15 -> 30475.8 | R30: ='CORE MANPOWER'!R15 -> 31 | S30: ='CORE MANPOWER'!S15 -> 33862 | T30: ='CORE MANPOWER'!T15 -> 30 | U30: ='CORE MANPOWER'!U15 -> 33862 | V30: ='CORE MANPOWER'!V15 -> 31 | W30: ='CORE MANPOWER'!W15 -> 33862 | ... AC30: ='CORE MANPOWER'!AC15 -> 33862
E31: =SUM(E3:E28) -> 773184 | M31: =SUM(M3:M29) -> 535810.94 | O31: =SUM(O3:O30) -> 652248 | Q31: =SUM(Q3:Q29) -> 714097.75 | S31: =SUM(S3:S29) -> 743617.15 | U31: =SUM(U3:U29) -> 766217 | W31: =SUM(W3:W29) -> 766266.68 | Y31: =SUM(Y3:Y29) -> 766266.68 | AA31: =SUM(AA3:AA29) -> 766107 | AC31: =SUM(AC3:AC29) -> 766266.68

Sheet JUNE PROJECT MANPOWER
A1: SL No | B1: Name | C1: Designation | D1: Project | E1: Monthly CTC | F1: 45748 | H1: 45778 | J1: 45809
F2: Attendance | G2: Amount | H2: Attendance | I2: Amount | J2: Attendance | K2: Amount
A3: 1 | B3: Sushila | C3: Project Assistant | D3: IOCL CSR HARYANA | E3: 24530 | F3: 30 | G3: 24523 | H3: 31 | I3: 24523 | J3: 30 | K3: 24530
A4: 2 | B4: Jayalekshmi J | C4: Project Assistant | D4: LSGB | E4: 24448 | F4: 30 | G4: 24509 | H4: 31 | I4: 24509 | J4: 30 | K4: 24509
A5: 3 | B5: Mariyathul Hibthiya | C5: Project Associate | D5: IOCL LAKSWADEEP | E5: 30156 | F5: 30 | G5: 30096 | H5: 31 | I5: 30096 | J5: 31 | K5: =(E5/31)*J5 -> 30156
A6: 4 | B6: Ruksana Beegum Pakkichippura | C6: Project Associate | D6: IOCL LAKSWADEEP | E6: 30156 | F6: 30 | G6: 30096 | H6: 31 | I6: 30096 | J6: 31 | K6: 30096
A7: 5 | B7: Abhirami N A | C7: Project Associate (Community Development) | D7: LSGB | E7: 31762 | F7: 25 | G7: 26468.333 | H7: 24 | I7: 24589.935 | J7: 24.5 | K7: 27149
A8: 6 | B8: Jayalekshmi M J | C8: Project Associate (Community Development) | D8: LSGB | E8: 33862 | F8: 30 | G8: 32035 | H8: 30.5 | I8: 31518.306 | J8: 30 | K8: 33862
A9: 7 | B9: Anjali A S | C9: Project Associate (Community Development) | D9: LSGB | E9: 30156 | F9: 30 | G9: 31064 | H9: 31 | I9: 31064 | J9: 29.5 | K9: 29653
A10: 8 | B10: Rakhi Mohan | C10: Project Associate (Community Development) | D10: LSGB | E10: 30156 | F10: 28 | G10: 28993.067 | H10: 31 | I10: 31064 | J10: 30 | K10: 30156
A11: 9 | B11: Swathy Krishna S | C11: Project Associate (Community Development) | D11: LSGB | E11: 30186 | F11: 29.5 | G11: 29653.4 | H11: 26 | I11: 25292.129 | J11: 28 | K11: 28150
A12: 10 | B12: Alka Wadhwa | C12: Project Associate (Public Health) | D12: IOCL CSR HARYANA | E12: 30156 | F12: 30 | G12: 30170 | H12: 31 | I12: 30170 | J12: 30 | K12: 30177
A13: 11 | B13: Sarika P S Krishna | C13: Project Associate (Public Health) | D13: LSGB | E13: 31762 | F13: 30 | G13: 31762 | H13: 31 | I13: 31762 | J13: 30 | K13: 31762
A14: 12 | B14: Bhavya R J | C14: Project Associate (Public Health) | D14: LSGB | E14: 31762 | F14: 27 | G14: 28585.8 | H14: 30 | I14: 30737.419 | J14: 30 | K14: 31762
A15: 13 | B15: Jesna C | C15: Project Associate (Public Health) | D15: LSGB | E15: 31762 | F15: 29 | G15: 30703.267 | H15: 31 | I15: 31762 | J15: 30 | K15: 31762
A16: 14 | B16: Rasna K S | C16: Project Associate (Public Health) | D16: LSGB | E16: 31762 | F16: 30 | G16: 31762 | H16: 29.5 | I16: 30225.129 | J16: 30 | K16: 31762
A17: 15 | B17: Arjuna V Nath | C17: Project Associate (Public Health) | D17: LSGB | E17: 32035 | F17: 30 | G17: 32035 | H17: 31 | I17: 32035 | J17: 30 | K17: 32035
... A26: 24 | B26: Ajila Mohan N J | C26: Project Associate | D26: LSGB | E26: 30156 | F26: 0 | G26: 0 | H26: 20 | I26: 19455.484 | J26: 30 | K26: 30156
A27: 25 | B27: Jijo S Pramod | C27: Project Associate | D27: LSGB | E27: 33862 | J27: 6 | K27: 6819
A28: 25 | B28: Greeshma Kuriakose | C28: Project Associate | D28: LSGB | E28: 30096 | J28: 18 | K28: 18059
E29: =SUM(E5:E28) -> 731620 | K29: =SUM(K3:K28) -> 690158

Sheet JULY 2025 ADMIN EXPENSES
I1: HR @ 5% CSR | W1: ADMIN CHARGES TOTAL | AH1: TOTAL | AI1: BALANCE
A2: Sl No | B2: Vendor | C2: Service | D2: Payment frequency | E2: Annual commitment | F2: Monthly Average | G2: Actual expense | I2: ='CORE MANPOWER'!AF2 -> HLL Malappuram | J2: ='CORE MANPOWER'!AG2 -> Power Grid Corporation of India Limited - Yelahanka, Bangalore | K2: ='CORE MANPOWER'!AH2 -> Cochin Shipyard Limited - Andaman | L2: ='CORE MANPOWER'!AI2 -> IOCL - Panipat | M2: ='CORE MANPOWER'!AJ2 -> HLL Cotton Hill, Trivandrum | N2: ='CORE MANPOWER'!AK2 -> Swasthya-An innovative behaviour change programme for Aneamia in women of reproductive age | O2: ='CORE MANPOWER'!AL2 -> Counselling support for transgender individuals-pre and post surgery and non surgical pathways in gender transition | P2: ='CORE MANPOWER'!AM2 -> Inclusive community mental health initiative in Wayanad district | ... S2: ='CORE MANPOWER'!AP2 -> HLL Maharashtra | T2: LSGB | U2: Additional LSGB | V2: Month | W2: ='CORE MANPOWER'!AF2 -> HLL Malappuram | X2: ='CORE MANPOWER'!AG2 -> Power Grid Corporation of India Limited - Yelahanka, Bangalore | Y2: ='CORE MANPOWER'!AH2 -> Cochin Shipyard Limited - Andaman | Z2: ='CORE MANPOWER'!AI2 -> IOCL - Panipat | AA2: ='CORE MANPOWER'!AJ2 -> HLL Cotton Hill, Trivandrum | AB2: ='CORE MANPOWER'!AK2 -> Swasthya-An innovative behaviour change programme for Aneamia in women of reproductive age | AC2: ='CORE MANPOWER'!AL2 -> Counselling support for transgender individuals-pre and post surgery and non surgical pathways in gender transition | AD2: ='CORE MANPOWER'!AM2 -> Inclusive community mental health initiative in Wayanad district | ... AG2: ='CORE MANPOWER'!AP2 -> HLL Maharashtra | AH2: HMA HR REVENUE | AI2: LSGB
A3: 1 | B3: Manjith Travels | C3: Contract Vehicle | D3: Monthly | E3: =F3*12 -> 523932 | F3: 43661 | G3: 43661 | H3: =SUM(F3:F8) -> 107841 | I3: ='PROJECT MASTER FILE - COPY'!$O17/H3*F3 -> 4534.5844 | J3: ='PROJECT MASTER FILE - COPY'!O30/H3*F3 -> 4534.5844 | K3: ='PROJECT MASTER FILE - COPY'!O43/H3*F3 -> 4534.5844 | L3: ='PROJECT MASTER FILE - COPY'!O56/H3*F3 -> 0 | M3: ='PROJECT MASTER FILE - COPY'!O69/H3*F3 -> 0 | N3: ='PROJECT MASTER FILE - COPY'!O82/H3*F3 -> 4534.5844 | O3: ='PROJECT MASTER FILE - COPY'!O95/H3*F3 -> 0 | P3: ='PROJECT MASTER FILE - COPY'!O108/H3*F3 -> 0 | Q3: 0 | R3: ='PROJECT MASTER FILE - COPY'!O134/H3*F3 -> 0 | S3: ='PROJECT MASTER FILE - COPY'!O4/H3*F3 -> 0 | T3: =F3- (I3+J3+K3+L3+M3+N3+O3+P3+Q3+R3+S3) -> 25522.662 | U3: =G3-F3 -> 0 | V3: 45839 | W3: ='PROJECT MASTER FILE - COPY'!O18 -> 0 | X3: ='PROJECT MASTER FILE - COPY'!O31 -> 0 | Y3: ='PROJECT MASTER FILE - COPY'!O44 -> 0 | Z3: ='PROJECT MASTER FILE - COPY'!O57 -> 0 | AA3: ='PROJECT MASTER FILE - COPY'!O70 -> 0 | AB3: ='PROJECT MASTER FILE - COPY'!O83 -> 0 | AC3: ='PROJECT MASTER FILE - COPY'!O96 -> 0 | AD3: ='PROJECT MASTER FILE - COPY'!O109 -> 0 | AE3: ='PROJECT MASTER FILE - COPY'!O122 -> 8333.3333 | AF3: 0 | AG3: ='PROJECT MASTER FILE - COPY'!O5 -> 0 | AH3: ='HMA HR REVNUE SHEET'!J6 -> 60000 | AI3: =G10-(W3+X3+Y3+AC3+AD3+AE3+AG3+AH3) -> 50766.667
A4: 2 | B4: Alchemy IBS | C4: Website | D4: Monthly | E4: 200000 | F4: 0 | I4: ='PROJECT MASTER FILE - COPY'!O17/H3*F4 -> 0 | J4: ='PROJECT MASTER FILE - COPY'!O30/H3*F4 -> 0 | K4: ='PROJECT MASTER FILE - COPY'!O43/H3*F4 -> 0 | L4: ='PROJECT MASTER FILE - COPY'!O56/H3*F4 -> 0 | M4: ='PROJECT MASTER FILE - COPY'!O69/H3*F4 -> 0 | N4: ='PROJECT MASTER FILE - COPY'!O82/H3*F4 -> 0 | O4: ='PROJECT MASTER FILE - COPY'!O95/H3*F4 -> 0 | P4: ='PROJECT MASTER FILE - COPY'!O108/H3*F4 -> 0 | Q4: ='PROJECT MASTER FILE - COPY'!O121/H3*F4 -> 0 | R4: ='PROJECT MASTER FILE - COPY'!O134/H3*F4 -> 0 | S4: ='PROJECT MASTER FILE - COPY'!O4/H3*F4 -> 0 | T4: =F4- (I4+J4+K4+L4+M4+N4+O4+P4+Q4+R4+S4) -> 0 | U4: =G4-F4 -> 0 | V4: 45870
A5: 3 | B5: Oval Blue Technologies | C5: Photocopier SDP | D5: Monthly | E5: 84000 | F5: =E5/12 -> 7000 | G5: 11391 | I5: ='PROJECT MASTER FILE - COPY'!O17/H3*F5 -> 727.01245 | J5: ='PROJECT MASTER FILE - COPY'!O30/H3*F5 -> 727.01245 | K5: ='PROJECT MASTER FILE - COPY'!O43/H3*F5 -> 727.01245 | L5: ='PROJECT MASTER FILE - COPY'!O56/H3*F5 -> 0 | M5: ='PROJECT MASTER FILE - COPY'!O69/H3*F5 -> 0 | N5: ='PROJECT MASTER FILE - COPY'!O82/H3*F5 -> 727.01245 | O5: ='PROJECT MASTER FILE - COPY'!O95/H3*F5 -> 0 | P5: ='PROJECT MASTER FILE - COPY'!O108/H3*F5 -> 0 | Q5: 0 | R5: ='PROJECT MASTER FILE - COPY'!O134/H3*F5 -> 0 | S5: ='PROJECT MASTER FILE - COPY'!O4/H3*F5 -> 0 | T5: =F5- (I5+J5+K5+L5+M5+N5+O5+P5+Q5+R5+S5) -> 4091.9502 | U5: =G5-F5 -> 4391 | V5: 45901
A6: 4 | B6: Volks Electronics | C6: Desktop rental | D6: Monthly | E6: 720000 | F6: 57180 | G6: 57180 | I6: ='PROJECT MASTER FILE - COPY'!O17/H3*F6 -> 5938.6532 | J6: ='PROJECT MASTER FILE - COPY'!O30/H3*F6 -> 5938.6532 | K6: ='PROJECT MASTER FILE - COPY'!O43/H3*F6 -> 5938.6532 | L6: ='PROJECT MASTER FILE - COPY'!O56/H3*F6 -> 0 | M6: ='PROJECT MASTER FILE - COPY'!O69/H3*F6 -> 0 | N6: ='PROJECT MASTER FILE - COPY'!O82/H3*F6 -> 5938.6532 | O6: ='PROJECT MASTER FILE - COPY'!O95/H3*F6 -> 0 | P6: ='PROJECT MASTER FILE - COPY'!O108/H3*F6 -> 0 | Q6: 0 | R6: ='PROJECT MASTER FILE - COPY'!O134/H3*F6 -> 0 | S6: ='PROJECT MASTER FILE - COPY'!O4/H3*F6 -> 0 | T6: =F6- (I6+J6+K6+L6+M6+N6+O6+P6+Q6+R6+S6) -> 33425.387 | U6: =G6-F6 -> 0 | V6: 45931
A7: 5 | B7: Asianet | C7: Internet Services | D7: Quarterly | E7: 56640 | F7: 0 | I7: ='PROJECT MASTER FILE - COPY'!O17/H3*F7 -> 0 | J7: ='PROJECT MASTER FILE - COPY'!O30/H3*F7 -> 0 | K7: ='PROJECT MASTER FILE - COPY'!O43/H3*F7 -> 0 | L7: ='PROJECT MASTER FILE - COPY'!O56/H3*F7 -> 0 | M7: ='PROJECT MASTER FILE - COPY'!O69/H3*F7 -> 0 | N7: ='PROJECT MASTER FILE - COPY'!O82/H3*F7 -> 0 | O7: ='PROJECT MASTER FILE - COPY'!O95/H3*F7 -> 0 | P7: ='PROJECT MASTER FILE - COPY'!O108/H3*F7 -> 0 | Q7: ='PROJECT MASTER FILE - COPY'!O121/H3*F7 -> 0 | R7: ='PROJECT MASTER FILE - COPY'!O134/H3*F7 -> 0 | S7: ='PROJECT MASTER FILE - COPY'!O4/H3*F7 -> 0 | T7: =F7- (I7+J7+K7+L7+M7+N7+O7+P7+Q7+R7+S7) -> 0 | U7: =G7-F7 -> 0 | V7: 45962
A8: 6 | B8: Stationary | C8: Stationary | E8: 200000 | F8: 0 | G8: 13328 | I8: ='PROJECT MASTER FILE - COPY'!O17/H3*F8 -> 0 | J8: ='PROJECT MASTER FILE - COPY'!O30/H3*F8 -> 0 | K8: ='PROJECT MASTER FILE - COPY'!O43/H3*F8 -> 0 | L8: ='PROJECT MASTER FILE - COPY'!O56/H3*F8 -> 0 | M8: ='PROJECT MASTER FILE - COPY'!O69/H3*F8 -> 0 | N8: ='PROJECT MASTER FILE - COPY'!O82/H3*F8 -> 0 | O8: ='PROJECT MASTER FILE - COPY'!O95/H3*F8 -> 0 | P8: ='PROJECT MASTER FILE - COPY'!O108/H3*F8 -> 0 | Q8: ='PROJECT MASTER FILE - COPY'!O121/H3*F8 -> 0 | R8: ='PROJECT MASTER FILE - COPY'!O134/H3*F8 -> 0 | S8: ='PROJECT MASTER FILE - COPY'!O4/H3*F8 -> 0 | T8: =F8- (I8+J8+K8+L8+M8+N8+O8+P8+Q8+R8+S8) -> 0 | U8: =G8-F8 -> 13328 | V8: 45992
I9: =SUM(I3:I8) -> 11200.25 | J9: =SUM(J3:J8) -> 11200.25 | K9: =SUM(K3:K8) -> 11200.25 | L9: =SUM(L3:L8) -> 0 | M9: =SUM(M3:M8) -> 0 | N9: =SUM(N3:N8) -> 11200.25 | O9: =SUM(O3:O8) -> 0 | P9: =SUM(P3:P8) -> 0 | ... U9: =SUM(U3:U8) -> 17719
A10: 7 | B10: Dr Anandam | C10: House Rent | D10: Monthly | E10: 1800000 | F10: =E10/12 -> 150000 | G10: 119100 | H10: =SUM(F10:F28) -> 601833.33
A11: 8 | B11: BSNL | C11: Land Line | D11: Monthly | E11: 24000 | F11: =E11/12 -> 2000 | AI11: 1974
A12: 9 | B12: KSEB | C12: Electricity Bill | D12: Monthly | E12: 264000 | F12: =E12/12 -> 22000 | G12: 21303 | AI12: 21303
A13: 10 | B13: KWA | C13: Water Bill | D13: Monthly | E13: 96000 | F13: =E13/12 -> 8000
A14: 11 | B14: Subramania Industries | C14: DG AMC | D14: Half Yearly | E14: 10000 | F14: =E14/12 -> 833.33333
A15: 12 | B15: Imprest | C15: Monthly Imprest | D15: Monthly | E15: 120000 | F15: =E15/12 -> 10000 | G15: 10000
A16: 13 | B16: Geejey Solutions | C16: Epabx AMC | D16: Half Yearly | E16: 8000 | F16: =E16/12 -> 666.66667 | AI16: 4360
A17: 14 | B17: VRS infosystems | C17: Tally Software Renewal | D17: Annualy | E17: 16000 | F17: =E17/12 -> 1333.3333
A18: 15 | B18: M/sArmtech Computer Services | C18: CAMC computer hardware | D18: Quarterly | E18: 15000 | F18: =E18/12 -> 1250
A19: 16 | B19: Nu aire | C19: AC AMC | D19: Quarterly | E19: 36000 | F19: =E19/12 -> 3000
A20: 17 | B20: Miscellaneous | C20: Repair & Maintenance | D20: Monthly | E20: 50000 | F20: =E20/12 -> 4166.6667
A21: 18 | B21: Microsoft 365 | C21: Software | D21: Annualy | E21: 7000 | F21: =E21/12 -> 583.33333
A22: 19 | B22: Asterisk | C22: Photocopier (Admin & DVP) | D22: Monthly | E22: 60000 | F22: 5000 | G22: 4728 | AI22: 4728
A23: 20 | B23: Indian Postal Department | C23: Speed post | D23: Monthly | E23: 120000 | F23: =E23/12 -> 10000 | G23: 20000 | W23: 0 | X23: 0 | Y23: 0 | Z23: 0 | AA23: 0 | AB23: 0 | AC23: 0 | AD23: 0 | AE23: 0 | AF23: 0 | AG23: 0 | AH23: 0 | AI23: 20000
A24: 21 | B24: Pradeep Kumar Cost Accountant | C24: Financial Consultant | D24: Monthly | E24: 1296000 | F24: =E24/12 -> 108000
A25: 22 | B25: Pradeep Kumar Cost Accountant | C25: Accounts Assistance | D25: Monthly | E25: 750000 | F25: =E25/12 -> 62500
A26: 23 | B26: Vismaya Services | C26: HK salary | D26: Monthly | E26: 600000 | F26: 50000 | G26: 46016 | AI26: 46016
A27: 24 | B27: Vismaya Services | C27: My city salary | D27: Monthly | E27: 810000 | F27: 67500 | G27: 66676 | AI27: 66676
A28: 25 | B28: Naveen Security Services | C28: Security salary | D28: Monthly | E28: =F28*12 -> 1140000 | F28: 95000 | G28: 96550 | AI28: 96550

Sheet HEKSY
A1: Name | B1: Designation | C1: Project | D1: Monthly CTC | E1: Date | F1: 45748 | H1: 45778 | J1: 45809 | L1: 45839 | N1: 45870 | P1: 45901 | R1: 45931 | T1: 45962 | V1: 45992 | X1: 46023 | Z1: 46054 | AB1: 46082
F2: Attendance | G2: Amount | H2: Attendance | I2: Amount | J2: Attendance | K2: Amount | L2: Attendance | M2: Amount | N2: Attendance | O2: Amount | P2: Attendance | Q2: Amount | R2: Attendance | S2: Amount | T2: Attendance | U2: Amount | V2: Attendance | W2: Amount | X2: Attendance | Y2: Amount | Z2: Attendance | AA2: Amount | AB2: Attendance | AC2: Amount
A3: Heksy Sebastian | B3: Admistrative Assistant (Projects) | C3: CORE TEAM | D3: 28130 | E3: 1 | F3: 27.5 | G3: 24644.583 | H3: 24.5 | I3: 21247.823 | L3: 1 | M3: =D3/31*L3 -> 907.41935 | N3: 1 | O3: =D3/31*N3 -> 907.41935 | P3: 1 | Q3: =D3/30*P3 -> 937.66667 | R3: 1 | S3: =D3/31*R3 -> 907.41935 | T3: 1 | U3: =D3/30*T3 -> 937.66667 | V3: 1 | W3: =D3/31*V3 -> 907.41935 | X3: 1 | Y3: =D3/31*X3 -> 907.41935 | Z3: 1 | AA3: =D3/28*Z3 -> 1004.6429 | AB3: 1 | AC3: =D3/31*AB3 -> 907.41935
D4: 28130 | E4: 2 | L4: 0 | M4: =D4/31*L4 -> 0 | N4: 1 | O4: =D4/31*N4 -> 907.41935 | P4: 1 | Q4: =D4/30*P4 -> 937.66667 | R4: 1 | S4: =D4/31*R4 -> 907.41935 | T4: 1 | U4: =D4/30*T4 -> 937.66667 | V4: 1 | W4: =D4/31*V4 -> 907.41935 | X4: 1 | Y4: =D4/31*X4 -> 907.41935 | Z4: 1 | AA4: =D4/28*Z4 -> 1004.6429 | AB4: 1 | AC4: =D4/31*AB4 -> 907.41935
D5: 28130 | E5: 3 | L5: 1 | M5: =D5/31*L5 -> 907.41935 | N5: 1 | O5: =D5/31*N5 -> 907.41935 | P5: 0 | Q5: =D5/30*P5 -> 0 | R5: 0 | S5: =D5/31*R5 -> 0 | T5: 1 | U5: =D5/30*T5 -> 937.66667 | V5: 1 | W5: =D5/31*V5 -> 907.41935 | X5: 1 | Y5: =D5/31*X5 -> 907.41935 | Z5: 1 | AA5: =D5/28*Z5 -> 1004.6429 | AB5: 1 | AC5: =D5/31*AB5 -> 907.41935
D6: 28130 | E6: 4 | L6: 1 | M6: =D6/31*L6 -> 907.41935 | N6: 1 | O6: =D6/31*N6 -> 907.41935 | P6: 1 | Q6: =D6/30*P6 -> 937.66667 | R6: 1 | S6: =D6/31*R6 -> 907.41935 | T6: 1 | U6: =D6/30*T6 -> 937.66667 | V6: 1 | W6: =D6/31*V6 -> 907.41935 | X6: 1 | Y6: =D6/31*X6 -> 907.41935 | Z6: 1 | AA6: =D6/28*Z6 -> 1004.6429 | AB6: 1 | AC6: =D6/31*AB6 -> 907.41935
D7: 28130 | E7: 5 | L7: 1 | M7: =D7/31*L7 -> 907.41935 | N7: 1 | O7: =D7/31*N7 -> 907.41935 | P7: 1 | Q7: =D7/30*P7 -> 937.66667 | R7: 1 | S7: =D7/31*R7 -> 907.41935 | T7: 1 | U7: =D7/30*T7 -> 937.66667 | V7: 1 | W7: =D7/31*V7 -> 907.41935 | X7: 1 | Y7: =D7/31*X7 -> 907.41935 | Z7: 1 | AA7: =D7/28*Z7 -> 1004.6429 | AB7: 1 | AC7: =D7/31*AB7 -> 907.41935
D8: 28130 | E8: 6 | L8: 1 | M8: =D8/31*L8 -> 907.41935 | N8: 1 | O8: =D8/31*N8 -> 907.41935 | P8: 1 | Q8: =D8/30*P8 -> 937.66667 | R8: 1 | S8: =D8/31*R8 -> 907.41935 | T8: 1 | U8: =D8/30*T8 -> 937.66667 | V8: 1 | W8: =D8/31*V8 -> 907.41935 | X8: 1 | Y8: =D8/31*X8 -> 907.41935 | Z8: 1 | AA8: =D8/28*Z8 -> 1004.6429 | AB8: 1 | AC8: =D8/31*AB8 -> 907.41935
D9: 28130 | E9: 7 | L9: 1 | M9: =D9/31*L9 -> 907.41935 | N9: 1 | O9: =D9/31*N9 -> 907.41935 | P9: 1 | Q9: =D9/30*P9 -> 937.66667 | R9: 1 | S9: =D9/31*R9 -> 907.41935 | T9: 1 | U9: =D9/30*T9 -> 937.66667 | V9: 1 | W9: =D9/31*V9 -> 907.41935 | X9: 1 | Y9: =D9/31*X9 -> 907.41935 | Z9: 1 | AA9: =D9/28*Z9 -> 1004.6429 | AB9: 1 | AC9: =D9/31*AB9 -> 907.41935
D10: 28130 | E10: 8 | L10: 1 | M10: =D10/31*L10 -> 907.41935 | N10: 0 | O10: =D10/31*N10 -> 0 | P10: 0 | Q10: =D10/30*P10 -> 0 | R10: 1 | S10: =D10/31*R10 -> 907.41935 | T10: 1 | U10: =D10/30*T10 -> 937.66667 | V10: 1 | W10: =D10/31*V10 -> 907.41935 | X10: 1 | Y10: =D10/31*X10 -> 907.41935 | Z10: 1 | AA10: =D10/28*Z10 -> 1004.6429 | AB10: 1 | AC10: =D10/31*AB10 -> 907.41935
D11: 28130 | E11: 9 | L11: 1 | M11: =D11/31*L11 -> 907.41935 | N11: 1 | O11: =D11/31*N11 -> 907.41935 | P11: 1 | Q11: =D11/30*P11 -> 937.66667 | R11: 1 | S11: =D11/31*R11 -> 907.41935 | T11: 1 | U11: =D11/30*T11 -> 937.66667 | V11: 1 | W11: =D11/31*V11 -> 907.41935 | X11: 1 | Y11: =D11/31*X11 -> 907.41935 | Z11: 1 | AA11: =D11/28*Z11 -> 1004.6429 | AB11: 1 | AC11: =D11/31*AB11 -> 907.41935
D12: 28130 | E12: 10 | L12: 0 | M12: =D12/31*L12 -> 0 | N12: 1 | O12: =D12/31*N12 -> 907.41935 | P12: 1 | Q12: =D12/30*P12 -> 937.66667 | R12: 0 | S12: =D12/31*R12 -> 0 | T12: 1 | U12: =D12/30*T12 -> 937.66667 | V12: 1 | W12: =D12/31*V12 -> 907.41935 | X12: 1 | Y12: =D12/31*X12 -> 907.41935 | Z12: 1 | AA12: =D12/28*Z12 -> 1004.6429 | AB12: 1 | AC12: =D12/31*AB12 -> 907.41935
D13: 28130 | E13: 11 | L13: 1 | M13: =D13/31*L13 -> 907.41935 | N13: 1 | O13: =D13/31*N13 -> 907.41935 | P13: 1 | Q13: =D13/30*P13 -> 937.66667 | R13: 1 | S13: =D13/31*R13 -> 907.41935 | T13: 1 | U13: =D13/30*T13 -> 937.66667 | V13: 1 | W13: =D13/31*V13 -> 907.41935 | X13: 1 | Y13: =D13/31*X13 -> 907.41935 | Z13: 1 | AA13: =D13/28*Z13 -> 1004.6429 | AB13: 1 | AC13: =D13/31*AB13 -> 907.41935
D14: 28130 | E14: 12 | L14: 1 | M14: =D14/31*L14 -> 907.41935 | N14: 1 | O14: =D14/31*N14 -> 907.41935 | P14: 0 | Q14: =D14/30*P14 -> 0 | R14: 1 | S14: =D14/31*R14 -> 907.41935 | T14: 1 | U14: =D14/30*T14 -> 937.66667 | V14: 1 | W14: =D14/31*V14 -> 907.41935 | X14: 1 | Y14: =D14/31*X14 -> 907.41935 | Z14: 1 | AA14: =D14/28*Z14 -> 1004.6429 | AB14: 1 | AC14: =D14/31*AB14 -> 907.41935
D15: 28130 | E15: 13 | L15: 1 | M15: =D15/31*L15 -> 907.41935 | N15: 1 | O15: =D15/31*N15 -> 907.41935 | P15: 1 | Q15: =D15/30*P15 -> 937.66667 | R15: 1 | S15: =D15/31*R15 -> 907.41935 | T15: 1 | U15: =D15/30*T15 -> 937.66667 | V15: 1 | W15: =D15/31*V15 -> 907.41935 | X15: 1 | Y15: =D15/31*X15 -> 907.41935 | Z15: 1 | AA15: =D15/28*Z15 -> 1004.6429 | AB15: 1 | AC15: =D15/31*AB15 -> 907.41935
... D30: 28130 | E30: 28 | L30: 1 | M30: =D30/31*L30 -> 907.41935 | N30: 1 | O30: =D30/31*N30 -> 907.41935 | P30: 1 | Q30: =D30/30*P30 -> 937.66667 | R30: 1 | S30: =D30/31*R30 -> 907.41935 | T30: 1 | U30: =D30/30*T30 -> 937.66667 | V30: 1 | W30: =D30/31*V30 -> 907.41935 | X30: 1 | Y30: =D30/31*X30 -> 907.41935 | Z30: 1 | AA30: =D30/28*Z30 -> 1004.6429 | AB30: 1 | AC30: =D30/31*AB30 -> 907.41935
D31: 28130 | E31: 29 | L31: 1 | M31: =D31/31*L31 -> 907.41935 | N31: 1 | O31: =D31/31*N31 -> 907.41935 | P31: 1 | Q31: =D31/30*P31 -> 937.66667 | R31: 1 | S31: =D31/31*R31 -> 907.41935 | T31: 1 | U31: =D31/30*T31 -> 937.66667 | V31: 1 | W31: =D31/31*V31 -> 907.41935 | X31: 1 | Y31: =D31/31*X31 -> 907.41935 | AB31: 1 | AC31: =D31/31*AB31 -> 907.41935
D32: 28130 | E32: 30 | L32: 1 | M32: =D32/31*L32 -> 907.41935 | N32: 0.5 | O32: =D32/31*N32 -> 453.70968 | P32: 1 | Q32: =D32/30*P32 -> 937.66667 | R32: 1 | S32: =D32/31*R32 -> 907.41935 | T32: 1 | U32: =D32/30*T32 -> 937.66667 | V32: 1 | W32: =D32/31*V32 -> 907.41935 | X32: 1 | Y32: =D32/31*X32 -> 907.41935 | AB32: 1 | AC32: =D32/31*AB32 -> 907.41935
D33: 28130 | E33: 31 | L33: 1 | M33: =D33/31*L33 -> 907.41935 | N33: 1 | O33: =D33/31*N33 -> 907.41935 | R33: 1 | S33: =D33/31*R33 -> 907.41935 | V33: 1 | W33: =D33/31*V33 -> 907.41935 | X33: 1 | Y33: =D33/31*X33 -> 907.41935 | AB33: 1 | AC33: =D33/31*AB33 -> 907.41935
C34: CASUAL LEAVE | D34: 28130 | L34: 1 | M34: =D34/31*L34 -> 907.41935 | N34: 1 | O34: =D34/31*N34 -> 907.41935
C35: SICK LEAVE | D35: 28130 | L35: 0 | M35: =D35/31*L35 -> 0 | N35: 1 | O35: =D35/31*N35 -> 907.41935
C36: COMP OFF | D36: 28130 | L36: 0 | M36: =D36/31*L36 -> 0 | O36: =D36/31*N36 -> 0
L37: =SUM(L3:L36) -> 28.5 | M37: =SUM(M3:M36) -> 25861.452 | N37: =SUM(N3:N36) -> 29.5 | O37: =SUM(O3:O36) -> 26768.871 | P37: =SUM(P3:P36) -> 26 | Q37: =SUM(Q3:Q36) -> 24379.333 | R37: =SUM(R3:R36) -> 28 | S37: =SUM(S3:S36) -> 25407.742 | ... AC37: =SUM(AC3:AC36) -> 28130

Sheet MANJUSHA
A1: Name | B1: Designation | C1: Project | D1: Monthly CTC | E1: Date | F1: 45748 | H1: 45778 | J1: 45809 | L1: 45839 | N1: 45870 | P1: 45901 | R1: 45931 | T1: 45962 | V1: 45992 | X1: 46023 | Z1: 46054 | AB1: 46082
F2: Attendance | G2: Amount | H2: Attendance | I2: Amount | J2: Attendance | K2: Amount | L2: Attendance | M2: Amount | N2: Attendance | O2: Amount | P2: Attendance | Q2: Amount | R2: Attendance | S2: Amount | T2: Attendance | U2: Amount | V2: Attendance | W2: Amount | X2: Attendance | Y2: Amount | Z2: Attendance | AA2: Amount | AB2: Attendance | AC2: Amount
A3: MANJUSHA V | B3: Admistrative Assistant (Projects) | C3: CORE TEAM | D3: 27598 | E3: 1 | L3: 1 | M3: =D3/31*L3 -> 890.25806 | N3: 1 | O3: =D3/31*N3 -> 890.25806 | P3: 1 | Q3: =D3/30*P3 -> 919.93333 | R3: 1 | S3: =D3/31*R3 -> 890.25806 | T3: 1 | U3: =D3/30*T3 -> 919.93333 | V3: 1 | W3: =D3/31*V3 -> 890.25806 | X3: 1 | Y3: =D3/31*X3 -> 890.25806 | Z3: 1 | AA3: =D3/28*Z3 -> 985.64286 | AB3: 1 | AC3: =D3/31*AB3 -> 890.25806
D4: 27598 | E4: 2 | L4: 0 | M4: =D4/31*L4 -> 0 | N4: 1 | O4: =D4/31*N4 -> 890.25806 | P4: 1 | Q4: =D4/30*P4 -> 919.93333 | R4: 1 | S4: =D4/31*R4 -> 890.25806 | T4: 1 | U4: =D4/30*T4 -> 919.93333 | V4: 1 | W4: =D4/31*V4 -> 890.25806 | X4: 1 | Y4: =D4/31*X4 -> 890.25806 | Z4: 1 | AA4: =D4/28*Z4 -> 985.64286 | AB4: 1 | AC4: =D4/31*AB4 -> 890.25806
D5: 27598 | E5: 3 | L5: 1 | M5: =D5/31*L5 -> 890.25806 | N5: 1 | O5: =D5/31*N5 -> 890.25806 | P5: 1 | Q5: =D5/30*P5 -> 919.93333 | R5: 0 | S5: =D5/31*R5 -> 0 | T5: 1 | U5: =D5/30*T5 -> 919.93333 | V5: 1 | W5: =D5/31*V5 -> 890.25806 | X5: 1 | Y5: =D5/31*X5 -> 890.25806 | Z5: 1 | AA5: =D5/28*Z5 -> 985.64286 | AB5: 1 | AC5: =D5/31*AB5 -> 890.25806
D6: 27598 | E6: 4 | L6: 1 | M6: =D6/31*L6 -> 890.25806 | N6: 1 | O6: =D6/31*N6 -> 890.25806 | P6: 1 | Q6: =D6/30*P6 -> 919.93333 | R6: 0 | S6: =D6/31*R6 -> 0 | T6: 1 | U6: =D6/30*T6 -> 919.93333 | V6: 1 | W6: =D6/31*V6 -> 890.25806 | X6: 1 | Y6: =D6/31*X6 -> 890.25806 | Z6: 1 | AA6: =D6/28*Z6 -> 985.64286 | AB6: 1 | AC6: =D6/31*AB6 -> 890.25806
D7: 27598 | E7: 5 | L7: 1 | M7: =D7/31*L7 -> 890.25806 | N7: 1 | O7: =D7/31*N7 -> 890.25806 | P7: 1 | Q7: =D7/30*P7 -> 919.93333 | R7: 1 | S7: =D7/31*R7 -> 890.25806 | T7: 1 | U7: =D7/30*T7 -> 919.93333 | V7: 1 | W7: =D7/31*V7 -> 890.25806 | X7: 1 | Y7: =D7/31*X7 -> 890.25806 | Z7: 1 | AA7: =D7/28*Z7 -> 985.64286 | AB7: 1 | AC7: =D7/31*AB7 -> 890.25806
D8: 27598 | E8: 6 | L8: 1 | M8: =D8/31*L8 -> 890.25806 | N8: 0 | O8: =D8/31*N8 -> 0 | P8: 1 | Q8: =D8/30*P8 -> 919.93333 | R8: 1 | S8: =D8/31*R8 -> 890.25806 | T8: 1 | U8: =D8/30*T8 -> 919.93333 | V8: 1 | W8: =D8/31*V8 -> 890.25806 | X8: 1 | Y8: =D8/31*X8 -> 890.25806 | Z8: 1 | AA8: =D8/28*Z8 -> 985.64286 | AB8: 1 | AC8: =D8/31*AB8 -> 890.25806
D9: 27598 | E9: 7 | L9: 1 | M9: =D9/31*L9 -> 890.25806 | N9: 1 | O9: =D9/31*N9 -> 890.25806 | P9: 1 | Q9: =D9/30*P9 -> 919.93333 | R9: 1 | S9: =D9/31*R9 -> 890.25806 | T9: 1 | U9: =D9/30*T9 -> 919.93333 | V9: 1 | W9: =D9/31*V9 -> 890.25806 | X9: 1 | Y9: =D9/31*X9 -> 890.25806 | Z9: 1 | AA9: =D9/28*Z9 -> 985.64286 | AB9: 1 | AC9: =D9/31*AB9 -> 890.25806
D10: 27598 | E10: 8 | L10: 1 | M10: =D10/31*L10 -> 890.25806 | N10: 1 | O10: =D10/31*N10 -> 890.25806 | P10: 1 | Q10: =D10/30*P10 -> 919.93333 | R10: 1 | S10: =D10/31*R10 -> 890.25806 | T10: 1 | U10: =D10/30*T10 -> 919.93333 | V10: 1 | W10: =D10/31*V10 -> 890.25806 | X10: 1 | Y10: =D10/31*X10 -> 890.25806 | Z10: 1 | AA10: =D10/28*Z10 -> 985.64286 | AB10: 1 | AC10: =D10/31*AB10 -> 890.25806
D11: 27598 | E11: 9 | L11: 1 | M11: =D11/31*L11 -> 890.25806 | N11: 1 | O11: =D11/31*N11 -> 890.25806 | P11: 1 | Q11: =D11/30*P11 -> 919.93333 | R11: 1 | S11: =D11/31*R11 -> 890.25806 | T11: 1 | U11: =D11/30*T11 -> 919.93333 | V11: 1 | W11: =D11/31*V11 -> 890.25806 | X11: 1 | Y11: =D11/31*X11 -> 890.25806 | Z11: 1 | AA11: =D11/28*Z11 -> 985.64286 | AB11: 1 | AC11: =D11/31*AB11 -> 890.25806
D12: 27598 | E12: 10 | L12: 1 | M12: =D12/31*L12 -> 890.25806 | N12: 1 | O12: =D12/31*N12 -> 890.25806 | P12: 1 | Q12: =D12/30*P12 -> 919.93333 | R12: 1 | S12: =D12/31*R12 -> 890.25806 | T12: 1 | U12: =D12/30*T12 -> 919.93333 | V12: 1 | W12: =D12/31*V12 -> 890.25806 | X12: 1 | Y12: =D12/31*X12 -> 890.25806 | Z12: 1 | AA12: =D12/28*Z12 -> 985.64286 | AB12: 1 | AC12: =D12/31*AB12 -> 890.25806
D13: 27598 | E13: 11 | L13: 1 | M13: =D13/31*L13 -> 890.25806 | N13: 1 | O13: =D13/31*N13 -> 890.25806 | P13: 1 | Q13: =D13/30*P13 -> 919.93333 | R13: 1 | S13: =D13/31*R13 -> 890.25806 | T13: 1 | U13: =D13/30*T13 -> 919.93333 | V13: 1 | W13: =D13/31*V13 -> 890.25806 | X13: 1 | Y13: =D13/31*X13 -> 890.25806 | Z13: 1 | AA13: =D13/28*Z13 -> 985.64286 | AB13: 1 | AC13: =D13/31*AB13 -> 890.25806
D14: 27598 | E14: 12 | L14: 1 | M14: =D14/31*L14 -> 890.25806 | N14: 0 | O14: =D14/31*N14 -> 0 | P14: 1 | Q14: =D14/30*P14 -> 919.93333 | R14: 1 | S14: =D14/31*R14 -> 890.25806 | T14: 1 | U14: =D14/30*T14 -> 919.93333 | V14: 1 | W14: =D14/31*V14 -> 890.25806 | X14: 1 | Y14: =D14/31*X14 -> 890.25806 | Z14: 1 | AA14: =D14/28*Z14 -> 985.64286 | AB14: 1 | AC14: =D14/31*AB14 -> 890.25806
D15: 27598 | E15: 13 | L15: 1 | M15: =D15/31*L15 -> 890.25806 | N15: 1 | O15: =D15/31*N15 -> 890.25806 | P15: 1 | Q15: =D15/30*P15 -> 919.93333 | R15: 1 | S15: =D15/31*R15 -> 890.25806 | T15: 1 | U15: =D15/30*T15 -> 919.93333 | V15: 1 | W15: =D15/31*V15 -> 890.25806 | X15: 1 | Y15: =D15/31*X15 -> 890.25806 | Z15: 1 | AA15: =D15/28*Z15 -> 985.64286 | AB15: 1 | AC15: =D15/31*AB15 -> 890.25806
... D30: 27598 | E30: 28 | L30: 1 | M30: =D30/31*L30 -> 890.25806 | N30: 1 | O30: =D30/31*N30 -> 890.25806 | P30: 1 | Q30: =D30/30*P30 -> 919.93333 | R30: 1 | S30: =D30/31*R30 -> 890.25806 | T30: 1 | U30: =D30/30*T30 -> 919.93333 | V30: 1 | W30: =D30/31*V30 -> 890.25806 | X30: 1 | Y30: =D30/31*X30 -> 890.25806 | Z30: 1 | AA30: =D30/28*Z30 -> 985.64286 | AB30: 1 | AC30: =D30/31*AB30 -> 890.25806
D31: 27598 | E31: 29 | L31: 1 | M31: =D31/31*L31 -> 890.25806 | N31: 1 | O31: =D31/31*N31 -> 890.25806 | P31: 1 | Q31: =D31/30*P31 -> 919.93333 | R31: 1 | S31: =D31/31*R31 -> 890.25806 | T31: 1 | U31: =D31/30*T31 -> 919.93333 | V31: 1 | W31: =D31/31*V31 -> 890.25806 | X31: 1 | Y31: =D31/31*X31 -> 890.25806 | AB31: 1 | AC31: =D31/31*AB31 -> 890.25806
D32: 27598 | E32: 30 | L32: 1 | M32: =D32/31*L32 -> 890.25806 | N32: 1 | O32: =D32/31*N32 -> 890.25806 | P32: 1 | Q32: =D32/30*P32 -> 919.93333 | R32: 1 | S32: =D32/31*R32 -> 890.25806 | T32: 1 | U32: =D32/30*T32 -> 919.93333 | V32: 1 | W32: =D32/31*V32 -> 890.25806 | X32: 1 | Y32: =D32/31*X32 -> 890.25806 | AB32: 1 | AC32: =D32/31*AB32 -> 890.25806
D33: 27598 | E33: 31 | L33: 1 | M33: =D33/31*L33 -> 890.25806 | N33: 1 | O33: =D33/31*N33 -> 890.25806 | R33: 1 | S33: =D33/31*R33 -> 890.25806 | V33: 1 | W33: =D33/31*V33 -> 890.25806 | X33: 1 | Y33: =D33/31*X33 -> 890.25806 | AB33: 1 | AC33: =D33/31*AB33 -> 890.25806
C34: CASUAL LEAVE | D34: 27598 | L34: 1 | M34: =D34/31*L34 -> 890.25806 | N34: 1 | O34: =D34/31*N34 -> 890.25806
C35: SICK LEAVE | D35: 27598 | L35: 1 | M35: =D35/31*L35 -> 890.25806 | N35: 1 | O35: =D35/31*N35 -> 890.25806
C36: COMP OFF | D36: 27598 | N36: 1 | O36: =D36/31*N36 -> 890.25806
L37: =SUM(L3:L36) -> 31 | M37: =SUM(M3:M36) -> 27598 | N37: =SUM(N3:N36) -> 31 | O37: =SUM(O3:O36) -> 27598 | P37: =SUM(P3:P36) -> 26 | Q37: =SUM(Q3:Q36) -> 23918.267 | R37: =SUM(R3:R36) -> 26 | S37: =SUM(S3:S36) -> 23146.71 | ... AC37: =SUM(AC3:AC36) -> 27598

Sheet VISHNU
A1: Name | B1: Designation | C1: Project | D1: Monthly CTC | E1: Date | F1: 45748 | H1: 45778 | J1: 45809 | L1: 45839 | N1: 45870 | P1: 45901 | R1: 45931 | T1: 45962 | V1: 45992 | X1: 46023 | Z1: 46054 | AB1: 46082
F2: Attendance | G2: Amount | H2: Attendance | I2: Amount | J2: Attendance | K2: Amount | L2: Attendance | M2: Amount | N2: Attendance | O2: Amount | P2: Attendance | Q2: Amount | R2: Attendance | S2: Amount | T2: Attendance | U2: Amount | V2: Attendance | W2: Amount | X2: Attendance | Y2: Amount | Z2: Attendance | AA2: Amount | AB2: Attendance | AC2: Amount
A3: VISHNU | B3: FIELD ASSISTANT | C3: CORE TEAM | D3: 21367 | E3: 1 | L3: 1 | M3: =D3/31*L3 -> 689.25806 | N3: 1 | O3: =D3/31*N3 -> 689.25806 | P3: 1 | Q3: =D3/30*P3 -> 712.23333 | R3: 1 | S3: =D3/31*R3 -> 689.25806 | T3: 1 | U3: =D3/30*T3 -> 712.23333 | V3: 1 | W3: =D3/31*V3 -> 689.25806 | X3: 1 | Y3: =D3/31*X3 -> 689.25806 | Z3: 1 | AA3: =D3/28*Z3 -> 763.10714 | AB3: 1 | AC3: =D3/31*AB3 -> 689.25806
D4: 21367 | E4: 2 | L4: 1 | M4: =D4/31*L4 -> 689.25806 | N4: 1 | O4: =D4/31*N4 -> 689.25806 | P4: 1 | Q4: =D4/30*P4 -> 712.23333 | R4: 1 | S4: =D4/31*R4 -> 689.25806 | T4: 1 | U4: =D4/30*T4 -> 712.23333 | V4: 1 | W4: =D4/31*V4 -> 689.25806 | X4: 1 | Y4: =D4/31*X4 -> 689.25806 | Z4: 1 | AA4: =D4/28*Z4 -> 763.10714 | AB4: 1 | AC4: =D4/31*AB4 -> 689.25806
D5: 21367 | E5: 3 | L5: 1 | M5: =D5/31*L5 -> 689.25806 | N5: 1 | O5: =D5/31*N5 -> 689.25806 | P5: 0.5 | Q5: =D5/30*P5 -> 356.11667 | R5: 1 | S5: =D5/31*R5 -> 689.25806 | T5: 1 | U5: =D5/30*T5 -> 712.23333 | V5: 1 | W5: =D5/31*V5 -> 689.25806 | X5: 1 | Y5: =D5/31*X5 -> 689.25806 | Z5: 1 | AA5: =D5/28*Z5 -> 763.10714 | AB5: 1 | AC5: =D5/31*AB5 -> 689.25806
D6: 21367 | E6: 4 | L6: 1 | M6: =D6/31*L6 -> 689.25806 | N6: 1 | O6: =D6/31*N6 -> 689.25806 | P6: 1 | Q6: =D6/30*P6 -> 712.23333 | R6: 1 | S6: =D6/31*R6 -> 689.25806 | T6: 1 | U6: =D6/30*T6 -> 712.23333 | V6: 1 | W6: =D6/31*V6 -> 689.25806 | X6: 1 | Y6: =D6/31*X6 -> 689.25806 | Z6: 1 | AA6: =D6/28*Z6 -> 763.10714 | AB6: 1 | AC6: =D6/31*AB6 -> 689.25806
D7: 21367 | E7: 5 | L7: 0 | M7: =D7/31*L7 -> 0 | N7: 1 | O7: =D7/31*N7 -> 689.25806 | P7: 1 | Q7: =D7/30*P7 -> 712.23333 | R7: 1 | S7: =D7/31*R7 -> 689.25806 | T7: 1 | U7: =D7/30*T7 -> 712.23333 | V7: 1 | W7: =D7/31*V7 -> 689.25806 | X7: 1 | Y7: =D7/31*X7 -> 689.25806 | Z7: 1 | AA7: =D7/28*Z7 -> 763.10714 | AB7: 1 | AC7: =D7/31*AB7 -> 689.25806
D8: 21367 | E8: 6 | L8: 1 | M8: =D8/31*L8 -> 689.25806 | N8: 1 | O8: =D8/31*N8 -> 689.25806 | P8: 1 | Q8: =D8/30*P8 -> 712.23333 | R8: 1 | S8: =D8/31*R8 -> 689.25806 | T8: 1 | U8: =D8/30*T8 -> 712.23333 | V8: 1 | W8: =D8/31*V8 -> 689.25806 | X8: 1 | Y8: =D8/31*X8 -> 689.25806 | Z8: 1 | AA8: =D8/28*Z8 -> 763.10714 | AB8: 1 | AC8: =D8/31*AB8 -> 689.25806
D9: 21367 | E9: 7 | L9: 1 | M9: =D9/31*L9 -> 689.25806 | N9: 1 | O9: =D9/31*N9 -> 689.25806 | P9: 1 | Q9: =D9/30*P9 -> 712.23333 | R9: 1 | S9: =D9/31*R9 -> 689.25806 | T9: 1 | U9: =D9/30*T9 -> 712.23333 | V9: 1 | W9: =D9/31*V9 -> 689.25806 | X9: 1 | Y9: =D9/31*X9 -> 689.25806 | Z9: 1 | AA9: =D9/28*Z9 -> 763.10714 | AB9: 1 | AC9: =D9/31*AB9 -> 689.25806
D10: 21367 | E10: 8 | L10: 1 | M10: =D10/31*L10 -> 689.25806 | N10: 1 | O10: =D10/31*N10 -> 689.25806 | P10: 0 | Q10: =D10/30*P10 -> 0 | R10: 1 | S10: =D10/31*R10 -> 689.25806 | T10: 1 | U10: =D10/30*T10 -> 712.23333 | V10: 1 | W10: =D10/31*V10 -> 689.25806 | X10: 1 | Y10: =D10/31*X10 -> 689.25806 | Z10: 1 | AA10: =D10/28*Z10 -> 763.10714 | AB10: 1 | AC10: =D10/31*AB10 -> 689.25806
D11: 21367 | E11: 9 | L11: 1 | M11: =D11/31*L11 -> 689.25806 | N11: 1 | O11: =D11/31*N11 -> 689.25806 | P11: 1 | Q11: =D11/30*P11 -> 712.23333 | R11: 1 | S11: =D11/31*R11 -> 689.25806 | T11: 1 | U11: =D11/30*T11 -> 712.23333 | V11: 1 | W11: =D11/31*V11 -> 689.25806 | X11: 1 | Y11: =D11/31*X11 -> 689.25806 | Z11: 1 | AA11: =D11/28*Z11 -> 763.10714 | AB11: 1 | AC11: =D11/31*AB11 -> 689.25806
D12: 21367 | E12: 10 | L12: 1 | M12: =D12/31*L12 -> 689.25806 | N12: 1 | O12: =D12/31*N12 -> 689.25806 | P12: 1 | Q12: =D12/30*P12 -> 712.23333 | R12: 0.5 | S12: =D12/31*R12 -> 344.62903 | T12: 1 | U12: =D12/30*T12 -> 712.23333 | V12: 1 | W12: =D12/31*V12 -> 689.25806 | X12: 1 | Y12: =D12/31*X12 -> 689.25806 | Z12: 1 | AA12: =D12/28*Z12 -> 763.10714 | AB12: 1 | AC12: =D12/31*AB12 -> 689.25806
D13: 21367 | E13: 11 | L13: 0 | M13: =D13/31*L13 -> 0 | N13: 1 | O13: =D13/31*N13 -> 689.25806 | P13: 1 | Q13: =D13/30*P13 -> 712.23333 | R13: 1 | S13: =D13/31*R13 -> 689.25806 | T13: 1 | U13: =D13/30*T13 -> 712.23333 | V13: 1 | W13: =D13/31*V13 -> 689.25806 | X13: 1 | Y13: =D13/31*X13 -> 689.25806 | Z13: 1 | AA13: =D13/28*Z13 -> 763.10714 | AB13: 1 | AC13: =D13/31*AB13 -> 689.25806
D14: 21367 | E14: 12 | L14: 1 | M14: =D14/31*L14 -> 689.25806 | N14: 1 | O14: =D14/31*N14 -> 689.25806 | P14: 1 | Q14: =D14/30*P14 -> 712.23333 | R14: 1 | S14: =D14/31*R14 -> 689.25806 | T14: 1 | U14: =D14/30*T14 -> 712.23333 | V14: 1 | W14: =D14/31*V14 -> 689.25806 | X14: 1 | Y14: =D14/31*X14 -> 689.25806 | Z14: 1 | AA14: =D14/28*Z14 -> 763.10714 | AB14: 1 | AC14: =D14/31*AB14 -> 689.25806
D15: 21367 | E15: 13 | L15: 1 | M15: =D15/31*L15 -> 689.25806 | N15: 1 | O15: =D15/31*N15 -> 689.25806 | P15: 1 | Q15: =D15/30*P15 -> 712.23333 | R15: 1 | S15: =D15/31*R15 -> 689.25806 | T15: 1 | U15: =D15/30*T15 -> 712.23333 | V15: 1 | W15: =D15/31*V15 -> 689.25806 | X15: 1 | Y15: =D15/31*X15 -> 689.25806 | Z15: 1 | AA15: =D15/28*Z15 -> 763.10714 | AB15: 1 | AC15: =D15/31*AB15 -> 689.25806
... D30: 21367 | E30: 28 | L30: 0 | M30: =D30/31*L30 -> 0 | N30: 1 | O30: =D30/31*N30 -> 689.25806 | P30: 1 | Q30: =D30/30*P30 -> 712.23333 | R30: 1 | S30: =D30/31*R30 -> 689.25806 | T30: 1 | U30: =D30/30*T30 -> 712.23333 | V30: 1 | W30: =D30/31*V30 -> 689.25806 | X30: 1 | Y30: =D30/31*X30 -> 689.25806 | Z30: 1 | AA30: =D30/28*Z30 -> 763.10714 | AB30: 1 | AC30: =D30/31*AB30 -> 689.25806
D31: 21367 | E31: 29 | L31: 1 | M31: =D31/31*L31 -> 689.25806 | N31: 1 | O31: =D31/31*N31 -> 689.25806 | P31: 1 | Q31: =D31/30*P31 -> 712.23333 | R31: 1 | S31: =D31/31*R31 -> 689.25806 | T31: 1 | U31: =D31/30*T31 -> 712.23333 | V31: 1 | W31: =D31/31*V31 -> 689.25806 | X31: 1 | Y31: =D31/31*X31 -> 689.25806 | AB31: 1 | AC31: =D31/31*AB31 -> 689.25806
D32: 21367 | E32: 30 | L32: 1 | M32: =D32/31*L32 -> 689.25806 | N32: 0.5 | O32: =D32/31*N32 -> 344.62903 | P32: 1 | Q32: =D32/30*P32 -> 712.23333 | R32: 1 | S32: =D32/31*R32 -> 689.25806 | T32: 1 | U32: =D32/30*T32 -> 712.23333 | V32: 1 | W32: =D32/31*V32 -> 689.25806 | X32: 1 | Y32: =D32/31*X32 -> 689.25806 | AB32: 1 | AC32: =D32/31*AB32 -> 689.25806
D33: 21367 | E33: 31 | L33: 1 | M33: =D33/31*L33 -> 689.25806 | N33: 1 | O33: =D33/31*N33 -> 689.25806 | R33: 1 | S33: =D33/31*R33 -> 689.25806 | V33: 1 | W33: =D33/31*V33 -> 689.25806 | X33: 1 | Y33: =D33/31*X33 -> 689.25806 | AB33: 1 | AC33: =D33/31*AB33 -> 689.25806
C34: CASUAL LEAVE | D34: 21367 | L34: 1 | M34: =D34/31*L34 -> 689.25806 | N34: 0.5 | O34: =D34/31*N34 -> 344.62903
C35: SICK LEAVE | D35: 21367 | N35: 1 | O35: =D35/31*N35 -> 689.25806
C36: COMP OFF | D36: 21367
L37: =SUM(L3:L36) -> 22 | M37: =SUM(M3:M36) -> 15163.677 | N37: =SUM(N3:N36) -> 31 | O37: =SUM(O3:O36) -> 21367 | P37: =SUM(P3:P36) -> 27.5 | Q37: =SUM(Q3:Q36) -> 19586.417 | R37: =SUM(R3:R36) -> 30.5 | S37: =SUM(S3:S36) -> 21022.371 | ... AC37: =SUM(AC3:AC36) -> 21367

Sheet ANAKHA JOY
A1: Name | B1: Designation | C1: Project | D1: Monthly CTC | E1: Date | F1: 45748 | H1: 45778 | J1: 45809 | L1: 45839 | N1: 45870 | P1: 45901 | R1: 45931 | T1: 45962 | V1: 45992 | X1: 46023 | Z1: 46054 | AB1: 46082
F2: Attendance | G2: Amount | H2: Attendance | I2: Amount | J2: Attendance | K2: Amount | L2: Attendance | M2: Amount | N2: Attendance | O2: Amount | P2: Attendance | Q2: Amount | R2: Attendance | S2: Amount | T2: Attendance | U2: Amount | V2: Attendance | W2: Amount | X2: Attendance | Y2: Amount | Z2: Attendance | AA2: Amount | AB2: Attendance | AC2: Amount
A3: ANAKHA JOY | B3: FIELD ASSISTANT | C3: CORE TEAM | D3: 21367 | E3: 1 | L3: 1 | M3: =D3/31*L3 -> 689.25806 | N3: 1 | O3: =D3/31*N3 -> 689.25806 | P3: 1 | Q3: =D3/30*P3 -> 712.23333 | R3: 1 | S3: =D3/31*R3 -> 689.25806 | T3: 1 | U3: =D3/30*T3 -> 712.23333 | V3: 1 | W3: =D3/31*V3 -> 689.25806 | X3: 1 | Y3: =D3/31*X3 -> 689.25806 | Z3: 1 | AA3: =D3/28*Z3 -> 763.10714 | AB3: 1 | AC3: =D3/31*AB3 -> 689.25806
D4: 21367 | E4: 2 | L4: 1 | M4: =D4/31*L4 -> 689.25806 | N4: 0 | O4: =D4/31*N4 -> 0 | P4: 1 | Q4: =D4/30*P4 -> 712.23333 | R4: 1 | S4: =D4/31*R4 -> 689.25806 | T4: 1 | U4: =D4/30*T4 -> 712.23333 | V4: 1 | W4: =D4/31*V4 -> 689.25806 | X4: 1 | Y4: =D4/31*X4 -> 689.25806 | Z4: 1 | AA4: =D4/28*Z4 -> 763.10714 | AB4: 1 | AC4: =D4/31*AB4 -> 689.25806
D5: 21367 | E5: 3 | L5: 1 | M5: =D5/31*L5 -> 689.25806 | N5: 1 | O5: =D5/31*N5 -> 689.25806 | P5: 1 | Q5: =D5/30*P5 -> 712.23333 | R5: 1 | S5: =D5/31*R5 -> 689.25806 | T5: 1 | U5: =D5/30*T5 -> 712.23333 | V5: 1 | W5: =D5/31*V5 -> 689.25806 | X5: 1 | Y5: =D5/31*X5 -> 689.25806 | Z5: 1 | AA5: =D5/28*Z5 -> 763.10714 | AB5: 1 | AC5: =D5/31*AB5 -> 689.25806
D6: 21367 | E6: 4 | L6: 1 | M6: =D6/31*L6 -> 689.25806 | N6: 0 | O6: =D6/31*N6 -> 0 | P6: 1 | Q6: =D6/30*P6 -> 712.23333 | R6: 1 | S6: =D6/31*R6 -> 689.25806 | T6: 1 | U6: =D6/30*T6 -> 712.23333 | V6: 1 | W6: =D6/31*V6 -> 689.25806 | X6: 1 | Y6: =D6/31*X6 -> 689.25806 | Z6: 1 | AA6: =D6/28*Z6 -> 763.10714 | AB6: 1 | AC6: =D6/31*AB6 -> 689.25806
D7: 21367 | E7: 5 | L7: 0 | M7: =D7/31*L7 -> 0 | N7: 0 | O7: =D7/31*N7 -> 0 | P7: 1 | Q7: =D7/30*P7 -> 712.23333 | R7: 1 | S7: =D7/31*R7 -> 689.25806 | T7: 1 | U7: =D7/30*T7 -> 712.23333 | V7: 1 | W7: =D7/31*V7 -> 689.25806 | X7: 1 | Y7: =D7/31*X7 -> 689.25806 | Z7: 1 | AA7: =D7/28*Z7 -> 763.10714 | AB7: 1 | AC7: =D7/31*AB7 -> 689.25806
D8: 21367 | E8: 6 | L8: 1 | M8: =D8/31*L8 -> 689.25806 | N8: 1 | O8: =D8/31*N8 -> 689.25806 | P8: 1 | Q8: =D8/30*P8 -> 712.23333 | R8: 1 | S8: =D8/31*R8 -> 689.25806 | T8: 1 | U8: =D8/30*T8 -> 712.23333 | V8: 1 | W8: =D8/31*V8 -> 689.25806 | X8: 1 | Y8: =D8/31*X8 -> 689.25806 | Z8: 1 | AA8: =D8/28*Z8 -> 763.10714 | AB8: 1 | AC8: =D8/31*AB8 -> 689.25806
D9: 21367 | E9: 7 | L9: 1 | M9: =D9/31*L9 -> 689.25806 | N9: 1 | O9: =D9/31*N9 -> 689.25806 | P9: 1 | Q9: =D9/30*P9 -> 712.23333 | R9: 0 | S9: =D9/31*R9 -> 0 | T9: 1 | U9: =D9/30*T9 -> 712.23333 | V9: 1 | W9: =D9/31*V9 -> 689.25806 | X9: 1 | Y9: =D9/31*X9 -> 689.25806 | Z9: 1 | AA9: =D9/28*Z9 -> 763.10714 | AB9: 1 | AC9: =D9/31*AB9 -> 689.25806
D10: 21367 | E10: 8 | L10: 1 | M10: =D10/31*L10 -> 689.25806 | N10: 1 | O10: =D10/31*N10 -> 689.25806 | P10: 1 | Q10: =D10/30*P10 -> 712.23333 | R10: 1 | S10: =D10/31*R10 -> 689.25806 | T10: 1 | U10: =D10/30*T10 -> 712.23333 | V10: 1 | W10: =D10/31*V10 -> 689.25806 | X10: 1 | Y10: =D10/31*X10 -> 689.25806 | Z10: 1 | AA10: =D10/28*Z10 -> 763.10714 | AB10: 1 | AC10: =D10/31*AB10 -> 689.25806
D11: 21367 | E11: 9 | L11: 0 | M11: =D11/31*L11 -> 0 | N11: 1 | O11: =D11/31*N11 -> 689.25806 | P11: 1 | Q11: =D11/30*P11 -> 712.23333 | R11: 0.5 | S11: =D11/31*R11 -> 344.62903 | T11: 1 | U11: =D11/30*T11 -> 712.23333 | V11: 1 | W11: =D11/31*V11 -> 689.25806 | X11: 1 | Y11: =D11/31*X11 -> 689.25806 | Z11: 1 | AA11: =D11/28*Z11 -> 763.10714 | AB11: 1 | AC11: =D11/31*AB11 -> 689.25806
D12: 21367 | E12: 10 | L12: 1 | M12: =D12/31*L12 -> 689.25806 | N12: 1 | O12: =D12/31*N12 -> 689.25806 | P12: 1 | Q12: =D12/30*P12 -> 712.23333 | R12: 1 | S12: =D12/31*R12 -> 689.25806 | T12: 1 | U12: =D12/30*T12 -> 712.23333 | V12: 1 | W12: =D12/31*V12 -> 689.25806 | X12: 1 | Y12: =D12/31*X12 -> 689.25806 | Z12: 1 | AA12: =D12/28*Z12 -> 763.10714 | AB12: 1 | AC12: =D12/31*AB12 -> 689.25806
D13: 21367 | E13: 11 | L13: 1 | M13: =D13/31*L13 -> 689.25806 | N13: 1 | O13: =D13/31*N13 -> 689.25806 | P13: 0 | Q13: =D13/30*P13 -> 0 | R13: 1 | S13: =D13/31*R13 -> 689.25806 | T13: 1 | U13: =D13/30*T13 -> 712.23333 | V13: 1 | W13: =D13/31*V13 -> 689.25806 | X13: 1 | Y13: =D13/31*X13 -> 689.25806 | Z13: 1 | AA13: =D13/28*Z13 -> 763.10714 | AB13: 1 | AC13: =D13/31*AB13 -> 689.25806
D14: 21367 | E14: 12 | L14: 1 | M14: =D14/31*L14 -> 689.25806 | N14: 1 | O14: =D14/31*N14 -> 689.25806 | P14: 0 | Q14: =D14/30*P14 -> 0 | R14: 1 | S14: =D14/31*R14 -> 689.25806 | T14: 1 | U14: =D14/30*T14 -> 712.23333 | V14: 1 | W14: =D14/31*V14 -> 689.25806 | X14: 1 | Y14: =D14/31*X14 -> 689.25806 | Z14: 1 | AA14: =D14/28*Z14 -> 763.10714 | AB14: 1 | AC14: =D14/31*AB14 -> 689.25806
D15: 21367 | E15: 13 | L15: 1 | M15: =D15/31*L15 -> 689.25806 | N15: 0.5 | O15: =D15/31*N15 -> 344.62903 | P15: 1 | Q15: =D15/30*P15 -> 712.23333 | R15: 1 | S15: =D15/31*R15 -> 689.25806 | T15: 1 | U15: =D15/30*T15 -> 712.23333 | V15: 1 | W15: =D15/31*V15 -> 689.25806 | X15: 1 | Y15: =D15/31*X15 -> 689.25806 | Z15: 1 | AA15: =D15/28*Z15 -> 763.10714 | AB15: 1 | AC15: =D15/31*AB15 -> 689.25806
... D30: 21367 | E30: 28 | L30: 1 | M30: =D30/31*L30 -> 689.25806 | N30: 1 | O30: =D30/31*N30 -> 689.25806 | P30: 1 | Q30: =D30/30*P30 -> 712.23333 | R30: 1 | S30: =D30/31*R30 -> 689.25806 | T30: 1 | U30: =D30/30*T30 -> 712.23333 | V30: 1 | W30: =D30/31*V30 -> 689.25806 | X30: 1 | Y30: =D30/31*X30 -> 689.25806 | Z30: 1 | AA30: =D30/28*Z30 -> 763.10714 | AB30: 1 | AC30: =D30/31*AB30 -> 689.25806
D31: 21367 | E31: 29 | L31: 1 | M31: =D31/31*L31 -> 689.25806 | N31: 1 | O31: =D31/31*N31 -> 689.25806 | P31: 1 | Q31: =D31/30*P31 -> 712.23333 | R31: 1 | S31: =D31/31*R31 -> 689.25806 | T31: 1 | U31: =D31/30*T31 -> 712.23333 | V31: 1 | W31: =D31/31*V31 -> 689.25806 | X31: 1 | Y31: =D31/31*X31 -> 689.25806 | AB31: 1 | AC31: =D31/31*AB31 -> 689.25806
D32: 21367 | E32: 30 | L32: 1 | M32: =D32/31*L32 -> 689.25806 | N32: 0 | O32: =D32/31*N32 -> 0 | P32: 1 | Q32: =D32/30*P32 -> 712.23333 | R32: 1 | S32: =D32/31*R32 -> 689.25806 | T32: 1 | U32: =D32/30*T32 -> 712.23333 | V32: 1 | W32: =D32/31*V32 -> 689.25806 | X32: 1 | Y32: =D32/31*X32 -> 689.25806 | AB32: 1 | AC32: =D32/31*AB32 -> 689.25806
D33: 21367 | E33: 31 | L33: 1 | M33: =D33/31*L33 -> 689.25806 | N33: 1 | O33: =D33/31*N33 -> 689.25806 | R33: 1 | S33: =D33/31*R33 -> 689.25806 | V33: 1 | W33: =D33/31*V33 -> 689.25806 | X33: 1 | Y33: =D33/31*X33 -> 689.25806 | AB33: 1 | AC33: =D33/31*AB33 -> 689.25806
C34: CASUAL LEAVE | D34: 21367 | L34: 2 | M34: =D34/31*L34 -> 1378.5161 | N34: 1 | O34: =D34/31*N34 -> 689.25806
C35: SICK LEAVE | D35: 21367 | L35: 1 | M35: =D35/31*L35 -> 689.25806 | N35: 1 | O35: =D35/31*N35 -> 689.25806
C36: COMP OFF | D36: 21367
L37: =SUM(L3:L36) -> 30 | M37: =SUM(M3:M36) -> 20677.742 | N37: =SUM(N3:N36) -> 27.5 | O37: =SUM(O3:O36) -> 18954.597 | P37: =SUM(P3:P36) -> 25 | Q37: =SUM(Q3:Q36) -> 17805.833 | R37: =SUM(R3:R36) -> 29.5 | S37: =SUM(S3:S36) -> 20333.113 | ... AC37: =SUM(AC3:AC36) -> 21367

Sheet SOUMYA S K
A1: Name | B1: Designation | C1: Project | D1: Monthly CTC | E1: Date | F1: 45748 | H1: 45778 | J1: 45809 | L1: 45839 | N1: 45870 | P1: 45901 | R1: 45931 | T1: 45962 | V1: 45992 | X1: 46023 | Z1: 46054 | AB1: 46082
F2: Attendance | G2: Amount | H2: Attendance | I2: Amount | J2: Attendance | K2: Amount | L2: Attendance | M2: Amount | N2: Attendance | O2: Amount | P2: Attendance | Q2: Amount | R2: Attendance | S2: Amount | T2: Attendance | U2: Amount | V2: Attendance | W2: Amount | X2: Attendance | Y2: Amount | Z2: Attendance | AA2: Amount | AB2: Attendance | AC2: Amount
A3: SOUMYA S K | B3: FIELD ASSISTANT | C3: CORE TEAM | D3: 23980 | E3: 1 | L3: 1 | M3: =D3/31*L3 -> 773.54839 | N3: 0.5 | O3: =D3/31*N3 -> 386.77419 | P3: 1 | Q3: =D3/30*P3 -> 799.33333 | R3: 1 | S3: =D3/31*R3 -> 773.54839 | T3: 1 | U3: =D3/30*T3 -> 799.33333 | V3: 1 | W3: =D3/31*V3 -> 773.54839 | X3: 1 | Y3: =D3/31*X3 -> 773.54839 | Z3: 1 | AA3: =D3/28*Z3 -> 856.42857 | AB3: 1 | AC3: =D3/31*AB3 -> 773.54839
D4: 23980 | E4: 2 | L4: 1 | M4: =D4/31*L4 -> 773.54839 | N4: 0 | O4: =D4/31*N4 -> 0 | P4: 1 | Q4: =D4/30*P4 -> 799.33333 | R4: 1 | S4: =D4/31*R4 -> 773.54839 | T4: 1 | U4: =D4/30*T4 -> 799.33333 | V4: 1 | W4: =D4/31*V4 -> 773.54839 | X4: 1 | Y4: =D4/31*X4 -> 773.54839 | Z4: 1 | AA4: =D4/28*Z4 -> 856.42857 | AB4: 1 | AC4: =D4/31*AB4 -> 773.54839
D5: 23980 | E5: 3 | L5: 0 | M5: =D5/31*L5 -> 0 | N5: 1 | O5: =D5/31*N5 -> 773.54839 | P5: 0.5 | Q5: =D5/30*P5 -> 399.66667 | R5: 1 | S5: =D5/31*R5 -> 773.54839 | T5: 1 | U5: =D5/30*T5 -> 799.33333 | V5: 1 | W5: =D5/31*V5 -> 773.54839 | X5: 1 | Y5: =D5/31*X5 -> 773.54839 | Z5: 1 | AA5: =D5/28*Z5 -> 856.42857 | AB5: 1 | AC5: =D5/31*AB5 -> 773.54839
D6: 23980 | E6: 4 | L6: 0.5 | M6: =D6/31*L6 -> 386.77419 | N6: 1 | O6: =D6/31*N6 -> 773.54839 | P6: 1 | Q6: =D6/30*P6 -> 799.33333 | R6: 1 | S6: =D6/31*R6 -> 773.54839 | T6: 1 | U6: =D6/30*T6 -> 799.33333 | V6: 1 | W6: =D6/31*V6 -> 773.54839 | X6: 1 | Y6: =D6/31*X6 -> 773.54839 | Z6: 1 | AA6: =D6/28*Z6 -> 856.42857 | AB6: 1 | AC6: =D6/31*AB6 -> 773.54839
D7: 23980 | E7: 5 | L7: 1 | M7: =D7/31*L7 -> 773.54839 | N7: 0 | O7: =D7/31*N7 -> 0 | P7: 1 | Q7: =D7/30*P7 -> 799.33333 | R7: 1 | S7: =D7/31*R7 -> 773.54839 | T7: 1 | U7: =D7/30*T7 -> 799.33333 | V7: 1 | W7: =D7/31*V7 -> 773.54839 | X7: 1 | Y7: =D7/31*X7 -> 773.54839 | Z7: 1 | AA7: =D7/28*Z7 -> 856.42857 | AB7: 1 | AC7: =D7/31*AB7 -> 773.54839
D8: 23980 | E8: 6 | L8: 1 | M8: =D8/31*L8 -> 773.54839 | N8: 1 | O8: =D8/31*N8 -> 773.54839 | P8: 1 | Q8: =D8/30*P8 -> 799.33333 | R8: 1 | S8: =D8/31*R8 -> 773.54839 | T8: 1 | U8: =D8/30*T8 -> 799.33333 | V8: 1 | W8: =D8/31*V8 -> 773.54839 | X8: 1 | Y8: =D8/31*X8 -> 773.54839 | Z8: 1 | AA8: =D8/28*Z8 -> 856.42857 | AB8: 1 | AC8: =D8/31*AB8 -> 773.54839
D9: 23980 | E9: 7 | L9: 0 | M9: =D9/31*L9 -> 0 | N9: 1 | O9: =D9/31*N9 -> 773.54839 | P9: 1 | Q9: =D9/30*P9 -> 799.33333 | R9: 1 | S9: =D9/31*R9 -> 773.54839 | T9: 1 | U9: =D9/30*T9 -> 799.33333 | V9: 1 | W9: =D9/31*V9 -> 773.54839 | X9: 1 | Y9: =D9/31*X9 -> 773.54839 | Z9: 1 | AA9: =D9/28*Z9 -> 856.42857 | AB9: 1 | AC9: =D9/31*AB9 -> 773.54839
D10: 23980 | E10: 8 | L10: 1 | M10: =D10/31*L10 -> 773.54839 | N10: 1 | O10: =D10/31*N10 -> 773.54839 | P10: 0 | Q10: =D10/30*P10 -> 0 | R10: 1 | S10: =D10/31*R10 -> 773.54839 | T10: 1 | U10: =D10/30*T10 -> 799.33333 | V10: 1 | W10: =D10/31*V10 -> 773.54839 | X10: 1 | Y10: =D10/31*X10 -> 773.54839 | Z10: 1 | AA10: =D10/28*Z10 -> 856.42857 | AB10: 1 | AC10: =D10/31*AB10 -> 773.54839
D11: 23980 | E11: 9 | L11: 0 | M11: =D11/31*L11 -> 0 | N11: 1 | O11: =D11/31*N11 -> 773.54839 | P11: 1 | Q11: =D11/30*P11 -> 799.33333 | R11: 1 | S11: =D11/31*R11 -> 773.54839 | T11: 1 | U11: =D11/30*T11 -> 799.33333 | V11: 1 | W11: =D11/31*V11 -> 773.54839 | X11: 1 | Y11: =D11/31*X11 -> 773.54839 | Z11: 1 | AA11: =D11/28*Z11 -> 856.42857 | AB11: 1 | AC11: =D11/31*AB11 -> 773.54839
D12: 23980 | E12: 10 | L12: 1 | M12: =D12/31*L12 -> 773.54839 | N12: 1 | O12: =D12/31*N12 -> 773.54839 | P12: 1 | Q12: =D12/30*P12 -> 799.33333 | R12: 1 | S12: =D12/31*R12 -> 773.54839 | T12: 1 | U12: =D12/30*T12 -> 799.33333 | V12: 1 | W12: =D12/31*V12 -> 773.54839 | X12: 1 | Y12: =D12/31*X12 -> 773.54839 | Z12: 1 | AA12: =D12/28*Z12 -> 856.42857 | AB12: 1 | AC12: =D12/31*AB12 -> 773.54839
D13: 23980 | E13: 11 | L13: 1 | M13: =D13/31*L13 -> 773.54839 | N13: 1 | O13: =D13/31*N13 -> 773.54839 | P13: 1 | Q13: =D13/30*P13 -> 799.33333 | R13: 1 | S13: =D13/31*R13 -> 773.54839 | T13: 1 | U13: =D13/30*T13 -> 799.33333 | V13: 1 | W13: =D13/31*V13 -> 773.54839 | X13: 1 | Y13: =D13/31*X13 -> 773.54839 | Z13: 1 | AA13: =D13/28*Z13 -> 856.42857 | AB13: 1 | AC13: =D13/31*AB13 -> 773.54839
D14: 23980 | E14: 12 | L14: 1 | M14: =D14/31*L14 -> 773.54839 | N14: 1 | O14: =D14/31*N14 -> 773.54839 | P14: 0.5 | Q14: =D14/30*P14 -> 399.66667 | R14: 1 | S14: =D14/31*R14 -> 773.54839 | T14: 1 | U14: =D14/30*T14 -> 799.33333 | V14: 1 | W14: =D14/31*V14 -> 773.54839 | X14: 1 | Y14: =D14/31*X14 -> 773.54839 | Z14: 1 | AA14: =D14/28*Z14 -> 856.42857 | AB14: 1 | AC14: =D14/31*AB14 -> 773.54839
D15: 23980 | E15: 13 | L15: 1 | M15: =D15/31*L15 -> 773.54839 | N15: 1 | O15: =D15/31*N15 -> 773.54839 | P15: 1 | Q15: =D15/30*P15 -> 799.33333 | R15: 1 | S15: =D15/31*R15 -> 773.54839 | T15: 1 | U15: =D15/30*T15 -> 799.33333 | V15: 1 | W15: =D15/31*V15 -> 773.54839 | X15: 1 | Y15: =D15/31*X15 -> 773.54839 | Z15: 1 | AA15: =D15/28*Z15 -> 856.42857 | AB15: 1 | AC15: =D15/31*AB15 -> 773.54839
... D30: 23980 | E30: 28 | L30: 1 | M30: =D30/31*L30 -> 773.54839 | N30: 1 | O30: =D30/31*N30 -> 773.54839 | P30: 1 | Q30: =D30/30*P30 -> 799.33333 | R30: 1 | S30: =D30/31*R30 -> 773.54839 | T30: 1 | U30: =D30/30*T30 -> 799.33333 | V30: 1 | W30: =D30/31*V30 -> 773.54839 | X30: 1 | Y30: =D30/31*X30 -> 773.54839 | Z30: 1 | AA30: =D30/28*Z30 -> 856.42857 | AB30: 1 | AC30: =D30/31*AB30 -> 773.54839
D31: 23980 | E31: 29 | L31: 1 | M31: =D31/31*L31 -> 773.54839 | N31: 1 | O31: =D31/31*N31 -> 773.54839 | P31: 1 | Q31: =D31/30*P31 -> 799.33333 | R31: 1 | S31: =D31/31*R31 -> 773.54839 | T31: 1 | U31: =D31/30*T31 -> 799.33333 | V31: 1 | W31: =D31/31*V31 -> 773.54839 | X31: 1 | Y31: =D31/31*X31 -> 773.54839 | AB31: 1 | AC31: =D31/31*AB31 -> 773.54839
D32: 23980 | E32: 30 | L32: 1 | M32: =D32/31*L32 -> 773.54839 | N32: 1 | O32: =D32/31*N32 -> 773.54839 | P32: 1 | Q32: =D32/30*P32 -> 799.33333 | R32: 1 | S32: =D32/31*R32 -> 773.54839 | T32: 1 | U32: =D32/30*T32 -> 799.33333 | V32: 1 | W32: =D32/31*V32 -> 773.54839 | X32: 1 | Y32: =D32/31*X32 -> 773.54839 | AB32: 1 | AC32: =D32/31*AB32 -> 773.54839
D33: 23980 | E33: 31 | L33: 1 | M33: =D33/31*L33 -> 773.54839 | N33: 1 | O33: =D33/31*N33 -> 773.54839 | R33: 1 | S33: =D33/31*R33 -> 773.54839 | V33: 1 | W33: =D33/31*V33 -> 773.54839 | X33: 1 | Y33: =D33/31*X33 -> 773.54839 | AB33: 1 | AC33: =D33/31*AB33 -> 773.54839
C34: CASUAL LEAVE | D34: 23980 | L34: 1 | M34: =D34/31*L34 -> 773.54839 | N34: 1 | O34: =D34/31*N34 -> 773.54839
C35: SICK LEAVE | D35: 23980 | L35: 0 | M35: =D35/31*L35 -> 0 | N35: 1 | O35: =D35/31*N35 -> 773.54839
C36: COMP OFF | D36: 23980 | L36: 1 | M36: =D36/31*L36 -> 773.54839
L37: =SUM(L3:L36) -> 28.5 | M37: =SUM(M3:M36) -> 22046.129 | N37: =SUM(N3:N36) -> 26.5 | O37: =SUM(O3:O36) -> 20499.032 | P37: =SUM(P3:P36) -> 26.5 | Q37: =SUM(Q3:Q36) -> 21182.333 | R37: =SUM(R3:R36) -> 30 | S37: =SUM(S3:S36) -> 23206.452 | ... AC37: =SUM(AC3:AC36) -> 23980

Sheet VIGNESH KUMAR
A1: Name | B1: Designation | C1: Project | D1: Monthly CTC | E1: Date | F1: 45748 | H1: 45778 | J1: 45809 | L1: 45839 | N1: 45870 | P1: 45901 | R1: 45931 | T1: 45962 | V1: 45992 | X1: 46023 | Z1: 46054 | AB1: 46082
F2: Attendance | G2: Amount | H2: Attendance | I2: Amount | J2: Attendance | K2: Amount | L2: Attendance | M2: Amount | N2: Attendance | O2: Amount | P2: Attendance | Q2: Amount | R2: Attendance | S2: Amount | T2: Attendance | U2: Amount | V2: Attendance | W2: Amount | X2: Attendance | Y2: Amount | Z2: Attendance | AA2: Amount | AB2: Attendance | AC2: Amount
A3: VIGNESH KUMAR P B | B3: OFFICE ASSISTANT | C3: CORE TEAM | D3: 22689 | E3: 1 | L3: 0 | M3: =D3/31*L3 -> 0 | N3: 1 | O3: =D3/31*N3 -> 731.90323 | P3: 1 | Q3: =D3/30*P3 -> 756.3 | R3: 1 | S3: =D3/31*R3 -> 731.90323 | T3: 1 | U3: =D3/30*T3 -> 756.3 | V3: 1 | W3: =D3/31*V3 -> 731.90323 | X3: 1 | Y3: =D3/31*X3 -> 731.90323 | Z3: 1 | AA3: =D3/28*Z3 -> 810.32143 | AB3: 1 | AC3: =D3/31*AB3 -> 731.90323
D4: 22689 | E4: 2 | L4: 0 | M4: =D4/31*L4 -> 0 | N4: 1 | O4: =D4/31*N4 -> 731.90323 | P4: 1 | Q4: =D4/30*P4 -> 756.3 | R4: 1 | S4: =D4/31*R4 -> 731.90323 | T4: 1 | U4: =D4/30*T4 -> 756.3 | V4: 1 | W4: =D4/31*V4 -> 731.90323 | X4: 1 | Y4: =D4/31*X4 -> 731.90323 | Z4: 1 | AA4: =D4/28*Z4 -> 810.32143 | AB4: 1 | AC4: =D4/31*AB4 -> 731.90323
D5: 22689 | E5: 3 | L5: 0 | M5: =D5/31*L5 -> 0 | N5: 1 | O5: =D5/31*N5 -> 731.90323 | P5: 1 | Q5: =D5/30*P5 -> 756.3 | R5: 1 | S5: =D5/31*R5 -> 731.90323 | T5: 1 | U5: =D5/30*T5 -> 756.3 | V5: 1 | W5: =D5/31*V5 -> 731.90323 | X5: 1 | Y5: =D5/31*X5 -> 731.90323 | Z5: 1 | AA5: =D5/28*Z5 -> 810.32143 | AB5: 1 | AC5: =D5/31*AB5 -> 731.90323
D6: 22689 | E6: 4 | L6: 0 | M6: =D6/31*L6 -> 0 | N6: 1 | O6: =D6/31*N6 -> 731.90323 | P6: 1 | Q6: =D6/30*P6 -> 756.3 | R6: 1 | S6: =D6/31*R6 -> 731.90323 | T6: 1 | U6: =D6/30*T6 -> 756.3 | V6: 1 | W6: =D6/31*V6 -> 731.90323 | X6: 1 | Y6: =D6/31*X6 -> 731.90323 | Z6: 1 | AA6: =D6/28*Z6 -> 810.32143 | AB6: 1 | AC6: =D6/31*AB6 -> 731.90323
D7: 22689 | E7: 5 | L7: 1 | M7: =D7/31*L7 -> 731.90323 | N7: 1 | O7: =D7/31*N7 -> 731.90323 | P7: 1 | Q7: =D7/30*P7 -> 756.3 | R7: 1 | S7: =D7/31*R7 -> 731.90323 | T7: 1 | U7: =D7/30*T7 -> 756.3 | V7: 1 | W7: =D7/31*V7 -> 731.90323 | X7: 1 | Y7: =D7/31*X7 -> 731.90323 | Z7: 1 | AA7: =D7/28*Z7 -> 810.32143 | AB7: 1 | AC7: =D7/31*AB7 -> 731.90323
D8: 22689 | E8: 6 | L8: 1 | M8: =D8/31*L8 -> 731.90323 | N8: 1 | O8: =D8/31*N8 -> 731.90323 | P8: 1 | Q8: =D8/30*P8 -> 756.3 | R8: 1 | S8: =D8/31*R8 -> 731.90323 | T8: 1 | U8: =D8/30*T8 -> 756.3 | V8: 1 | W8: =D8/31*V8 -> 731.90323 | X8: 1 | Y8: =D8/31*X8 -> 731.90323 | Z8: 1 | AA8: =D8/28*Z8 -> 810.32143 | AB8: 1 | AC8: =D8/31*AB8 -> 731.90323
D9: 22689 | E9: 7 | L9: 1 | M9: =D9/31*L9 -> 731.90323 | N9: 1 | O9: =D9/31*N9 -> 731.90323 | P9: 1 | Q9: =D9/30*P9 -> 756.3 | R9: 1 | S9: =D9/31*R9 -> 731.90323 | T9: 1 | U9: =D9/30*T9 -> 756.3 | V9: 1 | W9: =D9/31*V9 -> 731.90323 | X9: 1 | Y9: =D9/31*X9 -> 731.90323 | Z9: 1 | AA9: =D9/28*Z9 -> 810.32143 | AB9: 1 | AC9: =D9/31*AB9 -> 731.90323
D10: 22689 | E10: 8 | L10: 1 | M10: =D10/31*L10 -> 731.90323 | N10: 1 | O10: =D10/31*N10 -> 731.90323 | P10: 1 | Q10: =D10/30*P10 -> 756.3 | R10: 1 | S10: =D10/31*R10 -> 731.90323 | T10: 1 | U10: =D10/30*T10 -> 756.3 | V10: 1 | W10: =D10/31*V10 -> 731.90323 | X10: 1 | Y10: =D10/31*X10 -> 731.90323 | Z10: 1 | AA10: =D10/28*Z10 -> 810.32143 | AB10: 1 | AC10: =D10/31*AB10 -> 731.90323
D11: 22689 | E11: 9 | L11: 1 | M11: =D11/31*L11 -> 731.90323 | N11: 1 | O11: =D11/31*N11 -> 731.90323 | P11: 1 | Q11: =D11/30*P11 -> 756.3 | R11: 1 | S11: =D11/31*R11 -> 731.90323 | T11: 1 | U11: =D11/30*T11 -> 756.3 | V11: 1 | W11: =D11/31*V11 -> 731.90323 | X11: 1 | Y11: =D11/31*X11 -> 731.90323 | Z11: 1 | AA11: =D11/28*Z11 -> 810.32143 | AB11: 1 | AC11: =D11/31*AB11 -> 731.90323
D12: 22689 | E12: 10 | L12: 1 | M12: =D12/31*L12 -> 731.90323 | N12: 1 | O12: =D12/31*N12 -> 731.90323 | P12: 1 | Q12: =D12/30*P12 -> 756.3 | R12: 1 | S12: =D12/31*R12 -> 731.90323 | T12: 1 | U12: =D12/30*T12 -> 756.3 | V12: 1 | W12: =D12/31*V12 -> 731.90323 | X12: 1 | Y12: =D12/31*X12 -> 731.90323 | Z12: 1 | AA12: =D12/28*Z12 -> 810.32143 | AB12: 1 | AC12: =D12/31*AB12 -> 731.90323
D13: 22689 | E13: 11 | L13: 1 | M13: =D13/31*L13 -> 731.90323 | N13: 1 | O13: =D13/31*N13 -> 731.90323 | P13: 1 | Q13: =D13/30*P13 -> 756.3 | R13: 1 | S13: =D13/31*R13 -> 731.90323 | T13: 1 | U13: =D13/30*T13 -> 756.3 | V13: 1 | W13: =D13/31*V13 -> 731.90323 | X13: 1 | Y13: =D13/31*X13 -> 731.90323 | Z13: 1 | AA13: =D13/28*Z13 -> 810.32143 | AB13: 1 | AC13: =D13/31*AB13 -> 731.90323
D14: 22689 | E14: 12 | L14: 1 | M14: =D14/31*L14 -> 731.90323 | N14: 1 | O14: =D14/31*N14 -> 731.90323 | P14: 1 | Q14: =D14/30*P14 -> 756.3 | R14: 1 | S14: =D14/31*R14 -> 731.90323 | T14: 1 | U14: =D14/30*T14 -> 756.3 | V14: 1 | W14: =D14/31*V14 -> 731.90323 | X14: 1 | Y14: =D14/31*X14 -> 731.90323 | Z14: 1 | AA14: =D14/28*Z14 -> 810.32143 | AB14: 1 | AC14: =D14/31*AB14 -> 731.90323
D15: 22689 | E15: 13 | L15: 1 | M15: =D15/31*L15 -> 731.90323 | N15: 1 | O15: =D15/31*N15 -> 731.90323 | P15: 1 | Q15: =D15/30*P15 -> 756.3 | R15: 1 | S15: =D15/31*R15 -> 731.90323 | T15: 1 | U15: =D15/30*T15 -> 756.3 | V15: 1 | W15: =D15/31*V15 -> 731.90323 | X15: 1 | Y15: =D15/31*X15 -> 731.90323 | Z15: 1 | AA15: =D15/28*Z15 -> 810.32143 | AB15: 1 | AC15: =D15/31*AB15 -> 731.90323
... D30: 22689 | E30: 28 | L30: 1 | M30: =D30/31*L30 -> 731.90323 | N30: 1 | O30: =D30/31*N30 -> 731.90323 | P30: 1 | Q30: =D30/30*P30 -> 756.3 | R30: 1 | S30: =D30/31*R30 -> 731.90323 | T30: 1 | U30: =D30/30*T30 -> 756.3 | V30: 1 | W30: =D30/31*V30 -> 731.90323 | X30: 1 | Y30: =D30/31*X30 -> 731.90323 | Z30: 1 | AA30: =D30/28*Z30 -> 810.32143 | AB30: 1 | AC30: =D30/31*AB30 -> 731.90323
D31: 22689 | E31: 29 | L31: 1 | M31: =D31/31*L31 -> 731.90323 | N31: 1 | O31: =D31/31*N31 -> 731.90323 | P31: 1 | Q31: =D31/30*P31 -> 756.3 | R31: 1 | S31: =D31/31*R31 -> 731.90323 | T31: 1 | U31: =D31/30*T31 -> 756.3 | V31: 1 | W31: =D31/31*V31 -> 731.90323 | X31: 1 | Y31: =D31/31*X31 -> 731.90323 | AB31: 1 | AC31: =D31/31*AB31 -> 731.90323
D32: 22689 | E32: 30 | L32: 1 | M32: =D32/31*L32 -> 731.90323 | N32: 1 | O32: =D32/31*N32 -> 731.90323 | P32: 1 | Q32: =D32/30*P32 -> 756.3 | R32: 1 | S32: =D32/31*R32 -> 731.90323 | T32: 1 | U32: =D32/30*T32 -> 756.3 | V32: 1 | W32: =D32/31*V32 -> 731.90323 | X32: 1 | Y32: =D32/31*X32 -> 731.90323 | AB32: 1 | AC32: =D32/31*AB32 -> 731.90323
D33: 22689 | E33: 31 | L33: 1 | M33: =D33/31*L33 -> 731.90323 | N33: 1 | O33: =D33/31*N33 -> 731.90323 | R33: 1 | S33: =D33/31*R33 -> 731.90323 | V33: 1 | W33: =D33/31*V33 -> 731.90323 | X33: 1 | Y33: =D33/31*X33 -> 731.90323 | AB33: 1 | AC33: =D33/31*AB33 -> 731.90323
C34: CASUAL LEAVE | D34: 22689 | L34: 2 | M34: =D34/31*L34 -> 1463.8065 | N34: 1 | O34: =D34/31*N34 -> 731.90323
C35: SICK LEAVE | D35: 22689 | L35: 2 | M35: =D35/31*L35 -> 1463.8065 | N35: 1 | O35: =D35/31*N35 -> 731.90323
C36: COMP OFF | D36: 22689
L37: =SUM(L3:L36) -> 31 | M37: =SUM(M3:M36) -> 22689 | N37: =SUM(N3:N36) -> 31 | O37: =SUM(O3:O36) -> 22689 | P37: =SUM(P3:P36) -> 30 | Q37: =SUM(Q3:Q36) -> 22689 | R37: =SUM(R3:R36) -> 31 | S37: =SUM(S3:S36) -> 22689 | ... AC37: =SUM(AC3:AC36) -> 22689

Sheet ASHITHA VINS
A1: Name | B1: Designation | C1: Project | D1: Monthly CTC | E1: Date | F1: 45748 | H1: 45778 | J1: 45809 | L1: 45839 | N1: 45870 | P1: 45901 | R1: 45931 | T1: 45962 | V1: 45992 | X1: 46023 | Z1: 46054 | AB1: 46082
F2: Attendance | G2: Amount | H2: Attendance | I2: Amount | J2: Attendance | K2: Amount | L2: Attendance | M2: Amount | N2: Attendance | O2: Amount | P2: Attendance | Q2: Amount | R2: Attendance | S2: Amount | T2: Attendance | U2: Amount | V2: Attendance | W2: Amount | X2: Attendance | Y2: Amount | Z2: Attendance | AA2: Amount | AB2: Attendance | AC2: Amount
A3: ASHITHA VINS V M | B3: BACKEND SUPPORT | C3: CORE TEAM | D3: 23309 | E3: 1 | L3: 1 | M3: =D3/31*L3 -> 751.90323 | N3: 1 | O3: =D3/31*N3 -> 751.90323 | P3: 1 | Q3: =D3/30*P3 -> 776.96667 | R3: 1 | S3: =D3/31*R3 -> 751.90323 | T3: 1 | U3: =D3/30*T3 -> 776.96667 | V3: 1 | W3: =D3/31*V3 -> 751.90323 | X3: 1 | Y3: =D3/31*X3 -> 751.90323 | Z3: 1 | AA3: =D3/28*Z3 -> 832.46429 | AB3: 1 | AC3: =D3/31*AB3 -> 751.90323
D4: 23309 | E4: 2 | L4: 1 | M4: =D4/31*L4 -> 751.90323 | N4: 1 | O4: =D4/31*N4 -> 751.90323 | P4: 1 | Q4: =D4/30*P4 -> 776.96667 | R4: 1 | S4: =D4/31*R4 -> 751.90323 | T4: 1 | U4: =D4/30*T4 -> 776.96667 | V4: 1 | W4: =D4/31*V4 -> 751.90323 | X4: 1 | Y4: =D4/31*X4 -> 751.90323 | Z4: 1 | AA4: =D4/28*Z4 -> 832.46429 | AB4: 1 | AC4: =D4/31*AB4 -> 751.90323
D5: 23309 | E5: 3 | L5: 0 | M5: =D5/31*L5 -> 0 | N5: 1 | O5: =D5/31*N5 -> 751.90323 | P5: 1 | Q5: =D5/30*P5 -> 776.96667 | R5: 1 | S5: =D5/31*R5 -> 751.90323 | T5: 1 | U5: =D5/30*T5 -> 776.96667 | V5: 1 | W5: =D5/31*V5 -> 751.90323 | X5: 1 | Y5: =D5/31*X5 -> 751.90323 | Z5: 1 | AA5: =D5/28*Z5 -> 832.46429 | AB5: 1 | AC5: =D5/31*AB5 -> 751.90323
D6: 23309 | E6: 4 | L6: 1 | M6: =D6/31*L6 -> 751.90323 | N6: 1 | O6: =D6/31*N6 -> 751.90323 | P6: 1 | Q6: =D6/30*P6 -> 776.96667 | R6: 1 | S6: =D6/31*R6 -> 751.90323 | T6: 1 | U6: =D6/30*T6 -> 776.96667 | V6: 1 | W6: =D6/31*V6 -> 751.90323 | X6: 1 | Y6: =D6/31*X6 -> 751.90323 | Z6: 1 | AA6: =D6/28*Z6 -> 832.46429 | AB6: 1 | AC6: =D6/31*AB6 -> 751.90323
D7: 23309 | E7: 5 | L7: 1 | M7: =D7/31*L7 -> 751.90323 | N7: 1 | O7: =D7/31*N7 -> 751.90323 | P7: 1 | Q7: =D7/30*P7 -> 776.96667 | R7: 1 | S7: =D7/31*R7 -> 751.90323 | T7: 1 | U7: =D7/30*T7 -> 776.96667 | V7: 1 | W7: =D7/31*V7 -> 751.90323 | X7: 1 | Y7: =D7/31*X7 -> 751.90323 | Z7: 1 | AA7: =D7/28*Z7 -> 832.46429 | AB7: 1 | AC7: =D7/31*AB7 -> 751.90323
D8: 23309 | E8: 6 | L8: 1 | M8: =D8/31*L8 -> 751.90323 | N8: 1 | O8: =D8/31*N8 -> 751.90323 | P8: 1 | Q8: =D8/30*P8 -> 776.96667 | R8: 1 | S8: =D8/31*R8 -> 751.90323 | T8: 1 | U8: =D8/30*T8 -> 776.96667 | V8: 1 | W8: =D8/31*V8 -> 751.90323 | X8: 1 | Y8: =D8/31*X8 -> 751.90323 | Z8: 1 | AA8: =D8/28*Z8 -> 832.46429 | AB8: 1 | AC8: =D8/31*AB8 -> 751.90323
D9: 23309 | E9: 7 | L9: 1 | M9: =D9/31*L9 -> 751.90323 | N9: 1 | O9: =D9/31*N9 -> 751.90323 | P9: 1 | Q9: =D9/30*P9 -> 776.96667 | R9: 1 | S9: =D9/31*R9 -> 751.90323 | T9: 1 | U9: =D9/30*T9 -> 776.96667 | V9: 1 | W9: =D9/31*V9 -> 751.90323 | X9: 1 | Y9: =D9/31*X9 -> 751.90323 | Z9: 1 | AA9: =D9/28*Z9 -> 832.46429 | AB9: 1 | AC9: =D9/31*AB9 -> 751.90323
D10: 23309 | E10: 8 | L10: 1 | M10: =D10/31*L10 -> 751.90323 | N10: 0 | O10: =D10/31*N10 -> 0 | P10: 1 | Q10: =D10/30*P10 -> 776.96667 | R10: 1 | S10: =D10/31*R10 -> 751.90323 | T10: 1 | U10: =D10/30*T10 -> 776.96667 | V10: 1 | W10: =D10/31*V10 -> 751.90323 | X10: 1 | Y10: =D10/31*X10 -> 751.90323 | Z10: 1 | AA10: =D10/28*Z10 -> 832.46429 | AB10: 1 | AC10: =D10/31*AB10 -> 751.90323
D11: 23309 | E11: 9 | L11: 0 | M11: =D11/31*L11 -> 0 | N11: 1 | O11: =D11/31*N11 -> 751.90323 | P11: 1 | Q11: =D11/30*P11 -> 776.96667 | R11: 1 | S11: =D11/31*R11 -> 751.90323 | T11: 1 | U11: =D11/30*T11 -> 776.96667 | V11: 1 | W11: =D11/31*V11 -> 751.90323 | X11: 1 | Y11: =D11/31*X11 -> 751.90323 | Z11: 1 | AA11: =D11/28*Z11 -> 832.46429 | AB11: 1 | AC11: =D11/31*AB11 -> 751.90323
D12: 23309 | E12: 10 | L12: 1 | M12: =D12/31*L12 -> 751.90323 | N12: 1 | O12: =D12/31*N12 -> 751.90323 | P12: 1 | Q12: =D12/30*P12 -> 776.96667 | R12: 1 | S12: =D12/31*R12 -> 751.90323 | T12: 1 | U12: =D12/30*T12 -> 776.96667 | V12: 1 | W12: =D12/31*V12 -> 751.90323 | X12: 1 | Y12: =D12/31*X12 -> 751.90323 | Z12: 1 | AA12: =D12/28*Z12 -> 832.46429 | AB12: 1 | AC12: =D12/31*AB12 -> 751.90323
D13: 23309 | E13: 11 | L13: 1 | M13: =D13/31*L13 -> 751.90323 | N13: 0 | O13: =D13/31*N13 -> 0 | P13: 1 | Q13: =D13/30*P13 -> 776.96667 | R13: 1 | S13: =D13/31*R13 -> 751.90323 | T13: 1 | U13: =D13/30*T13 -> 776.96667 | V13: 1 | W13: =D13/31*V13 -> 751.90323 | X13: 1 | Y13: =D13/31*X13 -> 751.90323 | Z13: 1 | AA13: =D13/28*Z13 -> 832.46429 | AB13: 1 | AC13: =D13/31*AB13 -> 751.90323
D14: 23309 | E14: 12 | L14: 1 | M14: =D14/31*L14 -> 751.90323 | N14: 0 | O14: =D14/31*N14 -> 0 | P14: 1 | Q14: =D14/30*P14 -> 776.96667 | R14: 1 | S14: =D14/31*R14 -> 751.90323 | T14: 1 | U14: =D14/30*T14 -> 776.96667 | V14: 1 | W14: =D14/31*V14 -> 751.90323 | X14: 1 | Y14: =D14/31*X14 -> 751.90323 | Z14: 1 | AA14: =D14/28*Z14 -> 832.46429 | AB14: 1 | AC14: =D14/31*AB14 -> 751.90323
D15: 23309 | E15: 13 | L15: 1 | M15: =D15/31*L15 -> 751.90323 | N15: 1 | O15: =D15/31*N15 -> 751.90323 | P15: 1 | Q15: =D15/30*P15 -> 776.96667 | R15: 1 | S15: =D15/31*R15 -> 751.90323 | T15: 1 | U15: =D15/30*T15 -> 776.96667 | V15: 1 | W15: =D15/31*V15 -> 751.90323 | X15: 1 | Y15: =D15/31*X15 -> 751.90323 | Z15: 1 | AA15: =D15/28*Z15 -> 832.46429 | AB15: 1 | AC15: =D15/31*AB15 -> 751.90323
... D30: 23309 | E30: 28 | L30: 1 | M30: =D30/31*L30 -> 751.90323 | N30: 1 | O30: =D30/31*N30 -> 751.90323 | P30: 1 | Q30: =D30/30*P30 -> 776.96667 | R30: 1 | S30: =D30/31*R30 -> 751.90323 | T30: 1 | U30: =D30/30*T30 -> 776.96667 | V30: 1 | W30: =D30/31*V30 -> 751.90323 | X30: 1 | Y30: =D30/31*X30 -> 751.90323 | Z30: 1 | AA30: =D30/28*Z30 -> 832.46429 | AB30: 1 | AC30: =D30/31*AB30 -> 751.90323
D31: 23309 | E31: 29 | L31: 1 | M31: =D31/31*L31 -> 751.90323 | N31: 1 | O31: =D31/31*N31 -> 751.90323 | P31: 0 | Q31: =D31/30*P31 -> 0 | R31: 1 | S31: =D31/31*R31 -> 751.90323 | T31: 1 | U31: =D31/30*T31 -> 776.96667 | V31: 1 | W31: =D31/31*V31 -> 751.90323 | X31: 1 | Y31: =D31/31*X31 -> 751.90323 | AB31: 1 | AC31: =D31/31*AB31 -> 751.90323
D32: 23309 | E32: 30 | L32: 1 | M32: =D32/31*L32 -> 751.90323 | N32: 1 | O32: =D32/31*N32 -> 751.90323 | P32: 0 | Q32: =D32/30*P32 -> 0 | R32: 1 | S32: =D32/31*R32 -> 751.90323 | T32: 1 | U32: =D32/30*T32 -> 776.96667 | V32: 1 | W32: =D32/31*V32 -> 751.90323 | X32: 1 | Y32: =D32/31*X32 -> 751.90323 | AB32: 1 | AC32: =D32/31*AB32 -> 751.90323
D33: 23309 | E33: 31 | L33: 1 | M33: =D33/31*L33 -> 751.90323 | N33: 1 | O33: =D33/31*N33 -> 751.90323 | R33: 1 | S33: =D33/31*R33 -> 751.90323 | V33: 1 | W33: =D33/31*V33 -> 751.90323 | X33: 1 | Y33: =D33/31*X33 -> 751.90323 | AB33: 1 | AC33: =D33/31*AB33 -> 751.90323
C34: CASUAL LEAVE | D34: 23309 | L34: 1 | M34: =D34/31*L34 -> 751.90323 | N34: 1 | O34: =D34/31*N34 -> 751.90323
C35: SICK LEAVE | D35: 23309 | L35: 2 | M35: =D35/31*L35 -> 1503.8065 | N35: 1 | O35: =D35/31*N35 -> 751.90323
C36: COMP OFF | D36: 23309
L37: =SUM(L3:L36) -> 31 | M37: =SUM(M3:M36) -> 23309 | N37: =SUM(N3:N36) -> 28 | O37: =SUM(O3:O36) -> 21053.29 | P37: =SUM(P3:P36) -> 27 | Q37: =SUM(Q3:Q36) -> 20978.1 | R37: =SUM(R3:R36) -> 31 | S37: =SUM(S3:S36) -> 23309 | ... AC37: =SUM(AC3:AC36) -> 23309

Sheet SAVITHA Y
A1: Name | B1: Designation | C1: Project | D1: Monthly CTC | E1: Date | F1: 45748 | H1: 45778 | J1: 45809 | L1: 45839 | N1: 45870 | P1: 45901 | R1: 45931 | T1: 45962 | V1: 45992 | X1: 46023 | Z1: 46054 | AB1: 46082
F2: Attendance | G2: Amount | H2: Attendance | I2: Amount | J2: Attendance | K2: Amount | L2: Attendance | M2: Amount | N2: Attendance | O2: Amount | P2: Attendance | Q2: Amount | R2: Attendance | S2: Amount | T2: Attendance | U2: Amount | V2: Attendance | W2: Amount | X2: Attendance | Y2: Amount | Z2: Attendance | AA2: Amount | AB2: Attendance | AC2: Amount
A3: SAVITHA Y | B3: BACKEND SUPPORT | C3: CORE TEAM | D3: 23309 | E3: 1 | L3: 0 | M3: =D3/31*L3 -> 0 | N3: 1 | O3: =D3/31*N3 -> 751.90323 | P3: 1 | Q3: =D3/30*P3 -> 776.96667 | R3: 1 | S3: =D3/31*R3 -> 751.90323 | T3: 1 | U3: =D3/30*T3 -> 776.96667 | V3: 1 | W3: =D3/31*V3 -> 751.90323 | X3: 1 | Y3: =D3/31*X3 -> 751.90323 | Z3: 1 | AA3: =D3/28*Z3 -> 832.46429 | AB3: 1 | AC3: =D3/31*AB3 -> 751.90323
D4: 23309 | E4: 2 | L4: 0 | M4: =D4/31*L4 -> 0 | N4: 1 | O4: =D4/31*N4 -> 751.90323 | P4: 1 | Q4: =D4/30*P4 -> 776.96667 | R4: 1 | S4: =D4/31*R4 -> 751.90323 | T4: 1 | U4: =D4/30*T4 -> 776.96667 | V4: 1 | W4: =D4/31*V4 -> 751.90323 | X4: 1 | Y4: =D4/31*X4 -> 751.90323 | Z4: 1 | AA4: =D4/28*Z4 -> 832.46429 | AB4: 1 | AC4: =D4/31*AB4 -> 751.90323
D5: 23309 | E5: 3 | L5: 1 | M5: =D5/31*L5 -> 751.90323 | N5: 1 | O5: =D5/31*N5 -> 751.90323 | P5: 1 | Q5: =D5/30*P5 -> 776.96667 | R5: 1 | S5: =D5/31*R5 -> 751.90323 | T5: 1 | U5: =D5/30*T5 -> 776.96667 | V5: 1 | W5: =D5/31*V5 -> 751.90323 | X5: 1 | Y5: =D5/31*X5 -> 751.90323 | Z5: 1 | AA5: =D5/28*Z5 -> 832.46429 | AB5: 1 | AC5: =D5/31*AB5 -> 751.90323
D6: 23309 | E6: 4 | L6: 1 | M6: =D6/31*L6 -> 751.90323 | N6: 1 | O6: =D6/31*N6 -> 751.90323 | P6: 1 | Q6: =D6/30*P6 -> 776.96667 | R6: 1 | S6: =D6/31*R6 -> 751.90323 | T6: 1 | U6: =D6/30*T6 -> 776.96667 | V6: 1 | W6: =D6/31*V6 -> 751.90323 | X6: 1 | Y6: =D6/31*X6 -> 751.90323 | Z6: 1 | AA6: =D6/28*Z6 -> 832.46429 | AB6: 1 | AC6: =D6/31*AB6 -> 751.90323
D7: 23309 | E7: 5 | L7: 1 | M7: =D7/31*L7 -> 751.90323 | N7: 1 | O7: =D7/31*N7 -> 751.90323 | P7: 1 | Q7: =D7/30*P7 -> 776.96667 | R7: 1 | S7: =D7/31*R7 -> 751.90323 | T7: 1 | U7: =D7/30*T7 -> 776.96667 | V7: 1 | W7: =D7/31*V7 -> 751.90323 | X7: 1 | Y7: =D7/31*X7 -> 751.90323 | Z7: 1 | AA7: =D7/28*Z7 -> 832.46429 | AB7: 1 | AC7: =D7/31*AB7 -> 751.90323
D8: 23309 | E8: 6 | L8: 1 | M8: =D8/31*L8 -> 751.90323 | N8: 1 | O8: =D8/31*N8 -> 751.90323 | P8: 1 | Q8: =D8/30*P8 -> 776.96667 | R8: 1 | S8: =D8/31*R8 -> 751.90323 | T8: 1 | U8: =D8/30*T8 -> 776.96667 | V8: 1 | W8: =D8/31*V8 -> 751.90323 | X8: 1 | Y8: =D8/31*X8 -> 751.90323 | Z8: 1 | AA8: =D8/28*Z8 -> 832.46429 | AB8: 1 | AC8: =D8/31*AB8 -> 751.90323
D9: 23309 | E9: 7 | L9: 1 | M9: =D9/31*L9 -> 751.90323 | N9: 1 | O9: =D9/31*N9 -> 751.90323 | P9: 1 | Q9: =D9/30*P9 -> 776.96667 | R9: 1 | S9: =D9/31*R9 -> 751.90323 | T9: 1 | U9: =D9/30*T9 -> 776.96667 | V9: 1 | W9: =D9/31*V9 -> 751.90323 | X9: 1 | Y9: =D9/31*X9 -> 751.90323 | Z9: 1 | AA9: =D9/28*Z9 -> 832.46429 | AB9: 1 | AC9: =D9/31*AB9 -> 751.90323
D10: 23309 | E10: 8 | L10: 1 | M10: =D10/31*L10 -> 751.90323 | N10: 1 | O10: =D10/31*N10 -> 751.90323 | P10: 0 | Q10: =D10/30*P10 -> 0 | R10: 1 | S10: =D10/31*R10 -> 751.90323 | T10: 1 | U10: =D10/30*T10 -> 776.96667 | V10: 1 | W10: =D10/31*V10 -> 751.90323 | X10: 1 | Y10: =D10/31*X10 -> 751.90323 | Z10: 1 | AA10: =D10/28*Z10 -> 832.46429 | AB10: 1 | AC10: =D10/31*AB10 -> 751.90323
D11: 23309 | E11: 9 | L11: 1 | M11: =D11/31*L11 -> 751.90323 | N11: 1 | O11: =D11/31*N11 -> 751.90323 | P11: 1 | Q11: =D11/30*P11 -> 776.96667 | R11: 1 | S11: =D11/31*R11 -> 751.90323 | T11: 1 | U11: =D11/30*T11 -> 776.96667 | V11: 1 | W11: =D11/31*V11 -> 751.90323 | X11: 1 | Y11: =D11/31*X11 -> 751.90323 | Z11: 1 | AA11: =D11/28*Z11 -> 832.46429 | AB11: 1 | AC11: =D11/31*AB11 -> 751.90323
D12: 23309 | E12: 10 | L12: 1 | M12: =D12/31*L12 -> 751.90323 | N12: 1 | O12: =D12/31*N12 -> 751.90323 | P12: 1 | Q12: =D12/30*P12 -> 776.96667 | R12: 1 | S12: =D12/31*R12 -> 751.90323 | T12: 1 | U12: =D12/30*T12 -> 776.96667 | V12: 1 | W12: =D12/31*V12 -> 751.90323 | X12: 1 | Y12: =D12/31*X12 -> 751.90323 | Z12: 1 | AA12: =D12/28*Z12 -> 832.46429 | AB12: 1 | AC12: =D12/31*AB12 -> 751.90323
D13: 23309 | E13: 11 | L13: 1 | M13: =D13/31*L13 -> 751.90323 | N13: 1 | O13: =D13/31*N13 -> 751.90323 | P13: 1 | Q13: =D13/30*P13 -> 776.96667 | R13: 1 | S13: =D13/31*R13 -> 751.90323 | T13: 1 | U13: =D13/30*T13 -> 776.96667 | V13: 1 | W13: =D13/31*V13 -> 751.90323 | X13: 1 | Y13: =D13/31*X13 -> 751.90323 | Z13: 1 | AA13: =D13/28*Z13 -> 832.46429 | AB13: 1 | AC13: =D13/31*AB13 -> 751.90323
D14: 23309 | E14: 12 | L14: 1 | M14: =D14/31*L14 -> 751.90323 | N14: 1 | O14: =D14/31*N14 -> 751.90323 | P14: 1 | Q14: =D14/30*P14 -> 776.96667 | R14: 1 | S14: =D14/31*R14 -> 751.90323 | T14: 1 | U14: =D14/30*T14 -> 776.96667 | V14: 1 | W14: =D14/31*V14 -> 751.90323 | X14: 1 | Y14: =D14/31*X14 -> 751.90323 | Z14: 1 | AA14: =D14/28*Z14 -> 832.46429 | AB14: 1 | AC14: =D14/31*AB14 -> 751.90323
D15: 23309 | E15: 13 | L15: 1 | M15: =D15/31*L15 -> 751.90323 | N15: 1 | O15: =D15/31*N15 -> 751.90323 | P15: 1 | Q15: =D15/30*P15 -> 776.96667 | R15: 0 | S15: =D15/31*R15 -> 0 | T15: 1 | U15: =D15/30*T15 -> 776.96667 | V15: 1 | W15: =D15/31*V15 -> 751.90323 | X15: 1 | Y15: =D15/31*X15 -> 751.90323 | Z15: 1 | AA15: =D15/28*Z15 -> 832.46429 | AB15: 1 | AC15: =D15/31*AB15 -> 751.90323
... D30: 23309 | E30: 28 | L30: 1 | M30: =D30/31*L30 -> 751.90323 | N30: 0 | O30: =D30/31*N30 -> 0 | P30: 1 | Q30: =D30/30*P30 -> 776.96667 | R30: 1 | S30: =D30/31*R30 -> 751.90323 | T30: 1 | U30: =D30/30*T30 -> 776.96667 | V30: 1 | W30: =D30/31*V30 -> 751.90323 | X30: 1 | Y30: =D30/31*X30 -> 751.90323 | Z30: 1 | AA30: =D30/28*Z30 -> 832.46429 | AB30: 1 | AC30: =D30/31*AB30 -> 751.90323
D31: 23309 | E31: 29 | L31: 0 | M31: =D31/31*L31 -> 0 | N31: 1 | O31: =D31/31*N31 -> 751.90323 | P31: 1 | Q31: =D31/30*P31 -> 776.96667 | R31: 1 | S31: =D31/31*R31 -> 751.90323 | T31: 1 | U31: =D31/30*T31 -> 776.96667 | V31: 1 | W31: =D31/31*V31 -> 751.90323 | X31: 1 | Y31: =D31/31*X31 -> 751.90323 | AB31: 1 | AC31: =D31/31*AB31 -> 751.90323
D32: 23309 | E32: 30 | L32: 1 | M32: =D32/31*L32 -> 751.90323 | N32: 1 | O32: =D32/31*N32 -> 751.90323 | P32: 1 | Q32: =D32/30*P32 -> 776.96667 | R32: 1 | S32: =D32/31*R32 -> 751.90323 | T32: 1 | U32: =D32/30*T32 -> 776.96667 | V32: 1 | W32: =D32/31*V32 -> 751.90323 | X32: 1 | Y32: =D32/31*X32 -> 751.90323 | AB32: 1 | AC32: =D32/31*AB32 -> 751.90323
D33: 23309 | E33: 31 | L33: 1 | M33: =D33/31*L33 -> 751.90323 | N33: 1 | O33: =D33/31*N33 -> 751.90323 | R33: 1 | S33: =D33/31*R33 -> 751.90323 | V33: 1 | W33: =D33/31*V33 -> 751.90323 | X33: 1 | Y33: =D33/31*X33 -> 751.90323 | AB33: 1 | AC33: =D33/31*AB33 -> 751.90323
C34: CASUAL LEAVE | D34: 23309 | L34: 1 | M34: =D34/31*L34 -> 751.90323 | N34: 1 | O34: =D34/31*N34 -> 751.90323
C35: SICK LEAVE | D35: 23309 | L35: 1 | M35: =D35/31*L35 -> 751.90323 | O35: =D35/31*N35 -> 0
C36: COMP OFF | D36: 23309
L37: =SUM(L3:L36) -> 30 | M37: =SUM(M3:M36) -> 22557.097 | N37: =SUM(N3:N36) -> 31 | O37: =SUM(O3:O36) -> 23309 | P37: =SUM(P3:P36) -> 28 | Q37: =SUM(Q3:Q36) -> 21755.067 | R37: =SUM(R3:R36) -> 29.5 | S37: =SUM(S3:S36) -> 22181.145 | ... AC37: =SUM(AC3:AC36) -> 23309

Sheet SILPA P L
A1: Name | B1: Designation | C1: Project | D1: Monthly CTC | E1: Date | F1: 45748 | H1: 45778 | J1: 45809 | L1: 45839 | N1: 45870 | P1: 45901 | R1: 45931 | T1: 45962 | V1: 45992 | X1: 46023 | Z1: 46054 | AB1: 46082
F2: Attendance | G2: Amount | H2: Attendance | I2: Amount | J2: Attendance | K2: Amount | L2: Attendance | M2: Amount | N2: Attendance | O2: Amount | P2: Attendance | Q2: Amount | R2: Attendance | S2: Amount | T2: Attendance | U2: Amount | V2: Attendance | W2: Amount | X2: Attendance | Y2: Amount | Z2: Attendance | AA2: Amount | AB2: Attendance | AC2: Amount
